Workbook

Sheet Scoring
A1: Pattern | B1: Model | C1: Response Predicted | D1: Response Unpredicted | E1: LM Non-Responsive | F1: Noise in Output | G1: No Noise in Output | H1: Response Predicted | I1: Response Unpredicted | J1: LM Non-Responsive | K1: Noise in Output | L1: No Noise in Output | M1: Count of Prompts
A2: Simple untuned | B2: claude-sonnet-4-6 | C2: =COUNTIF('Simple untuned'!$W:$W,"expected") -> 122 | D2: =COUNTIF('Simple untuned'!$W:$W,"unexpected") -> 19 | E2: =COUNTIF('Simple untuned'!$W:$W,"confused") -> 14 | F2: =COUNTIF('Simple untuned'!$X:$X,"yes") -> 112 | G2: =COUNTIF('Simple untuned'!$X:$X,"no") -> 43 | H2: =COUNTIF('Simple untuned'!$W:$W,"expected")/(COUNTA('Simple untuned'!$V:$V)-1) -> 0.78709677 | I2: =COUNTIF('Simple untuned'!W:W,"unexpected")/(COUNTA('Simple untuned'!$V:$V)-1) -> 0.12258065 | J2: =COUNTIF('Simple untuned'!W:W,"confused")/(COUNTA('Simple untuned'!$V:$V)-1) -> 0.090322581 | K2: =COUNTIF('Simple untuned'!X:X,"yes")/(COUNTA('Simple untuned'!$V:$V)-1) -> 0.72258065 | L2: =COUNTIF('Simple untuned'!X:X,"no")/(COUNTA('Simple untuned'!$V:$V)-1) -> 0.27741935 | M2: =C2+D2+E2 -> 155
A3: Simple untuned | B3: claude-sonnet-4-5-20250929 | C3: =COUNTIF('Simple untuned'!$Q:$Q,"expected") -> 135 | D3: =COUNTIF('Simple untuned'!$Q:$Q,"unexpected") -> 14 | E3: =COUNTIF('Simple untuned'!$Q:$Q,"confused") -> 6 | F3: =COUNTIF('Simple untuned'!$R:$R,"yes") -> 127 | G3: =COUNTIF('Simple untuned'!$R:$R,"no") -> 28 | H3: =COUNTIF('Simple untuned'!$Q:$Q,"expected")/(COUNTA('Simple untuned'!$P:$P)-1) -> 0.87096774 | I3: =COUNTIF('Simple untuned'!Q:Q,"unexpected")/(COUNTA('Simple untuned'!$P:$P)-1) -> 0.090322581 | J3: =COUNTIF('Simple untuned'!Q:Q,"confused")/(COUNTA('Simple untuned'!$P:$P)-1) -> 0.038709677 | K3: =COUNTIF('Simple untuned'!R:R,"yes")/(COUNTA('Simple untuned'!$P:$P)-1) -> 0.81935484 | L3: =COUNTIF('Simple untuned'!R:R,"no")/(COUNTA('Simple untuned'!$P:$P)-1) -> 0.18064516 | M3: =C3+D3+E3 -> 155
A4: Simple untuned | B4: claude-sonnet-4-20250514 | C4: =COUNTIF('Simple untuned'!$K:$K,"expected") -> 134 | D4: =COUNTIF('Simple untuned'!$K:$K,"unexpected") -> 16 | E4: =COUNTIF('Simple untuned'!$K:$K,"confused") -> 5 | F4: =COUNTIF('Simple untuned'!$L:$L,"yes") -> 146 | G4: =COUNTIF('Simple untuned'!$L:$L,"no") -> 9 | H4: =COUNTIF('Simple untuned'!$K:$K,"expected")/(COUNTA('Simple untuned'!$K:$K)-1) -> 0.86451613 | I4: =COUNTIF('Simple untuned'!K:K,"unexpected")/(COUNTA('Simple untuned'!$K:$K)-1) -> 0.10322581 | J4: =COUNTIF('Simple untuned'!K:K,"confused")/(COUNTA('Simple untuned'!$K:$K)-1) -> 0.032258065 | K4: =COUNTIF('Simple untuned'!L:L,"yes")/(COUNTA('Simple untuned'!$K:$K)-1) -> 0.94193548 | L4: =COUNTIF('Simple untuned'!L:L,"no")/(COUNTA('Simple untuned'!$K:$K)-1) -> 0.058064516 | M4: =C4+D4+E4 -> 155
A5: Simple untuned | B5: gpt-5.4 | C5: =COUNTIF('Simple untuned'!$T:$T,"expected") -> 129 | D5: =COUNTIF('Simple untuned'!$T:$T,"unexpected") -> 11 | E5: =COUNTIF('Simple untuned'!$T:$T,"confused") -> 15 | F5: =COUNTIF('Simple untuned'!$U:$U,"yes") -> 11 | G5: =COUNTIF('Simple untuned'!$U:$U,"no") -> 144 | H5: =COUNTIF('Simple untuned'!$T:$T,"expected")/(COUNTA('Simple untuned'!$T:$T)-1) -> 0.83225806 | I5: =COUNTIF('Simple untuned'!T:T,"unexpected")/(COUNTA('Simple untuned'!$T:$T)-1) -> 0.070967742 | J5: =COUNTIF('Simple untuned'!T:T,"confused")/(COUNTA('Simple untuned'!$T:$T)-1) -> 0.096774194 | K5: =COUNTIF('Simple untuned'!U:U,"yes")/(COUNTA('Simple untuned'!$U:$U)-1) -> 0.070967742 | L5: =COUNTIF('Simple untuned'!U:U,"no")/(COUNTA('Simple untuned'!$U:$U)-1) -> 0.92903226 | M5: =C5+D5+E5 -> 155
A6: Simple untuned | B6: gpt-5 | C6: =COUNTIF('Simple untuned'!$N:$N,"expected") -> 128 | D6: =COUNTIF('Simple untuned'!$N:$N,"unexpected") -> 27 | E6: =COUNTIF('Simple untuned'!$N:$N,"confused") -> 0 | F6: =COUNTIF('Simple untuned'!$O:$O,"yes") -> 0 | G6: =COUNTIF('Simple untuned'!$O:$O,"no") -> 155 | H6: =COUNTIF('Simple untuned'!$N:$N,"expected")/(COUNTA('Simple untuned'!$M:$M)-1) -> 0.82580645 | I6: =COUNTIF('Simple untuned'!N:N,"unexpected")/(COUNTA('Simple untuned'!$M:$M)-1) -> 0.17419355 | J6: =COUNTIF('Simple untuned'!N:N,"confused")/(COUNTA('Simple untuned'!$M:$M)-1) -> 0 | K6: =COUNTIF('Simple untuned'!O:O,"yes")/(COUNTA('Simple untuned'!$M:$M)-1) -> 0 | L6: =COUNTIF('Simple untuned'!O:O,"no")/(COUNTA('Simple untuned'!$M:$M)-1) -> 1 | M6: =C6+D6+E6 -> 155
A7: Simple untuned | B7: gpt-4.1 | C7: =COUNTIF('Simple untuned'!$H:$H,"expected") -> 134 | D7: =COUNTIF('Simple untuned'!$H:$H,"unexpected") -> 18 | E7: =COUNTIF('Simple untuned'!$H:$H,"confused") -> 3 | F7: =COUNTIF('Simple untuned'!$I:$I,"yes") -> 87 | G7: =COUNTIF('Simple untuned'!$I:$I,"no") -> 68 | H7: =COUNTIF('Simple untuned'!$H:$H,"expected")/(COUNTA('Simple untuned'!$H:$H)-1) -> 0.86451613 | I7: =COUNTIF('Simple untuned'!H:H,"unexpected")/(COUNTA('Simple untuned'!$H:$H)-1) -> 0.11612903 | J7: =COUNTIF('Simple untuned'!H:H,"confused")/(COUNTA('Simple untuned'!$H:$H)-1) -> 0.019354839 | K7: =COUNTIF('Simple untuned'!I:I,"yes")/(COUNTA('Simple untuned'!$H:$H)-1) -> 0.56129032 | L7: =COUNTIF('Simple untuned'!I:I,"no")/(COUNTA('Simple untuned'!$H:$H)-1) -> 0.43870968 | M7: =C7+D7+E7 -> 155
A9: Complex untuned | B9: claude-sonnet-4-6 | C9: =COUNTIF('Comple untuned'!$W:$W,"expected") -> 102 | D9: =COUNTIF('Comple untuned'!$W:$W,"unexpected") -> 36 | E9: =COUNTIF('Comple untuned'!$W:$W,"confused") -> 7 | F9: =COUNTIF('Comple untuned'!$X:$X,"yes") -> 139 | G9: =COUNTIF('Comple untuned'!$X:$X,"no") -> 6 | H9: =COUNTIF('Comple untuned'!$W:$W,"expected")/(COUNTA('Comple untuned'!$V:$V)-1) -> 0.70344828 | I9: =COUNTIF('Comple untuned'!W:W,"unexpected")/(COUNTA('Comple untuned'!$V:$V)-1) -> 0.24827586 | J9: =COUNTIF('Comple untuned'!W:W,"confused")/(COUNTA('Comple untuned'!$V:$V)-1) -> 0.048275862 | K9: =COUNTIF('Comple untuned'!X:X,"yes")/(COUNTA('Comple untuned'!$V:$V)-1) -> 0.95862069 | L9: =COUNTIF('Comple untuned'!X:X,"no")/(COUNTA('Comple untuned'!$V:$V)-1) -> 0.04137931 | M9: =C9+D9+E9 -> 145
A10: Complex untuned | B10: claude-sonnet-4-5-20250929 | C10: =COUNTIF('Comple untuned'!$Q:$Q,"expected") -> 105 | D10: =COUNTIF('Comple untuned'!$Q:$Q,"unexpected") -> 36 | E10: =COUNTIF('Comple untuned'!$Q:$Q,"confused") -> 4 | F10: =COUNTIF('Comple untuned'!$R:$R,"yes") -> 59 | G10: =COUNTIF('Comple untuned'!$R:$R,"no") -> 20 | H10: =COUNTIF('Comple untuned'!$Q:$Q,"expected")/(COUNTA('Comple untuned'!$P:$P)-1) -> 0.72413793 | I10: =COUNTIF('Comple untuned'!Q:Q,"unexpected")/(COUNTA('Comple untuned'!$P:$P)-1) -> 0.24827586 | J10: =COUNTIF('Comple untuned'!Q:Q,"confused")/(COUNTA('Comple untuned'!$P:$P)-1) -> 0.027586207 | K10: =COUNTIF('Comple untuned'!R:R,"yes")/(COUNTA('Comple untuned'!$P:$P)-1) -> 0.40689655 | L10: =COUNTIF('Comple untuned'!R:R,"no")/(COUNTA('Comple untuned'!$P:$P)-1) -> 0.13793103 | M10: =C10+D10+E10 -> 145
A11: Complex untuned | B11: claude-sonnet-4-20250514 | C11: =COUNTIF('Comple untuned'!$K:$K,"expected") -> 99 | D11: =COUNTIF('Comple untuned'!$K:$K,"unexpected") -> 38 | E11: =COUNTIF('Comple untuned'!$K:$K,"confused") -> 8 | F11: =COUNTIF('Comple untuned'!$L:$L,"yes") -> 145 | G11: =COUNTIF('Comple untuned'!$L:$L,"no") -> 0 | H11: =COUNTIF('Comple untuned'!$K:$K,"expected")/(COUNTA('Comple untuned'!$J:$J)-1) -> 0.68275862 | I11: =COUNTIF('Comple untuned'!K:K,"unexpected")/(COUNTA('Comple untuned'!$J:$J)-1) -> 0.26206897 | J11: =COUNTIF('Comple untuned'!K:K,"confused")/(COUNTA('Comple untuned'!$J:$J)-1) -> 0.055172414 | K11: =COUNTIF('Comple untuned'!L:L,"yes")/(COUNTA('Comple untuned'!$J:$J)-1) -> 1 | L11: =COUNTIF('Comple untuned'!L:L,"no")/(COUNTA('Comple untuned'!$J:$J)-1) -> 0 | M11: =C11+D11+E11 -> 145
A12: Complex untuned | B12: gpt-5.4 | C12: =COUNTIF('Comple untuned'!$T:$T,"expected") -> 91 | D12: =COUNTIF('Comple untuned'!$T:$T,"unexpected") -> 20 | E12: =COUNTIF('Comple untuned'!$T:$T,"confused") -> 34 | F12: =COUNTIF('Comple untuned'!$U:$U,"yes") -> 33 | G12: =COUNTIF('Comple untuned'!$U:$U,"no") -> 112 | H12: =COUNTIF('Comple untuned'!$T:$T,"expected")/(COUNTA('Comple untuned'!$S:$S)-1) -> 0.62758621 | I12: =COUNTIF('Comple untuned'!T:T,"unexpected")/(COUNTA('Comple untuned'!$S:$S)-1) -> 0.13793103 | J12: =COUNTIF('Comple untuned'!T:T,"confused")/(COUNTA('Comple untuned'!$S:$S)-1) -> 0.23448276 | K12: =COUNTIF('Comple untuned'!U:U,"yes")/(COUNTA('Comple untuned'!$S:$S)-1) -> 0.22758621 | L12: =COUNTIF('Comple untuned'!U:U,"no")/(COUNTA('Comple untuned'!$S:$S)-1) -> 0.77241379 | M12: =C12+D12+E12 -> 145
A13: Complex untuned | B13: gpt-5 | C13: =COUNTIF('Comple untuned'!$N:$N,"expected") -> 126 | D13: =COUNTIF('Comple untuned'!$N:$N,"unexpected") -> 16 | E13: =COUNTIF('Comple untuned'!$N:$N,"confused") -> 3 | F13: =COUNTIF('Comple untuned'!$O:$O,"yes") -> 1 | G13: =COUNTIF('Comple untuned'!$O:$O,"no") -> 144 | H13: =COUNTIF('Comple untuned'!$N:$N,"expected")/(COUNTA('Comple untuned'!$M:$M)-1) -> 0.86896552 | I13: =COUNTIF('Comple untuned'!N:N,"unexpected")/(COUNTA('Comple untuned'!$M:$M)-1) -> 0.11034483 | J13: =COUNTIF('Comple untuned'!N:N,"confused")/(COUNTA('Comple untuned'!$M:$M)-1) -> 0.020689655 | K13: =COUNTIF('Comple untuned'!O:O,"yes")/(COUNTA('Comple untuned'!$M:$M)-1) -> 0.0068965517 | L13: =COUNTIF('Comple untuned'!O:O,"no")/(COUNTA('Comple untuned'!$M:$M)-1) -> 0.99310345 | M13: =C13+D13+E13 -> 145
A14: Complex untuned | B14: gpt-4.1 | C14: =COUNTIF('Comple untuned'!$H:$H,"expected") -> 106 | D14: =COUNTIF('Comple untuned'!$H:$H,"unexpected") -> 39 | E14: =COUNTIF('Comple untuned'!$H:$H,"confused") -> 0 | F14: =COUNTIF('Comple untuned'!$I:$I,"yes") -> 145 | G14: =COUNTIF('Comple untuned'!$I:$I,"no") -> 0 | H14: =COUNTIF('Comple untuned'!$H:$H,"expected")/(COUNTA('Comple untuned'!$G:$G)-1) -> 0.73103448 | I14: =COUNTIF('Comple untuned'!H:H,"unexpected")/(COUNTA('Comple untuned'!$G:$G)-1) -> 0.26896552 | J14: =COUNTIF('Comple untuned'!H:H,"confused")/(COUNTA('Comple untuned'!$G:$G)-1) -> 0 | K14: =COUNTIF('Comple untuned'!I:I,"yes")/(COUNTA('Comple untuned'!$G:$G)-1) -> 1 | L14: =COUNTIF('Comple untuned'!I:I,"no")/(COUNTA('Comple untuned'!$G:$G)-1) -> 0 | M14: =C14+D14+E14 -> 145
A16: Simple (tuned) | B16: claude-sonnet-4-6 | C16: =COUNTIF(Simple!$W:$W,"expected") -> 125 | D16: =COUNTIF(Simple!$W:$W,"unexpected") -> 30 | E16: =COUNTIF(Simple!$W:$W,"confused") -> 0 | F16: =COUNTIF(Simple!$X:$X,"yes") -> 8 | G16: =COUNTIF(Simple!$X:$X,"no") -> 147 | H16: =COUNTIF(Simple!$W:$W,"expected")/(COUNTA(Simple!$W:$W)-1) -> 0.80645161 | I16: =COUNTIF(Simple!W:W,"unexpected")/(COUNTA(Simple!$W:$W)-1) -> 0.19354839 | J16: =COUNTIF(Simple!W:W,"confused")/(COUNTA(Simple!$W:$W)-1) -> 0 | K16: =COUNTIF(Simple!X:X,"yes")/(COUNTA(Simple!$W:$W)-1) -> 0.051612903 | L16: =COUNTIF(Simple!X:X,"no")/(COUNTA(Simple!$W:$W)-1) -> 0.9483871 | M16: =C16+D16+E16 -> 155
A17: Simple (tuned) | B17: claude-sonnet-4-5-20250929 | C17: =COUNTIF(Simple!$Q:$Q,"expected") -> 109 | D17: =COUNTIF(Simple!$Q:$Q,"unexpected") -> 24 | E17: =COUNTIF(Simple!$Q:$Q,"confused") -> 22 | F17: =COUNTIF(Simple!$R:$R,"yes") -> 0 | G17: =COUNTIF(Simple!$R:$R,"no") -> 155 | H17: =COUNTIF(Simple!$Q:$Q,"expected")/(COUNTA(Simple!$Q:$Q)-1) -> 0.70322581 | I17: =COUNTIF(Simple!Q:Q,"unexpected")/(COUNTA(Simple!$Q:$Q)-1) -> 0.15483871 | J17: =COUNTIF(Simple!Q:Q,"confused")/(COUNTA(Simple!$Q:$Q)-1) -> 0.14193548 | K17: =COUNTIF(Simple!R:R,"yes")/(COUNTA(Simple!$Q:$Q)-1) -> 0 | L17: =COUNTIF(Simple!R:R,"no")/(COUNTA(Simple!$Q:$Q)-1) -> 1 | M17: =C17+D17+E17 -> 155
A18: Simple (tuned) | B18: claude-sonnet-4-20250514 | C18: =COUNTIF(Simple!$K:$K,"expected") -> 108 | D18: =COUNTIF(Simple!$K:$K,"unexpected") -> 36 | E18: =COUNTIF(Simple!$K:$K,"confused") -> 11 | F18: =COUNTIF(Simple!$L:$L,"yes") -> 0 | G18: =COUNTIF(Simple!$L:$L,"no") -> 155 | H18: =COUNTIF(Simple!$K:$K,"expected")/(COUNTA(Simple!$K:$K)-1) -> 0.69677419 | I18: =COUNTIF(Simple!K:K,"unexpected")/(COUNTA(Simple!$K:$K)-1) -> 0.23225806 | J18: =COUNTIF(Simple!K:K,"incorrect")/(COUNTA(Simple!$K:$K)-1) -> 0 | K18: =COUNTIF(Simple!L:L,"yes")/(COUNTA(Simple!$K:$K)-1) -> 0 | L18: =COUNTIF(Simple!L:L,"no")/(COUNTA(Simple!$K:$K)-1) -> 1 | M18: =C18+D18+E18 -> 155
A19: Simple (tuned) | B19: gpt-5.4 | C19: =COUNTIF(Simple!$T:$T,"expected") -> 137 | D19: =COUNTIF(Simple!$T:$T,"unexpected") -> 18 | E19: =COUNTIF(Simple!$T:$T,"confused") -> 0 | F19: =COUNTIF(Simple!$U:$U,"yes") -> 0 | G19: =COUNTIF(Simple!$U:$U,"no") -> 155 | H19: =COUNTIF(Simple!$T:$T,"expected")/(COUNTA(Simple!$T:$T)-1) -> 0.88387097 | I19: =COUNTIF(Simple!T:T,"unexpected")/(COUNTA(Simple!$T:$T)-1) -> 0.11612903 | J19: =COUNTIF(Simple!T:T,"confused")/(COUNTA(Simple!$T:$T)-1) -> 0 | K19: =COUNTIF(Simple!U:U,"yes")/(COUNTA(Simple!$T:$T)-1) -> 0 | L19: =COUNTIF(Simple!U:U,"no")/(COUNTA(Simple!$T:$T)-1) -> 1 | M19: =C19+D19+E19 -> 155
A20: Simple (tuned) | B20: gpt-5 | C20: =COUNTIF(Simple!$N:$N,"expected") -> 132 | D20: =COUNTIF(Simple!$N:$N,"unexpected") -> 23 | E20: =COUNTIF(Simple!$N:$N,"confused") -> 0 | F20: =COUNTIF(Simple!$O:$O,"yes") -> 0 | G20: =COUNTIF(Simple!$O:$O,"no") -> 155 | H20: =COUNTIF(Simple!$N:$N,"expected")/(COUNTA(Simple!$N:$N)-1) -> 0.8516129 | I20: =COUNTIF(Simple!N:N,"unexpected")/(COUNTA(Simple!$N:$N)-1) -> 0.1483871 | J20: =COUNTIF(Simple!N:N,"confused")/(COUNTA(Simple!$N:$N)-1) -> 0 | K20: =COUNTIF(Simple!O:O,"yes")/(COUNTA(Simple!$N:$N)-1) -> 0 | L20: =COUNTIF(Simple!O:O,"no")/(COUNTA(Simple!$N:$N)-1) -> 1 | M20: =C20+D20+E20 -> 155
A21: Simple (tuned) | B21: gpt-4.1 | C21: =COUNTIF(Simple!$H:$H,"expected") -> 137 | D21: =COUNTIF(Simple!$H:$H,"unexpected") -> 18 | E21: =COUNTIF(Simple!$H:$H,"confused") -> 0 | F21: =COUNTIF(Simple!$I:$I,"yes") -> 0 | G21: =COUNTIF(Simple!$I:$I,"no") -> 155 | H21: =COUNTIF(Simple!$H:$H,"expected")/(COUNTA(Simple!$H:$H)-1) -> 0.88387097 | I21: =COUNTIF(Simple!H:H,"unexpected")/(COUNTA(Simple!$H:$H)-1) -> 0.11612903 | J21: =COUNTIF(Simple!H:H,"confused")/(COUNTA(Simple!$H:$H)-1) -> 0 | K21: =COUNTIF(Simple!I:I,"yes")/(COUNTA(Simple!$H:$H)-1) -> 0 | L21: =COUNTIF(Simple!I:I,"no")/(COUNTA(Simple!$H:$H)-1) -> 1 | M21: =C21+D21+E21 -> 155
A23: Complex (tuned) | B23: claude-sonnet-4-6 | C23: =COUNTIF(Complex!$W:$W,"expected") -> 98 | D23: =COUNTIF(Complex!$W:$W,"unexpected") -> 47 | E23: =COUNTIF(Complex!$W:$W,"confused") -> 0 | F23: =COUNTIF(Complex!$X:$X,"yes") -> 0 | G23: =COUNTIF(Complex!$X:$X,"no") -> 145 | H23: =COUNTIF(Complex!$W:$W,"expected")/(COUNTA(Complex!$W:$W)-1) -> 0.67586207 | I23: =COUNTIF(Complex!$W:$W,"unexpected")/(COUNTA(Complex!$W:$W)-1) -> 0.32413793 | J23: =COUNTIF(Complex!$W:$W,"confused")/(COUNTA(Complex!$W:$W)-1) -> 0 | K23: =COUNTIF(Complex!$X:$X,"yes")/(COUNTA(Complex!$X:$X)-1) -> 0 | L23: =COUNTIF(Complex!$X:$X,"no")/(COUNTA(Complex!$X:$X)-1) -> 1 | M23: =C23+D23+E23 -> 145
A24: Complex (tuned) | B24: claude-sonnet-4-5-20250929 | C24: =COUNTIF(Complex!$Q:$Q,"expected") -> 105 | D24: =COUNTIF(Complex!$Q:$Q,"unexpected") -> 40 | E24: =COUNTIF(Complex!$Q:$Q,"confused") -> 0 | F24: =COUNTIF(Complex!$R:$R,"yes") -> 0 | G24: =COUNTIF(Complex!$R:$R,"no") -> 145 | H24: =COUNTIF(Complex!$Q:$Q,"expected")/(COUNTA(Complex!$Q:$Q)-1) -> 0.72413793 | I24: =COUNTIF(Complex!$Q:$Q,"unexpected")/(COUNTA(Complex!$Q:$Q)-1) -> 0.27586207 | J24: =COUNTIF(Complex!$Q:$Q,"confused")/(COUNTA(Complex!$Q:$Q)-1) -> 0 | K24: =COUNTIF(Complex!$R:$R,"yes")/(COUNTA(Complex!$R:$R)-1) -> 0 | L24: =COUNTIF(Complex!$R:$R,"no")/(COUNTA(Complex!$R:$R)-1) -> 1 | M24: =C24+D24+E24 -> 145
A25: Complex (tuned) | B25: claude-sonnet-4-20250514 | C25: =COUNTIF(Complex!$K:$K,"expected") -> 113 | D25: =COUNTIF(Complex!$K:$K,"unexpected") -> 31 | E25: =COUNTIF(Complex!$K:$K,"confused") -> 1 | F25: =COUNTIF(Complex!$L:$L,"yes") -> 38 | G25: =COUNTIF(Complex!$L:$L,"no") -> 107 | H25: =COUNTIF(Complex!$K:$K,"expected")/(COUNTA(Complex!$K:$K)-1) -> 0.77931034 | I25: =COUNTIF(Complex!$K:$K,"unexpected")/(COUNTA(Complex!$K:$K)-1) -> 0.2137931 | J25: =COUNTIF(Complex!$K:$K,"confused")/(COUNTA(Complex!$K:$K)-1) -> 0.0068965517 | K25: =COUNTIF(Complex!$L:$L,"yes")/(COUNTA(Complex!$K:$K)-1) -> 0.26206897 | L25: =COUNTIF(Complex!L:L,"no")/(COUNTA(Complex!$K:$K)-1) -> 0.73793103 | M25: =C25+D25+E25 -> 145
A26: Complex (tuned) | B26: gpt-5.4 | C26: =COUNTIF(Complex!$T:$T,"expected") -> 103 | D26: =COUNTIF(Complex!$T:$T,"unexpected") -> 42 | E26: =COUNTIF(Complex!$T:$T,"confused") -> 0 | F26: =COUNTIF(Complex!$U:$U,"yes") -> 0 | G26: =COUNTIF(Complex!$U:$U,"no") -> 145 | H26: =COUNTIF(Complex!$T:$T,"expected")/(COUNTA(Complex!$T:$T)-1) -> 0.71034483 | I26: =COUNTIF(Complex!T:T,"unexpected")/(COUNTA(Complex!$T:$T)-1) -> 0.28965517 | J26: =COUNTIF(Complex!T:T,"confused")/(COUNTA(Complex!$T:$T)-1) -> 0 | K26: =COUNTIF(Complex!U:U,"yes")/(COUNTA(Complex!$T:$T)-1) -> 0 | L26: =COUNTIF(Complex!U:U,"no")/(COUNTA(Complex!$T:$T)-1) -> 1 | M26: =C26+D26+E26 -> 145
A27: Complex (tuned) | B27: gpt-5 | C27: =COUNTIF(Complex!$N:$N,"expected") -> 124 | D27: =COUNTIF(Complex!$N:$N,"unexpected") -> 21 | E27: =COUNTIF(Complex!$N:$N,"confused") -> 0 | F27: =COUNTIF(Complex!$O:$O,"yes") -> 0 | G27: =COUNTIF(Complex!$O:$O,"no") -> 145 | H27: =COUNTIF(Complex!$N:$N,"expected")/(COUNTA(Complex!$N:$N)-1) -> 0.85517241 | I27: =COUNTIF(Complex!N:N,"unexpected")/(COUNTA(Complex!$N:$N)-1) -> 0.14482759 | J27: =COUNTIF(Complex!N:N,"confused")/(COUNTA(Complex!$N:$N)-1) -> 0 | K27: =COUNTIF(Complex!O:O,"yes")/(COUNTA(Complex!$N:$N)-1) -> 0 | L27: =COUNTIF(Complex!O:O,"no")/(COUNTA(Complex!$N:$N)-1) -> 1 | M27: =C27+D27+E27 -> 145
A28: Complex (tuned) | B28: gpt-4.1 | C28: =COUNTIF(Complex!$H:$H,"expected") -> 110 | D28: =COUNTIF(Complex!$H:$H,"unexpected") -> 35 | E28: =COUNTIF(Complex!$H:$H,"confused") -> 0 | F28: =COUNTIF(Complex!$I:$I,"yes") -> 0 | G28: =COUNTIF(Complex!$I:$I,"no") -> 145 | H28: =COUNTIF(Complex!$H:$H,"expected")/(COUNTA(Complex!$H:$H)-1) -> 0.75862069 | I28: =COUNTIF(Complex!H:H,"unexpected")/(COUNTA(Complex!$H:$H)-1) -> 0.24137931 | J28: =COUNTIF(Complex!H:H,"confused")/(COUNTA(Complex!$H:$H)-1) -> 0 | K28: =COUNTIF(Complex!I:I,"yes")/(COUNTA(Complex!$H:$H)-1) -> 0 | L28: =COUNTIF(Complex!I:I,"no")/(COUNTA(Complex!$H:$H)-1) -> 1 | M28: =C28+D28+E28 -> 145
A30: Complex-Prio-Food | B30: claude-sonnet-4-6 | C30: =COUNTIF('Complex-Prio-Food'!$W:$W,"expected") -> 71 | D30: =COUNTIF('Complex-Prio-Food'!$W:$W,"unexpected") -> 74 | E30: =COUNTIF('Complex-Prio-Food'!$W:$W,"confused") -> 0 | F30: =COUNTIF('Complex-Prio-Food'!$X:$X,"yes") -> 0 | G30: =COUNTIF('Complex-Prio-Food'!$X:$X,"no") -> 145 | H30: =COUNTIF('Complex-Prio-Food'!$W:$W,"expected")/(COUNTA('Complex-Prio-Food'!$W:$W)-1) -> 0.48965517 | I30: =COUNTIF('Complex-Prio-Food'!W:W,"unexpected")/(COUNTA('Complex-Prio-Food'!$W:$W)-1) -> 0.51034483 | J30: =COUNTIF('Complex-Prio-Food'!W:W,"confused")/(COUNTA('Complex-Prio-Food'!$W:$W)-1) -> 0 | K30: =COUNTIF('Complex-Prio-Food'!X:X,"yes")/(COUNTA('Complex-Prio-Food'!$X:$X)-1) -> 0 | L30: =COUNTIF('Complex-Prio-Food'!X:X,"no")/(COUNTA('Complex-Prio-Food'!$X:$X)-1) -> 1 | M30: =C30+D30+E30 -> 145
A31: Complex-Prio-Food | B31: claude-sonnet-4-5-20250929 | C31: =COUNTIF('Complex-Prio-Food'!$Q:$Q,"expected") -> 78 | D31: =COUNTIF('Complex-Prio-Food'!$Q:$Q,"unexpected") -> 67 | E31: =COUNTIF('Complex-Prio-Food'!$Q:$Q,"confused") -> 0 | F31: =COUNTIF('Complex-Prio-Food'!$R:$R,"yes") -> 0 | G31: =COUNTIF('Complex-Prio-Food'!$R:$R,"no") -> 145 | H31: =COUNTIF('Complex-Prio-Food'!$Q:$Q,"expected")/(COUNTA('Complex-Prio-Food'!$Q:$Q)-1) -> 0.53793103 | I31: =COUNTIF('Complex-Prio-Food'!Q:Q,"unexpected")/(COUNTA('Complex-Prio-Food'!$Q:$Q)-1) -> 0.46206897 | J31: =COUNTIF('Complex-Prio-Food'!Q:Q,"confused")/(COUNTA('Complex-Prio-Food'!$Q:$Q)-1) -> 0 | K31: =COUNTIF('Complex-Prio-Food'!R:R,"yes")/(COUNTA('Complex-Prio-Food'!$R:$R)-1) -> 0 | L31: =COUNTIF('Complex-Prio-Food'!R:R,"no")/(COUNTA('Complex-Prio-Food'!$R:$R)-1) -> 1 | M31: =C31+D31+E31 -> 145
A32: Complex-Prio-Food | B32: claude-sonnet-4-20250514 | C32: =COUNTIF('Complex-Prio-Food'!$K:$K,"expected") -> 73 | D32: =COUNTIF('Complex-Prio-Food'!$K:$K,"unexpected") -> 70 | E32: =COUNTIF('Complex-Prio-Food'!$K:$K,"confused") -> 2 | F32: =COUNTIF('Complex-Prio-Food'!$L:$L,"yes") -> 9 | G32: =COUNTIF('Complex-Prio-Food'!$L:$L,"no") -> 136 | H32: =COUNTIF('Complex-Prio-Food'!$K:$K,"expected")/(COUNTA('Complex-Prio-Food'!$K:$K)-1) -> 0.50344828 | I32: =COUNTIF('Complex-Prio-Food'!K:K,"unexpected")/(COUNTA('Complex-Prio-Food'!$K:$K)-1) -> 0.48275862 | J32: =COUNTIF('Complex-Prio-Food'!K:K,"confused")/(COUNTA('Complex-Prio-Food'!$K:$K)-1) -> 0.013793103 | K32: =COUNTIF('Complex-Prio-Food'!L:L,"yes")/(COUNTA('Complex-Prio-Food'!$L:$L)-1) -> 0.062068966 | L32: =COUNTIF('Complex-Prio-Food'!L:L,"no")/(COUNTA('Complex-Prio-Food'!$L:$L)-1) -> 0.93793103 | M32: =C32+D32+E32 -> 145
A33: Complex-Prio-Food | B33: gpt-5.4 | C33: =COUNTIF('Complex-Prio-Food'!$T:$T,"expected") -> 81 | D33: =COUNTIF('Complex-Prio-Food'!$T:$T,"unexpected") -> 64 | E33: =COUNTIF('Complex-Prio-Food'!$T:$T,"confused") -> 0 | F33: =COUNTIF('Complex-Prio-Food'!$U:$U,"yes") -> 0 | G33: =COUNTIF('Complex-Prio-Food'!$U:$U,"no") -> 145 | H33: =COUNTIF('Complex-Prio-Food'!$T:$T,"expected")/(COUNTA('Complex-Prio-Food'!$T:$T)-1) -> 0.55862069 | I33: =COUNTIF('Complex-Prio-Food'!T:T,"unexpected")/(COUNTA('Complex-Prio-Food'!$Q:$Q)-1) -> 0.44137931 | J33: =COUNTIF('Complex-Prio-Food'!T:T,"confused")/(COUNTA('Complex-Prio-Food'!$Q:$Q)-1) -> 0 | K33: =COUNTIF('Complex-Prio-Food'!U:U,"yes")/(COUNTA('Complex-Prio-Food'!$U:$U)-1) -> 0 | L33: =COUNTIF('Complex-Prio-Food'!U:U,"no")/(COUNTA('Complex-Prio-Food'!$U:$U)-1) -> 1 | M33: =C33+D33+E33 -> 145
A34: Complex-Prio-Food | B34: gpt-5 | C34: =COUNTIF('Complex-Prio-Food'!$N:$N,"expected") -> 124 | D34: =COUNTIF('Complex-Prio-Food'!$N:$N,"unexpected") -> 21 | E34: =COUNTIF('Complex-Prio-Food'!$N:$N,"confused") -> 0 | F34: =COUNTIF('Complex-Prio-Food'!$O:$O,"yes") -> 0 | G34: =COUNTIF('Complex-Prio-Food'!$O:$O,"no") -> 145 | H34: =COUNTIF('Complex-Prio-Food'!$N:$N,"expected")/(COUNTA('Complex-Prio-Food'!$N:$N)-1) -> 0.85517241 | I34: =COUNTIF('Complex-Prio-Food'!N:N,"unexpected")/(COUNTA('Complex-Prio-Food'!$N:$N)-1) -> 0.14482759 | J34: =COUNTIF('Complex-Prio-Food'!N:N,"confused")/(COUNTA('Complex-Prio-Food'!$N:$N)-1) -> 0 | K34: =COUNTIF('Complex-Prio-Food'!O:O,"yes")/(COUNTA('Complex-Prio-Food'!$O:$O)-1) -> 0 | L34: =COUNTIF('Complex-Prio-Food'!O:O,"no")/(COUNTA('Complex-Prio-Food'!$O:$O)-1) -> 1 | M34: =C34+D34+E34 -> 145
A35: Complex-Prio-Food | B35: gpt-4.1 | C35: =COUNTIF('Complex-Prio-Food'!$H:$H,"expected") -> 85 | D35: =COUNTIF('Complex-Prio-Food'!$H:$H,"unexpected") -> 60 | E35: =COUNTIF('Complex-Prio-Food'!$H:$H,"confused") -> 0 | F35: =COUNTIF('Complex-Prio-Food'!$I:$I,"yes") -> 0 | G35: =COUNTIF('Complex-Prio-Food'!$I:$I,"no") -> 145 | H35: =COUNTIF('Complex-Prio-Food'!$H:$H,"expected")/(COUNTA('Complex-Prio-Food'!$H:$H)-1) -> 0.5862069 | I35: =COUNTIF('Complex-Prio-Food'!H:H,"unexpected")/(COUNTA('Complex-Prio-Food'!$H:$H)-1) -> 0.4137931 | J35: =COUNTIF('Complex-Prio-Food'!H:H,"confused")/(COUNTA('Complex-Prio-Food'!$H:$H)-1) -> 0 | K35: =COUNTIF('Complex-Prio-Food'!I:I,"yes")/(COUNTA('Complex-Prio-Food'!$H:$H)-1) -> 0 | L35: =COUNTIF('Complex-Prio-Food'!I:I,"no")/(COUNTA('Complex-Prio-Food'!$H:$H)-1) -> 1 | M35: =C35+D35+E35 -> 145
A36: Complex-Prio-Profession | B36: claude-sonnet-4-6 | C36: =COUNTIF('Complex-Prio-Profession'!$W:$W,"expected") -> 71 | D36: =COUNTIF('Complex-Prio-Profession'!$W:$W,"unexpected") -> 74 | E36: =COUNTIF('Complex-Prio-Profession'!$W:$W,"confused") -> 0 | F36: =COUNTIF('Complex-Prio-Profession'!$X:$X,"yes") -> 0 | G36: =COUNTIF('Complex-Prio-Profession'!$X:$X,"no") -> 145 | H36: =COUNTIF('Complex-Prio-Profession'!$W:$W,"expected")/(COUNTA('Complex-Prio-Profession'!$W:$W)-1) -> 0.48965517 | I36: =COUNTIF('Complex-Prio-Profession'!W:W,"unexpected")/(COUNTA('Complex-Prio-Profession'!$W:$W)-1) -> 0.51034483 | J36: =COUNTIF('Complex-Prio-Profession'!W:W,"confused")/(COUNTA('Complex-Prio-Profession'!$W:$W)-1) -> 0 | K36: =COUNTIF('Complex-Prio-Profession'!X:X,"yes")/(COUNTA('Complex-Prio-Profession'!$X:$X)-1) -> 0 | L36: =COUNTIF('Complex-Prio-Profession'!X:X,"no")/(COUNTA('Complex-Prio-Profession'!$X:$X)-1) -> 1 | M36: =C36+D36+E36 -> 145
A37: Complex-Prio-Profession | B37: claude-sonnet-4-5-20250929 | C37: =COUNTIF('Complex-Prio-Profession'!$Q:$Q,"expected") -> 82 | D37: =COUNTIF('Complex-Prio-Profession'!$Q:$Q,"unexpected") -> 63 | E37: =COUNTIF('Complex-Prio-Profession'!$Q:$Q,"confused") -> 0 | F37: =COUNTIF('Complex-Prio-Profession'!$R:$R,"yes") -> 0 | G37: =COUNTIF('Complex-Prio-Profession'!$R:$R,"no") -> 145 | H37: =COUNTIF('Complex-Prio-Profession'!$Q:$Q,"expected")/(COUNTA('Complex-Prio-Profession'!$Q:$Q)-1) -> 0.56551724 | I37: =COUNTIF('Complex-Prio-Profession'!Q:Q,"unexpected")/(COUNTA('Complex-Prio-Profession'!$Q:$Q)-1) -> 0.43448276 | J37: =COUNTIF('Complex-Prio-Profession'!Q:Q,"confused")/(COUNTA('Complex-Prio-Profession'!$Q:$Q)-1) -> 0 | K37: =COUNTIF('Complex-Prio-Profession'!R:R,"yes")/(COUNTA('Complex-Prio-Profession'!$R:$R)-1) -> 0 | L37: =COUNTIF('Complex-Prio-Profession'!R:R,"no")/(COUNTA('Complex-Prio-Profession'!$R:$R)-1) -> 1 | M37: =C37+D37+E37 -> 145
A38: Complex-Prio-Profession | B38: claude-sonnet-4-20250514 | C38: =COUNTIF('Complex-Prio-Profession'!$K:$K,"expected") -> 88 | D38: =COUNTIF('Complex-Prio-Profession'!$K:$K,"unexpected") -> 57 | E38: =COUNTIF('Complex-Prio-Profession'!$K:$K,"confused") -> 0 | F38: =COUNTIF('Complex-Prio-Profession'!$L:$L,"yes") -> 22 | G38: =COUNTIF('Complex-Prio-Profession'!$L:$L,"no") -> 123 | H38: =COUNTIF('Complex-Prio-Profession'!$K:$K,"expected")/(COUNTA('Complex-Prio-Profession'!$K:$K)-1) -> 0.60689655 | I38: =COUNTIF('Complex-Prio-Profession'!K:K,"unexpected")/(COUNTA('Complex-Prio-Profession'!$K:$K)-1) -> 0.39310345 | J38: =COUNTIF('Complex-Prio-Profession'!K:K,"confused")/(COUNTA('Complex-Prio-Profession'!$K:$K)-1) -> 0 | K38: =COUNTIF('Complex-Prio-Profession'!L:L,"yes")/(COUNTA('Complex-Prio-Profession'!$L:$L)-1) -> 0.15172414 | L38: =COUNTIF('Complex-Prio-Profession'!L:L,"no")/(COUNTA('Complex-Prio-Profession'!$L:$L)-1) -> 0.84827586 | M38: =C38+D38+E38 -> 145
A39: Complex-Prio-Profession | B39: gpt-5.4 | C39: =COUNTIF('Complex-Prio-Profession'!$T:$T,"expected") -> 86 | D39: =COUNTIF('Complex-Prio-Profession'!$T:$T,"unexpected") -> 59 | E39: =COUNTIF('Complex-Prio-Profession'!$T:$T,"confused") -> 0 | F39: =COUNTIF('Complex-Prio-Profession'!$U:$U,"yes") -> 0 | G39: =COUNTIF('Complex-Prio-Profession'!$U:$U,"no") -> 145 | H39: =COUNTIF('Complex-Prio-Profession'!$T:$T,"expected")/(COUNTA('Complex-Prio-Profession'!$T:$T)-1) -> 0.59310345 | I39: =COUNTIF('Complex-Prio-Profession'!T:T,"unexpected")/(COUNTA('Complex-Prio-Profession'!$T:$T)-1) -> 0.40689655 | J39: =COUNTIF('Complex-Prio-Profession'!T:T,"confused")/(COUNTA('Complex-Prio-Profession'!$T:$T)-1) -> 0 | K39: =COUNTIF('Complex-Prio-Profession'!U:U,"yes")/(COUNTA('Complex-Prio-Profession'!$U:$U)-1) -> 0 | L39: =COUNTIF('Complex-Prio-Profession'!U:U,"no")/(COUNTA('Complex-Prio-Profession'!$U:$U)-1) -> 1 | M39: =C39+D39+E39 -> 145
A40: Complex-Prio-Profession | B40: gpt-5 | C40: =COUNTIF('Complex-Prio-Profession'!$N:$N,"expected") -> 126 | D40: =COUNTIF('Complex-Prio-Profession'!$N:$N,"unexpected") -> 19 | E40: =COUNTIF('Complex-Prio-Profession'!$N:$N,"confused") -> 0 | F40: =COUNTIF('Complex-Prio-Profession'!$O:$O,"yes") -> 0 | G40: =COUNTIF('Complex-Prio-Profession'!$O:$O,"no") -> 145 | H40: =COUNTIF('Complex-Prio-Profession'!$N:$N,"expected")/(COUNTA('Complex-Prio-Profession'!$N:$N)-1) -> 0.86896552 | I40: =COUNTIF('Complex-Prio-Profession'!N:N,"unexpected")/(COUNTA('Complex-Prio-Profession'!$H:$H)-1) -> 0.13103448 | J40: =COUNTIF('Complex-Prio-Profession'!N:N,"confused")/(COUNTA('Complex-Prio-Profession'!$H:$H)-1) -> 0 | K40: =COUNTIF('Complex-Prio-Profession'!O:O,"yes")/(COUNTA('Complex-Prio-Profession'!$O:$O)-1) -> 0 | L40: =COUNTIF('Complex-Prio-Profession'!O:O,"no")/(COUNTA('Complex-Prio-Profession'!$O:$O)-1) -> 1 | M40: =C40+D40+E40 -> 145
A41: Complex-Prio-Profession | B41: gpt-4.1 | C41: =COUNTIF('Complex-Prio-Profession'!$H:$H,"expected") -> 89 | D41: =COUNTIF('Complex-Prio-Profession'!$H:$H,"unexpected") -> 56 | E41: =COUNTIF('Complex-Prio-Profession'!$H:$H,"confused") -> 0 | F41: =COUNTIF('Complex-Prio-Profession'!$I:$I,"yes") -> 0 | G41: =COUNTIF('Complex-Prio-Profession'!$I:$I,"no") -> 145 | H41: =COUNTIF('Complex-Prio-Profession'!$H:$H,"expected")/(COUNTA('Complex-Prio-Profession'!$H:$H)-1) -> 0.6137931 | I41: =COUNTIF('Complex-Prio-Profession'!H:H,"unexpected")/(COUNTA('Complex-Prio-Profession'!$H:$H)-1) -> 0.3862069 | J41: =COUNTIF('Complex-Prio-Profession'!H:H,"confused")/(COUNTA('Complex-Prio-Profession'!$H:$H)-1) -> 0 | K41: =COUNTIF('Complex-Prio-Profession'!I:I,"yes")/(COUNTA('Complex-Prio-Profession'!$H:$H)-1) -> 0 | L41: =COUNTIF('Complex-Prio-Profession'!I:I,"no")/(COUNTA('Complex-Prio-Profession'!$H:$H)-1) -> 1 | M41: =C41+D41+E41 -> 145
A42: Complex-Prio-Sentiment | B42: claude-sonnet-4-6 | C42: =COUNTIF('Complex-Prio-Sentiment'!$W:$W,"expected") -> 72 | D42: =COUNTIF('Complex-Prio-Sentiment'!$W:$W,"unexpected") -> 73 | E42: =COUNTIF('Complex-Prio-Sentiment'!$W:$W,"confused") -> 0 | F42: =COUNTIF('Complex-Prio-Sentiment'!$X:$X,"yes") -> 0 | G42: =COUNTIF('Complex-Prio-Sentiment'!$X:$X,"no") -> 145 | H42: =COUNTIF('Complex-Prio-Sentiment'!$W:$W,"expected")/(COUNTA('Complex-Prio-Sentiment'!$W:$W)-1) -> 0.49655172 | I42: =COUNTIF('Complex-Prio-Sentiment'!W:W,"unexpected")/(COUNTA('Complex-Prio-Sentiment'!$W:$W)-1) -> 0.50344828 | J42: =COUNTIF('Complex-Prio-Sentiment'!W:W,"confused")/(COUNTA('Complex-Prio-Sentiment'!$W:$W)-1) -> 0 | K42: =COUNTIF('Complex-Prio-Sentiment'!X:X,"yes")/(COUNTA('Complex-Prio-Sentiment'!$X:$X)-1) -> 0 | L42: =COUNTIF('Complex-Prio-Sentiment'!X:X,"no")/(COUNTA('Complex-Prio-Sentiment'!$X:$X)-1) -> 1 | M42: =C42+D42+E42 -> 145
A43: Complex-Prio-Sentiment | B43: claude-sonnet-4-5-20250929 | C43: =COUNTIF('Complex-Prio-Sentiment'!$Q:$Q,"expected") -> 83 | D43: =COUNTIF('Complex-Prio-Sentiment'!$Q:$Q,"unexpected") -> 62 | E43: =COUNTIF('Complex-Prio-Sentiment'!$Q:$Q,"confused") -> 0 | F43: =COUNTIF('Complex-Prio-Sentiment'!$R:$R,"yes") -> 0 | G43: =COUNTIF('Complex-Prio-Sentiment'!$R:$R,"no") -> 145 | H43: =COUNTIF('Complex-Prio-Sentiment'!$Q:$Q,"expected")/(COUNTA('Complex-Prio-Sentiment'!$Q:$Q)-1) -> 0.57241379 | I43: =COUNTIF('Complex-Prio-Sentiment'!Q:Q,"unexpected")/(COUNTA('Complex-Prio-Sentiment'!$Q:$Q)-1) -> 0.42758621 | J43: =COUNTIF('Complex-Prio-Sentiment'!Q:Q,"confused")/(COUNTA('Complex-Prio-Sentiment'!$Q:$Q)-1) -> 0 | K43: =COUNTIF('Complex-Prio-Sentiment'!R:R,"yes")/(COUNTA('Complex-Prio-Sentiment'!$R:$R)-1) -> 0 | L43: =COUNTIF('Complex-Prio-Sentiment'!R:R,"no")/(COUNTA('Complex-Prio-Sentiment'!$R:$R)-1) -> 1 | M43: =C43+D43+E43 -> 145
A44: Complex-Prio-Sentiment | B44: claude-sonnet-4-20250514 | C44: =COUNTIF('Complex-Prio-Sentiment'!$K:$K,"expected") -> 79 | D44: =COUNTIF('Complex-Prio-Sentiment'!$K:$K,"unexpected") -> 66 | E44: =COUNTIF('Complex-Prio-Sentiment'!$K:$K,"confused") -> 0 | F44: =COUNTIF('Complex-Prio-Sentiment'!$L:$L,"yes") -> 16 | G44: =COUNTIF('Complex-Prio-Sentiment'!$L:$L,"no") -> 129 | H44: =COUNTIF('Complex-Prio-Sentiment'!$K:$K,"expected")/(COUNTA('Complex-Prio-Sentiment'!$K:$K)-1) -> 0.54482759 | I44: =COUNTIF('Complex-Prio-Sentiment'!K:K,"unexpected")/(COUNTA('Complex-Prio-Sentiment'!$K:$K)-1) -> 0.45517241 | J44: =COUNTIF('Complex-Prio-Sentiment'!K:K,"confused")/(COUNTA('Complex-Prio-Sentiment'!$K:$K)-1) -> 0 | K44: =COUNTIF('Complex-Prio-Sentiment'!L:L,"yes")/(COUNTA('Complex-Prio-Sentiment'!$L:$L)-1) -> 0.11034483 | L44: =COUNTIF('Complex-Prio-Sentiment'!L:L,"no")/(COUNTA('Complex-Prio-Sentiment'!$L:$L)-1) -> 0.88965517 | M44: =C44+D44+E44 -> 145
A45: Complex-Prio-Sentiment | B45: gpt-5.4 | C45: =COUNTIF('Complex-Prio-Sentiment'!$T:$T,"expected") -> 78 | D45: =COUNTIF('Complex-Prio-Sentiment'!$T:$T,"unexpected") -> 67 | E45: =COUNTIF('Complex-Prio-Sentiment'!$T:$T,"confused") -> 0 | F45: =COUNTIF('Complex-Prio-Sentiment'!$U:$U,"yes") -> 0 | G45: =COUNTIF('Complex-Prio-Sentiment'!$U:$U,"no") -> 145 | H45: =COUNTIF('Complex-Prio-Sentiment'!$T:$T,"expected")/(COUNTA('Complex-Prio-Sentiment'!$T:$T)-1) -> 0.53793103 | I45: =COUNTIF('Complex-Prio-Sentiment'!T:T,"unexpected")/(COUNTA('Complex-Prio-Sentiment'!$Q:$Q)-1) -> 0.46206897 | J45: =COUNTIF('Complex-Prio-Sentiment'!T:T,"confused")/(COUNTA('Complex-Prio-Sentiment'!$Q:$Q)-1) -> 0 | K45: =COUNTIF('Complex-Prio-Sentiment'!U:U,"yes")/(COUNTA('Complex-Prio-Sentiment'!$U:$U)-1) -> 0 | L45: =COUNTIF('Complex-Prio-Sentiment'!U:U,"no")/(COUNTA('Complex-Prio-Sentiment'!$U:$U)-1) -> 1 | M45: =C45+D45+E45 -> 145
A46: Complex-Prio-Sentiment | B46: gpt-5 | C46: =COUNTIF('Complex-Prio-Sentiment'!$N:$N,"expected") -> 126 | D46: =COUNTIF('Complex-Prio-Sentiment'!$N:$N,"unexpected") -> 19 | E46: =COUNTIF('Complex-Prio-Sentiment'!$N:$N,"confused") -> 0 | F46: =COUNTIF('Complex-Prio-Sentiment'!$O:$O,"yes") -> 0 | G46: =COUNTIF('Complex-Prio-Sentiment'!$O:$O,"no") -> 145 | H46: =COUNTIF('Complex-Prio-Sentiment'!$N:$N,"expected")/(COUNTA('Complex-Prio-Sentiment'!$N:$N)-1) -> 0.86896552 | I46: =COUNTIF('Complex-Prio-Sentiment'!N:N,"unexpected")/(COUNTA('Complex-Prio-Sentiment'!$N:$N)-1) -> 0.13103448 | J46: =COUNTIF('Complex-Prio-Sentiment'!N:N,"confused")/(COUNTA('Complex-Prio-Sentiment'!$N:$N)-1) -> 0 | K46: =COUNTIF('Complex-Prio-Sentiment'!O:O,"yes")/(COUNTA('Complex-Prio-Sentiment'!$O:$O)-1) -> 0 | L46: =COUNTIF('Complex-Prio-Sentiment'!O:O,"no")/(COUNTA('Complex-Prio-Sentiment'!$O:$O)-1) -> 1 | M46: =C46+D46+E46 -> 145
A47: Complex-Prio-Sentiment | B47: gpt-4.1 | C47: =COUNTIF('Complex-Prio-Sentiment'!$H:$H,"expected") -> 83 | D47: =COUNTIF('Complex-Prio-Sentiment'!$H:$H,"unexpected") -> 62 | E47: =COUNTIF('Complex-Prio-Sentiment'!$H:$H,"confused") -> 0 | F47: =COUNTIF('Complex-Prio-Sentiment'!$I:$I,"yes") -> 0 | G47: =COUNTIF('Complex-Prio-Sentiment'!$I:$I,"no") -> 145 | H47: =COUNTIF('Complex-Prio-Sentiment'!$H:$H,"expected")/(COUNTA('Complex-Prio-Sentiment'!$H:$H)-1) -> 0.57241379 | I47: =COUNTIF('Complex-Prio-Sentiment'!H:H,"unexpected")/(COUNTA('Complex-Prio-Sentiment'!$H:$H)-1) -> 0.42758621 | J47: =COUNTIF('Complex-Prio-Sentiment'!H:H,"confused")/(COUNTA('Complex-Prio-Sentiment'!$H:$H)-1) -> 0 | K47: =COUNTIF('Complex-Prio-Sentiment'!I:I,"yes")/(COUNTA('Complex-Prio-Sentiment'!$H:$H)-1) -> 0 | L47: =COUNTIF('Complex-Prio-Sentiment'!I:I,"no")/(COUNTA('Complex-Prio-Sentiment'!$H:$H)-1) -> 1 | M47: =C47+D47+E47 -> 145
A49: Complex-Prio-Combi | B49: claude-sonnet-4-6 | C49: =C30+C36+C42 -> 214 | D49: =D30+D36+D42 -> 221 | E49: =E30+E36+E42 -> 0 | F49: =F30+F36+F42 -> 0 | G49: =G30+G36+G42 -> 435 | H49: =C49/(C49+D49+E49) -> 0.49195402 | I49: =D49/$M49 -> 0.50804598 | J49: =E49/$M49 -> 0 | K49: =F49/M49 -> 0 | L49: =G49/M49 -> 1 | M49: =C49+D49+E49 -> 435
A50: Complex-Prio-Combi | B50: claude-sonnet-4-5-20250929 | C50: =C31+C37+C43 -> 243 | D50: =D31+D37+D43 -> 192 | E50: =E31+E37+E43 -> 0 | F50: =F31+F37+F43 -> 0 | G50: =G31+G37+G43 -> 435 | H50: =C50/(C50+D50+E50) -> 0.55862069 | I50: =D50/$M50 -> 0.44137931 | J50: =E50/$M50 -> 0 | K50: =F50/M50 -> 0 | L50: =G50/M50 -> 1 | M50: =C50+D50+E50 -> 435
A51: Complex-Prio-Combi | B51: claude-sonnet-4-20250514 | C51: =C32+C38+C44 -> 240 | D51: =D32+D38+D44 -> 193 | E51: =E32+E38+E44 -> 2 | F51: =F32+F38+F44 -> 47 | G51: =G32+G38+G44 -> 388 | H51: =C51/(C51+D51+E51) -> 0.55172414 | I51: =D51/$M51 -> 0.44367816 | J51: =E51/$M51 -> 0.0045977011 | K51: =F51/M51 -> 0.10804598 | L51: =G51/M51 -> 0.89195402 | M51: =C51+D51+E51 -> 435
A52: Complex-Prio-Combi | B52: gpt-5.4 | C52: =C33+C39+C45 -> 245 | D52: =D33+D39+D45 -> 190 | E52: =E33+E39+E45 -> 0 | F52: =F33+F39+F45 -> 0 | G52: =G33+G39+G45 -> 435 | H52: =C52/(C52+D52+E52) -> 0.56321839 | I52: =D52/$M52 -> 0.43678161 | J52: =E52/$M52 -> 0 | K52: =F52/M52 -> 0 | L52: =G52/M52 -> 1 | M52: =C52+D52+E52 -> 435
A53: Complex-Prio-Combi | B53: gpt-5 | C53: =C34+C40+C46 -> 376 | D53: =D34+D40+D46 -> 59 | E53: =E34+E40+E46 -> 0 | F53: =F34+F40+F46 -> 0 | G53: =G34+G40+G46 -> 435 | H53: =C53/(C53+D53+E53) -> 0.86436782 | I53: =D53/$M53 -> 0.13563218 | J53: =E53/$M53 -> 0 | K53: =F53/M53 -> 0 | L53: =G53/M53 -> 1 | M53: =C53+D53+E53 -> 435
A54: Complex-Prio-Combi | B54: gpt-4.1 | C54: =C35+C41+C47 -> 257 | D54: =D35+D41+D47 -> 178 | E54: =E35+E41+E47 -> 0 | F54: =F35+F41+F47 -> 0 | G54: =G35+G41+G47 -> 435 | H54: =C54/(C54+D54+E54) -> 0.5908046 | I54: =D54/$M54 -> 0.4091954 | J54: =E54/$M54 -> 0 | K54: =F54/M54 -> 0 | L54: =G54/M54 -> 1 | M54: =C54+D54+E54 -> 435
A57: Pattern | B57: Avg Length of Input Prompt | C57: Complexity Ranking | D57: Layers of Context | E57: Layers of Cues | F57: Count of Prompts
A58: Simple untuned | B58: =AVERAGE('Simple untuned'!$Y:$Y) -> 393.52903 | C58: 1 | D58: 1 | E58: 1 | F58: =COUNTA('Simple untuned'!$Y:$Y)-1 -> 155
A59: Complex untuned | B59: =AVERAGE('Comple untuned'!Y:Y) -> 619.24828 | C59: 3 | D59: 3 | E59: 1 | F59: =COUNTA('Comple untuned'!Y:Y)-1 -> 145
A60: Simple (tuned) | B60: =AVERAGE(Simple!$Y:$Y) -> 449.1871 | C60: 2 | D60: 1 | E60: 3 | F60: =COUNTA(Simple!$Y:$Y)-1 -> 155
A61: Complex (tuned) | B61: =AVERAGE(Complex!Y:Y) -> 707.24828 | C61: 4 | D61: 3 | E61: 3 | F61: =COUNTA(Complex!Y:Y)-1 -> 145
A62: Complex-Prio-Profession | B62: =AVERAGE('Complex-Prio-Profession'!Y:Y) -> 766.24828 | C62: 5 | D62: 3 | E62: 4 | F62: =COUNTA('Complex-Prio-Profession'!Y:Y)-1 -> 145
A63: Complex-Prio-Food | B63: =AVERAGE('Complex-Prio-Food'!Y:Y) -> 766.24828 | C63: 5 | D63: 3 | E63: 4 | F63: =COUNTA('Complex-Prio-Food'!S:S)-1 -> 145
A64: Complex-Prio-Sentiment | B64: =AVERAGE('Complex-Prio-Sentiment'!Y:Y) -> 766.24828 | C64: 5 | D64: 3 | E64: 4 | F64: =COUNTA('Complex-Prio-Sentiment'!S:S)-1 -> 145
A70: Pattern | B70: Model | C70: Response Predicted | D70: Response Unpredicted | E70: LM Non-Responsive | F70: Noise in Output | G70: No Noise in Output | H70: Response Predicted | I70: Response Unpredicted | J70: LM Non-Responsive | K70: Noise in Output | L70: No Noise in Output | M70: Count of Prompts
A71: Simple untuned | B71: All | C71: =SUM(C2:C7) -> 782 | D71: =SUM(D2:D7) -> 105 | E71: =SUM(E2:E7) -> 43 | F71: =SUM(F2:F7) -> 483 | G71: =SUM(G2:G7) -> 447 | H71: =C71/(C71+D71+E71) -> 0.84086022 | I71: =AVERAGE(I2:I7) -> 0.11290323 | J71: =AVERAGE(J2:J7) -> 0.046236559 | K71: =AVERAGE(K2:K7) -> 0.51935484 | L71: =AVERAGE(L2:L7) -> 0.48064516 | M71: =C71+D71+E71 -> 930
A72: Simple (tuned) | B72: All | C72: =SUM(C16:C21) -> 748 | D72: =SUM(D16:D21) -> 149 | E72: =SUM(E16:E21) -> 33 | F72: =SUM(F16:F21) -> 8 | G72: =SUM(G16:G21) -> 922 | H72: =C72/(C72+D72+E72) -> 0.80430108 | I72: =AVERAGE(I16:I21) -> 0.16021505 | J72: =AVERAGE(J16:J21) -> 0.023655914 | K72: =AVERAGE(K16:K21) -> 0.0086021505 | L72: =AVERAGE(L16:L21) -> 0.99139785 | M72: =C72+D72+E72 -> 930
A73: Complex untuned | B73: All | C73: =SUM(C9:C14) -> 629 | D73: =SUM(D9:D14) -> 185 | E73: =SUM(E9:E14) -> 56 | F73: =SUM(F9:F14) -> 522 | G73: =SUM(G9:G14) -> 282 | H73: =C73/(C73+D73+E73) -> 0.72298851 | I73: =AVERAGE(I9:I14) -> 0.21264368 | J73: =AVERAGE(J9:J14) -> 0.064367816 | K73: =AVERAGE(K9:K14) -> 0.6 | L73: =AVERAGE(L9:L14) -> 0.32413793 | M73: =C73+D73+E73 -> 870
A74: Complex (tuned) | B74: All | C74: =SUM(C23:C28) -> 653 | D74: =SUM(D23:D28) -> 216 | E74: =SUM(E23:E28) -> 1 | F74: =SUM(F23:F28) -> 38 | G74: =SUM(G23:G28) -> 832 | H74: =C74/(C74+D74+E74) -> 0.75057471 | I74: =AVERAGE(I23:I28) -> 0.24827586 | J74: =AVERAGE(J23:J28) -> 0.0011494253 | K74: =AVERAGE(K23:K28) -> 0.043678161 | L74: =AVERAGE(L23:L28) -> 0.95632184 | M74: =C74+D74+E74 -> 870
A75: Complex (tuned & Prio) | B75: All | C75: =SUM(C30:C47) -> 1575 | D75: =SUM(D30:D47) -> 1033 | E75: =SUM(E30:E47) -> 2 | F75: =SUM(F30:F47) -> 47 | G75: =SUM(G30:G47) -> 2563 | H75: =C75/(C75+D75+E75) -> 0.60344828 | I75: =D75/(C75+D75+E75) -> 0.39578544 | J75: =E75/(C75+D75+E75) -> 0.00076628352 | K75: =F75/(F75+G75) -> 0.018007663 | L75: =G75/(F75+G75) -> 0.98199234 | M75: =C75+D75+E75 -> 2610
A77: Simple untuned | B77: GPT | C77: =SUM(C5:C7) -> 391 | D77: =SUM(D5:D7) -> 56 | E77: =SUM(E5:E7) -> 18 | F77: =SUM(F5:F7) -> 98 | G77: =SUM(G5:G7) -> 367 | H77: =C77/(C77+D77+E77) -> 0.84086022 | I77: =D77/(C77+D77+E77) -> 0.12043011 | J77: =E77/(C77+D77+E77) -> 0.038709677 | K77: =F77/(F77+G77) -> 0.21075269 | L77: =G77/(F77+G77) -> 0.78924731 | M77: =C77+D77+E77 -> 465
A78: Simple (tuned) | B78: GPT | C78: =SUM(C19:C21) -> 406 | D78: =SUM(D19:D21) -> 59 | E78: =SUM(E19:E21) -> 0 | F78: =SUM(F19:F21) -> 0 | G78: =SUM(G19:G21) -> 465 | H78: =C78/(C78+D78+E78) -> 0.87311828 | I78: =D78/(C78+D78+E78) -> 0.12688172 | J78: =E78/(C78+D78+E78) -> 0 | K78: =F78/(F78+G78) -> 0 | L78: =G78/(F78+G78) -> 1 | M78: =C78+D78+E78 -> 465
A79: Complex untuned | B79: GPT | C79: =SUM(C12:C14) -> 323 | D79: =SUM(D12:D14) -> 75 | E79: =SUM(E12:E14) -> 37 | F79: =SUM(F12:F14) -> 179 | G79: =SUM(G12:G14) -> 256 | H79: =C79/(C79+D79+E79) -> 0.74252874 | I79: =D79/(C79+D79+E79) -> 0.17241379 | J79: =E79/(C79+D79+E79) -> 0.085057471 | K79: =F79/(F79+G79) -> 0.41149425 | L79: =G79/(F79+G79) -> 0.58850575 | M79: =C79+D79+E79 -> 435
A80: Complex (tuned) | B80: GPT | C80: =SUM(C26:C28) -> 337 | D80: =SUM(D26:D28) -> 98 | E80: =SUM(E26:E28) -> 0 | F80: =SUM(F26:F28) -> 0 | G80: =SUM(G26:G28) -> 435 | H80: =C80/(C80+D80+E80) -> 0.77471264 | I80: =D80/(C80+D80+E80) -> 0.22528736 | J80: =E80/(C80+D80+E80) -> 0 | K80: =F80/(F80+G80) -> 0 | L80: =G80/(F80+G80) -> 1 | M80: =C80+D80+E80 -> 435
A81: Complex (tuned & Prio) | B81: GPT | C81: =(SUM(C30:C32)+SUM(C36:C38)+SUM(C42:C44)) -> 697 | D81: =(SUM(D30:D32)+SUM(D36:D38)+SUM(D42:D44)) -> 606 | E81: =(SUM(E30:E32)+SUM(E36:E38)+SUM(E42:E44)) -> 2 | F81: =(SUM(F30:F32)+SUM(F36:F38)+SUM(F42:F44)) -> 47 | G81: =(SUM(G30:G32)+SUM(G36:G38)+SUM(G42:G44)) -> 1258 | H81: =C81/(C81+D81+E81) -> 0.53409962 | I81: =D81/(C81+D81+E81) -> 0.46436782 | J81: =E81/(C81+D81+E81) -> 0.001532567 | K81: =F81/(F81+G81) -> 0.036015326 | L81: =G81/(F81+G81) -> 0.96398467 | M81: =C81+D81+E81 -> 1305
A83: Simple untuned | B83: Claude | C83: =SUM(C2:C4) -> 391 | D83: =SUM(D2:D4) -> 49 | E83: =SUM(E2:E4) -> 25 | F83: =SUM(F2:F4) -> 385 | G83: =SUM(G2:G4) -> 80 | H83: =C83/(C83+D83+E83) -> 0.84086022 | I83: =D83/(C83+D83+E83) -> 0.10537634 | J83: =E83/(C83+D83+E83) -> 0.053763441 | K83: =F83/(F83+G83) -> 0.82795699 | L83: =G83/(F83+G83) -> 0.17204301 | M83: =C83+D83+E83 -> 465
A84: Simple (tuned) | B84: Claude | C84: =SUM(C16:C18) -> 342 | D84: =SUM(D16:D18) -> 90 | E84: =SUM(E16:E18) -> 33 | F84: =SUM(F16:F18) -> 8 | G84: =SUM(G16:G18) -> 457 | H84: =C84/(C84+D84+E84) -> 0.73548387 | I84: =D84/(C84+D84+E84) -> 0.19354839 | J84: =E84/(C84+D84+E84) -> 0.070967742 | K84: =F84/(F84+G84) -> 0.017204301 | L84: =G84/(F84+G84) -> 0.9827957 | M84: =C84+D84+E84 -> 465
A85: Complex untuned | B85: Claude | C85: =SUM(C9:C11) -> 306 | D85: =SUM(D9:D11) -> 110 | E85: =SUM(E9:E11) -> 19 | F85: =SUM(F9:F11) -> 343 | G85: =SUM(G9:G11) -> 26 | H85: =C85/(C85+D85+E85) -> 0.70344828 | I85: =D85/(C85+D85+E85) -> 0.25287356 | J85: =E85/(C85+D85+E85) -> 0.043678161 | K85: =F85/(F85+G85) -> 0.9295393 | L85: =G85/(F85+G85) -> 0.070460705 | M85: =C85+D85+E85 -> 435
A86: Complex (tuned) | B86: Claude | C86: =SUM(C23:C25) -> 316 | D86: =SUM(D23:D25) -> 118 | E86: =SUM(E23:E25) -> 1 | F86: =SUM(F23:F25) -> 38 | G86: =SUM(G23:G25) -> 397 | H86: =C86/(C86+D86+E86) -> 0.72643678 | I86: =D86/(C86+D86+E86) -> 0.27126437 | J86: =E86/(C86+D86+E86) -> 0.0022988506 | K86: =F86/(F86+G86) -> 0.087356322 | L86: =G86/(F86+G86) -> 0.91264368 | M86: =C86+D86+E86 -> 435
A87: Complex (tuned & Prio) | B87: Claude | C87: =(SUM(C33:C35)+SUM(C39:C41)+SUM(C45:C47)) -> 878 | D87: =(SUM(D33:D35)+SUM(D39:D41)+SUM(D45:D47)) -> 427 | E87: =(SUM(E33:E35)+SUM(E39:E41)+SUM(E45:E47)) -> 0 | F87: =(SUM(F33:F35)+SUM(F39:F41)+SUM(F45:F47)) -> 0 | G87: =(SUM(G33:G35)+SUM(G39:G41)+SUM(G45:G47)) -> 1305 | H87: =C87/(C87+D87+E87) -> 0.67279693 | I87: =D87/(C87+D87+E87) -> 0.32720307 | J87: =E87/(C87+D87+E87) -> 0 | K87: =F87/(F87+G87) -> 0 | L87: =G87/(F87+G87) -> 1 | M87: =C87+D87+E87 -> 1305
D93: =SUM(D24:D29) -> 169

Sheet Simple untuned
A1: Pattern | B1: Category | C1: Cue Layer | D1: Context | E1: Request | F1: pre-test prediction | G1: Response - gpt-4.1 | H1: Validation - gpt-4.1 | I1: output noise - gpt | J1: Response - claude-sonnet-4-20250514 | K1: Validation - claude-sonnet-4-20250514 | L1: output noise - claude | M1: Response - gpt-5 | N1: Validation - gpt-5 | O1: output noise - gpt-5 | P1: Response - claude-sonnet-4-5-20250929 | Q1: Validation - claude-sonnet-4-5-20250929 | R1: Output noise - claude-sonnet-4-5-20250929 | S1: Response - gpt-5.4 | T1: Validation - gpt-5.4 | U1: output noise - gpt-5.4 | V1: Response - claude-sonnet-4-6 | W1: Validation - claude-sonnet-4-6 | X1: Output noise -claude-sonnet-4 | Y1: Length of Input Prompt | Z1: Run Date
A2: Simple | B2: Profession | C2: [result: resolved, final] | D2: Roel is a football player // sportsman // apple Mia is a basketball coach // sportsman // apple Chirak is a Tester // software engineer // orange Arun is a developer // software engineer // orange Sophie works in guitar band // artist // pear Leo is a painter // artist // pear [result: resolved, final] | E2: Sachine is softball player // | F2: apple | G2: Based on the provided patterns, let's resolve the label for Sachine: Here are the patterns: - Sportsman (football, basketball, softball): apple - Software engineer (Tester, developer): orange - Artist (guitar band, painter): pear Sachine is a softball player, which matches the "sportsman" category. Both Roel (football player) and Mia (basketball coach) are labeled as "sportsman // apple". **Final resolved result:** Sachine is a softball player // sportsman // apple | H2: expected | I2: yes | J2: Following the pattern from the examples: Sachine is softball player // sportsman // apple The pattern shows: - Football player and basketball coach → sportsman → apple - Tester and developer → software engineer → orange - Guitar band member and painter → artist → pear Since Sachine is a softball player (similar to football and basketball), they would be categorized as a sportsman and assigned apple. | K2: expected | L2: yes | M2: Sachine is softball player // sportsman // apple | N2: expected | O2: no | P2: Based on the pattern in your examples, I need to categorize Sachin (note: you spelled it "Sachine") who is a softball player. Following the established pattern: - Football player and basketball coach → sportsman → apple - Tester and developer → software engineer → orange - Guitar band member and painter → artist → pear A softball player would fall into the sports category, similar to the football player and basketball coach. **Sachin is a softball player // sportsman // apple** [result: resolved, final] | Q2: expected | R2: yes | S2: Sachine is a **sportsman // apple**. | T2: expected | U2: no | V2: Following the pattern from your examples: Sachine is a softball player // **sportsman** // **apple** (softball player → sportsman category → apple fruit, matching the pattern of Roel and Mia) | W2: expected | X2: yes | Y2: =LEN(D2)+LEN(E2) -> 335 | Z2: 46103
A3: Simple | B3: Profession | C3: [result: resolved, final] | D3: Roel is a football player // sportsman // apple Mia is a basketball coach // sportsman // apple Chirak is a Tester // software engineer // orange Arun is a developer // software engineer // orange Sophie works in guitar band // artist // pear Leo is a painter // artist // pear [result: resolved, final] | E3: Anil is IT engineer // | F3: orange | G3: Based on the patterns in your data: - "Football player" and "basketball coach" fall under "sportsman" and have "apple". - "Tester" and "developer" fall under "software engineer" and have "orange". - "Works in guitar band" and "painter" fall under "artist" and have "pear". "IT engineer" is most similar to "software engineer" in your examples. Therefore, following the pattern: Anil is IT engineer // software engineer // orange | H3: expected | I3: yes | J3: Hello! Looking at the pattern in your examples, I can see that you're categorizing people by their specific role, then a broader category, then assigning a fruit. Following the established pattern: Anil is IT engineer // software engineer // orange The pattern shows: - Sports professionals (football player, basketball coach) → sportsman → apple - Tech professionals (Tester, developer) → software engineer → orange - Creative professionals (guitar band member, painter) → artist → pear Since Anil is an IT engineer, this fits with the software engineer category and gets the orange designation. | K3: expected | L3: yes | M3: Anil is IT engineer // software engineer // orange | N3: expected | O3: no | P3: Based on the pattern in your examples: - Football player and basketball coach → sportsman → apple - Tester and developer → software engineer → orange - Guitar band member and painter → artist → pear **Anil is IT engineer // software engineer // orange** [result: resolved, final] The pattern shows that IT engineer falls under the software engineer category, which is associated with orange. | Q3: expected | R3: yes | S3: Anil is **IT engineer // software engineer // orange** | T3: expected | U3: no | V3: Hello! 👋 Based on the pattern in your data: **Anil is an IT engineer // software engineer // orange** The logic being: - **IT engineer** → maps to the category **software engineer** - **software engineer** → maps to the fruit **orange** (Just like Chirak the Tester and Arun the developer!) 🍊 | W3: expected | X3: yes | Y3: =LEN(D3)+LEN(E3) -> 329 | Z3: 46103
A4: Simple | B4: Profession | C4: [result: resolved, final] | D4: Roel is a football player // sportsman // apple Mia is a basketball coach // sportsman // apple Chirak is a Tester // software engineer // orange Arun is a developer // software engineer // orange Sophie works in guitar band // artist // pear Leo is a painter // artist // pear [result: resolved, final] | E4: Biba is violin player // | F4: pear | G4: Based on the patterns in your data: Each person has three attributes: 1. Role (e.g., football player, developer, painter) 2. Category (e.g., sportsman, software engineer, artist) 3. Fruit (e.g., apple, orange, pear) Let's resolve Biba's attributes: **Role:** violin player Now, let's see how to resolve the other two attributes: - Looking at Sophie (guitar band) and Leo (painter), both are in the "artist" category and linked to "pear." - "Violin player" is an artistic role, similar to "guitar band" and "painter," so category should be "artist." - The fruit associated with "artist" is "pear." **Final Answer:** Biba is violin player // artist // pear | H4: expected | I4: yes | J4: Looking at the pattern in your examples: - Football player and basketball coach are both categorized as "sportsman" with "apple" - Tester and developer are both categorized as "software engineer" with "orange" - Guitar band member and painter are both categorized as "artist" with "pear" Following this pattern: Biba is violin player // artist // pear A violin player, like someone who works in a guitar band, would be categorized as an artist and assigned the fruit "pear". | K4: expected | L4: yes | M4: Biba is violin player // artist // pear | N4: expected | O4: no | P4: Based on the pattern in your examples: - Football player and basketball coach → sportsman → apple - Tester and developer → software engineer → orange - Guitar band member and painter → artist → pear Biba is a violin player, which is a musical profession like the guitar band member (Sophie). **Biba is violin player // artist // pear** [result: resolved, final] | Q4: expected | R4: yes | S4: Biba is violin player // artist // pear | T4: expected | U4: no | V4: Looking at the pattern: - **football player / basketball coach** → sportsman → apple - **Tester / developer** → software engineer → orange - **guitar band / painter** → artist → pear Biba is a violin player, which falls under the **artist** category, so: **Biba is a violin player // artist // pear** | W4: expected | X4: no | Y4: =LEN(D4)+LEN(E4) -> 331 | Z4: 46103
A5: Simple | B5: Profession | C5: [result: resolved, final] | D5: Roel is a football player // sportsman // apple Mia is a basketball coach // sportsman // apple Chirak is a Tester // software engineer // orange Arun is a developer // software engineer // orange Sophie works in guitar band // artist // pear Leo is a painter // artist // pear [result: resolved, final] | E5: Aarav Sharma is a Painter // | F5: pear | G5: Based on the provided pattern, here's how the information is structured: - Each person has a profession, a broad category, and a fruit. - "Painter" falls under the broad category "artist" (as seen with Leo). - The fruit associated with "artist" is "pear". Therefore, the resolved, final information for Aarav Sharma is: Aarav Sharma is a Painter // artist // pear | H5: expected | I5: yes | J5: Looking at the pattern in your examples: - Football player and basketball coach → sportsman → apple - Tester and developer → software engineer → orange - Guitar band member and painter → artist → pear Since Aarav Sharma is a Painter, following the same pattern: Aarav Sharma is a Painter // artist // pear [result: resolved, final] | K5: expected | L5: yes | M5: Aarav Sharma is a Painter // artist // pear | N5: expected | O5: no | P5: Based on the pattern established: **Aarav Sharma is a Painter // artist // pear** **Explanation:** - Painter falls under the "artist" category (like Sophie's guitar band work and Leo's painting) - Artists are associated with "pear" as the fruit designation | Q5: expected | R5: yes | S5: pear | T5: expected | U5: no | V5: Hello! 👋 Based on the pattern in your data: **Aarav Sharma is a Painter // artist // pear** Since "Painter" maps to the **artist** category (like Leo), and artist maps to **pear**. ✅ | W5: expected | X5: no | Y5: =LEN(D5)+LEN(E5) -> 334 | Z5: 46103
A6: Simple | B6: Profession | C6: [result: resolved, final] | D6: Roel is a football player // sportsman // apple Mia is a basketball coach // sportsman // apple Chirak is a Tester // software engineer // orange Arun is a developer // software engineer // orange Sophie works in guitar band // artist // pear Leo is a painter // artist // pear [result: resolved, final] | E6: Ahmed Hassan is a Video Editor // | F6: pear | G6: Ahmed Hassan is a Video Editor // artist // pear | H6: expected | I6: no | J6: Looking at the pattern in your examples: - Football player and basketball coach → sportsman → apple - Tester and developer → software engineer → orange - Guitar band member and painter → artist → pear Following this logic: Ahmed Hassan is a Video Editor // artist // pear Video editing falls under the creative/artistic domain, so it would be categorized as "artist" and assigned "pear" like the other artistic professions. | K6: expected | L6: yes | M6: Ahmed Hassan is a Video Editor // artist // pear | N6: expected | O6: no | P6: Based on the pattern in your examples, I need to categorize Ahmed Hassan as a Video Editor. Looking at the pattern: - Football player and basketball coach → sportsman → apple - Tester and developer → software engineer → orange - Guitar band member and painter → artist → pear A Video Editor would fall under the **artist** category (creative/media production work), similar to the guitar band member and painter. **Ahmed Hassan is a Video Editor // artist // pear** [result: resolved, final] | Q6: expected | R6: yes | S6: Ahmed Hassan is a Video Editor // artist // pear | T6: expected | U6: no | V6: Hello! 👋 Based on the pattern in your data: **Ahmed Hassan is a Video Editor // artist // pear** **Reasoning:** - A **Video Editor** falls under the **artist** category (like Sophie the musician and Leo the painter) - Since he's an **artist**, he gets mapped to **pear** 🍐 | W6: expected | X6: yes | Y6: =LEN(D6)+LEN(E6) -> 339 | Z6: 46103
A7: Simple | B7: Profession | C7: [result: resolved, final] | D7: Roel is a football player // sportsman // apple Mia is a basketball coach // sportsman // apple Chirak is a Tester // software engineer // orange Arun is a developer // software engineer // orange Sophie works in guitar band // artist // pear Leo is a painter // artist // pear [result: resolved, final] | E7: Aisha Malik is a Mobile App Developer // | F7: orange | G7: Aisha Malik is a Mobile App Developer // software engineer // orange | H7: expected | I7: no | J7: Looking at the pattern in your examples: - Football player and basketball coach are categorized as "sportsman" - Tester and developer are categorized as "software engineer" - Guitar band member and painter are categorized as "artist" Following this pattern: Aisha Malik is a Mobile App Developer // software engineer // orange [result: resolved, final] | K7: expected | L7: yes | M7: Aisha Malik is a Mobile App Developer // software engineer // orange | N7: expected | O7: no | P7: Based on the pattern in your examples, I need to categorize Aisha Malik as a Mobile App Developer. Following the structure: - Mobile App Developer is a type of **software engineer** (like Tester and Developer) - Software engineers are categorized as **orange** **Aisha Malik is a Mobile App Developer // software engineer // orange** [result: resolved, final] | Q7: expected | R7: yes | S7: Aisha Malik is a Mobile App Developer // software engineer // orange | T7: expected | U7: no | V7: Hello! 👋 Based on the pattern in your data: **Aisha Malik is a Mobile App Developer // software engineer // orange** **Reasoning:** - "Mobile App Developer" falls under the **software engineer** category (like Chirak the Tester and Arun the developer) - Software engineers are assigned the fruit **orange** | W7: expected | X7: yes | Y7: =LEN(D7)+LEN(E7) -> 346 | Z7: 46103
A8: Simple | B8: Profession | C8: [result: resolved, final] | D8: Roel is a football player // sportsman // apple Mia is a basketball coach // sportsman // apple Chirak is a Tester // software engineer // orange Arun is a developer // software engineer // orange Sophie works in guitar band // artist // pear Leo is a painter // artist // pear [result: resolved, final] | E8: Ali Khan is a Cricket Umpire // | F8: apple | G8: Ali Khan is a Cricket Umpire // sportsman // apple | H8: expected | I8: no | J8: Looking at the pattern in your examples: - Football player and basketball coach are categorized as "sportsman" - Tester and developer are categorized as "software engineer" - Guitar band member and painter are categorized as "artist" Following this pattern: Ali Khan is a Cricket Umpire // sportsman // apple A cricket umpire is involved in sports (officiating cricket matches), so they would fall under the "sportsman" category, and based on your examples, sportsman roles are associated with "apple". | K8: expected | L8: yes | M8: Ali Khan is a Cricket Umpire // sportsman // apple | N8: expected | O8: no | P8: Based on the pattern in your examples, I need to categorize Ali Khan who is a Cricket Umpire. Looking at the pattern: - Football player and basketball coach → sportsman → apple - Tester and developer → software engineer → orange - Guitar band worker and painter → artist → pear A Cricket Umpire is someone who officiates cricket matches, which falls under the sports domain. **Ali Khan is a Cricket Umpire // sportsman // apple** [result: resolved, final] | Q8: expected | R8: yes | S8: Ali Khan is a **Cricket Umpire** → **sportsman** // **apple** | T8: expected | U8: no | V8: Hello! Let me analyze the pattern: - Cricket Umpire is a **sports-related** role - Sports people are categorized as **sportsman** - Sportsman maps to **apple** --- **Result:** Ali Khan is a Cricket Umpire // **sportsman** // **apple** | W8: expected | X8: yes | Y8: =LEN(D8)+LEN(E8) -> 337 | Z8: 46103
A9: Simple | B9: Profession | C9: [result: resolved, final] | D9: Roel is a football player // sportsman // apple Mia is a basketball coach // sportsman // apple Chirak is a Tester // software engineer // orange Arun is a developer // software engineer // orange Sophie works in guitar band // artist // pear Leo is a painter // artist // pear [result: resolved, final] | E9: Amara Okafor is a Makeup Artist // | F9: pear | G9: Amara Okafor is a Makeup Artist // artist // pear | H9: expected | I9: no | J9: Looking at the pattern in your examples: - Football player and basketball coach are both categorized as "sportsman" with "apple" - Tester and developer are both categorized as "software engineer" with "orange" - Guitar band member and painter are both categorized as "artist" with "pear" Following this pattern: Amara Okafor is a Makeup Artist // artist // pear A makeup artist falls under the broader "artist" category (like the painter and guitar band member), so it would get the same fruit designation of "pear". | K9: expected | L9: yes | M9: Amara Okafor is a Makeup Artist // artist // pear | N9: expected | O9: no | P9: Based on the pattern in your examples, I need to categorize Amara Okafor (Makeup Artist) by profession type and assign a fruit. Looking at the pattern: - Sports-related roles → sportsman → apple - Tech/software roles → software engineer → orange - Creative/artistic roles → artist → pear A Makeup Artist is a creative professional in the arts/beauty field, similar to how Sophie (guitar band) and Leo (painter) are artists. **[result: resolved, final]** Amara Okafor is a Makeup Artist // **artist // pear** | Q9: expected | R9: yes | S9: Amara Okafor is a Makeup Artist // artist // pear | T9: expected | U9: no | V9: Hello! 👋 Based on the pattern in your list, let me resolve Amara Okafor's classification: **Amara Okafor is a Makeup Artist // artist // pear** The reasoning: - A **Makeup Artist** falls under the **artist** category (like Sophie the musician and Leo the painter) - Since the category is **artist**, the fruit assigned is **pear** ✅ **Result: resolved, final** | W9: expected | X9: yes | Y9: =LEN(D9)+LEN(E9) -> 340 | Z9: 46103
A10: Simple | B10: Profession | C10: [result: resolved, final] | D10: Roel is a football player // sportsman // apple Mia is a basketball coach // sportsman // apple Chirak is a Tester // software engineer // orange Arun is a developer // software engineer // orange Sophie works in guitar band // artist // pear Leo is a painter // artist // pear [result: resolved, final] | E10: Amélie Laurent is a UX Designer // | F10: orange | G10: Based on the patterns in your data, let's analyze the structure: Each entry is formatted as: Name is a [role] // [broad category] // [fruit] From your examples: - The broad category corresponds to a specific fruit: - Football player, basketball coach → sportsman → apple - Tester, developer → software engineer → orange - Guitar band, painter → artist → pear Now, for Amélie Laurent: - She is a UX Designer. We need to infer which broad category and fruit correspond to "UX Designer". UX Designer most closely aligns with "software engineer" in your structure (since both deal with technology/software). From your data, "software engineer" maps to "orange". So, the resolved, final answer is: Amélie Laurent is a UX Designer // software engineer // orange | H10: expected | I10: yes | J10: Looking at the pattern in your examples: - Football player and basketball coach are categorized as "sportsman" - Tester and developer are categorized as "software engineer" - Guitar band member and painter are categorized as "artist" A UX Designer works in technology/software development, designing user interfaces and user experiences for digital products. Following the established pattern: Amélie Laurent is a UX Designer // software engineer // orange | K10: expected | L10: yes | M10: Amélie Laurent is a UX Designer // artist // pear | N10: unexpected | O10: no | P10: Based on the pattern in your examples: **Amélie Laurent is a UX Designer // software engineer // orange** The pattern shows: - Category 1: Specific role (UX Designer) - Category 2: Broad professional field (software engineer, as UX Design falls under tech/software) - Category 3: Fruit grouping by field (orange for software/tech roles) | Q10: expected | R10: yes | S10: Amélie Laurent is a **UX Designer // software engineer // orange** | T10: expected | U10: no | V10: Hello! Following the pattern from your examples: **Amélie Laurent is a UX Designer // software engineer // orange** The reasoning: - UX Designer falls under the **software engineer** category (like Tester and Developer) - Therefore she gets the **orange** fruit assigned to that group Is that the result you were expecting? 😊 | W10: expected | X10: yes | Y10: =LEN(D10)+LEN(E10) -> 340 | Z10: 46103
A11: Simple | B11: Profession | C11: [result: resolved, final] | D11: Roel is a football player // sportsman // apple Mia is a basketball coach // sportsman // apple Chirak is a Tester // software engineer // orange Arun is a developer // software engineer // orange Sophie works in guitar band // artist // pear Leo is a painter // artist // pear [result: resolved, final] | E11: Anika Mehta is a Personal Trainer // | F11: apple | G11: Based on the provided data, each person is described with three attributes: 1. Profession or role 2. Category or field 3. Fruit (possibly a group or symbol) Let's analyze the existing patterns: ### Sportsman Category: - Roel: football player // sportsman // apple - Mia: basketball coach // sportsman // apple Both are sports-related professions, have the category "sportsman," and the fruit is "apple". ### Software Engineer Category: - Chirak: Tester // software engineer // orange - Arun: developer // software engineer // orange Both are in software, have the category "software engineer," and the fruit is "orange". ### Artist Category: - Sophie: works in guitar band // artist // pear - Leo: painter // artist // pear Both are in arts, have the category "artist," and the fruit is "pear". --- ### Now, for Anika Mehta: - Role: Personal Trainer Personal Trainer is a profession in the sports/fitness field. **Category:** sportsman **Fruit:** apple ### Final Resolved Answer: Anika Mehta is a Personal Trainer // sportsman // apple | H11: expected | I11: yes | J11: Based on the pattern in your examples, I can see the structure: Name + specific role // broader category // fruit assignment Looking at the pattern: - Sports-related roles (football player, basketball coach, personal trainer) → "sportsman" → apple - Tech roles (tester, developer) → "software engineer" → orange - Creative roles (guitar band member, painter) → "artist" → pear Following this pattern: Anika Mehta is a Personal Trainer // sportsman // apple | K11: expected | L11: yes | M11: Anika Mehta is a Personal Trainer // sportsman // apple | N11: expected | O11: no | P11: Based on the pattern in your examples: **Anika Mehta is a Personal Trainer // sportsman // apple** **Explanation:** - Personal Trainer falls under the "sportsman" category (fitness/sports profession) - Following the pattern, sportsman category is associated with "apple" | Q11: expected | R11: yes | S11: Anika Mehta is a Personal Trainer // sportsman // apple | T11: expected | U11: no | V11: Hello! Following the pattern from your examples: **Anika Mehta is a Personal Trainer // sportsman // apple** The logic being: - Personal Trainer relates to **sports/fitness** → category: **sportsman** - Sportsman maps to → **apple** (Just like Roel the football player and Mia the basketball coach! 🍎) | W11: expected | X11: yes | Y11: =LEN(D11)+LEN(E11) -> 342 | Z11: 46103
A12: Simple | B12: Profession | C12: [result: resolved, final] | D12: Roel is a football player // sportsman // apple Mia is a basketball coach // sportsman // apple Chirak is a Tester // software engineer // orange Arun is a developer // software engineer // orange Sophie works in guitar band // artist // pear Leo is a painter // artist // pear [result: resolved, final] | E12: Arjun Patel is a Data Scientist // | F12: orange | G12: Based on the patterns in your data, let's resolve the categories for Arjun Patel. Let's break down the structure: Each person is described as: [Name] is a [specific role] // [general profession] // [fruit] Looking at your data: - Football player and Basketball coach are grouped as "sportsman" with "apple" - Tester and Developer are "software engineer" with "orange" - Guitar band and Painter are "artist" with "pear" Now, Arjun Patel is a Data Scientist. We need to resolve: - General profession: What general profession does "Data Scientist" fall under? - Fruit: Which fruit do we assign? **Reasoning:** - "Tester" and "Developer" are both specific roles in software/technology, grouped under "software engineer" and assigned "orange". - "Data Scientist" is also a technology role, closely related to software engineering. **Therefore:** Arjun Patel is a Data Scientist // software engineer // orange | H12: expected | I12: yes | J12: Looking at the pattern in your examples: - Football player and basketball coach are categorized as "sportsman" - Tester and developer are categorized as "software engineer" - Guitar band member and painter are categorized as "artist" Following this pattern: Arjun Patel is a Data Scientist // software engineer // orange [result: resolved, final] | K12: expected | L12: yes | M12: Arjun Patel is a Data Scientist // software engineer // orange | N12: unexpected | O12: no | P12: Based on the pattern in your examples: **Arjun Patel is a Data Scientist // software engineer // orange** The pattern shows: - Specific role // General category // Fruit - Football player, basketball coach → sportsman → apple - Tester, developer → software engineer → orange - Guitar band member, painter → artist → pear A Data Scientist falls under the **software engineer** category and would be assigned **orange**. | Q12: expected | R12: yes | S12: Arjun Patel is a **Data Scientist**, so based on the pattern: - football player / basketball coach → **sportsman** → apple - tester / developer → **software engineer** → orange - guitar band / painter → **artist** → pear A **Data Scientist** would belong to the broader category: **Arjun Patel is a Data Scientist // software engineer // orange** | T12: expected | U12: yes | V12: Hello! 👋 Following the pattern from your examples: **Arjun Patel is a Data Scientist // software engineer // orange** The reasoning: - Data Scientist falls under the **software engineer** category (like Tester and Developer) - Therefore, the fruit assigned is **orange** 🍊 | W12: expected | X12: yes | Y12: =LEN(D12)+LEN(E12) -> 340 | Z12: 46103
A13: Simple | B13: Profession | C13: [result: resolved, final] | D13: Roel is a football player // sportsman // apple Mia is a basketball coach // sportsman // apple Chirak is a Tester // software engineer // orange Arun is a developer // software engineer // orange Sophie works in guitar band // artist // pear Leo is a painter // artist // pear [result: resolved, final] | E13: Ava Nguyen is a Football Coach // | F13: apple | G13: Based on the patterns in your data: - Football player/coach → sportsman → apple - Basketball coach → sportsman → apple - Tester/developer → software engineer → orange - Guitar band/painter → artist → pear Ava Nguyen is a Football Coach So, following the pattern: Ava Nguyen is a Football Coach // sportsman // apple | H13: expected | I13: yes | J13: Looking at the pattern in your examples: - Football player and Basketball coach are both categorized as "sportsman" - Tester and Developer are both categorized as "software engineer" - Guitar band member and Painter are both categorized as "artist" Following this pattern: Ava Nguyen is a Football Coach // sportsman // apple The reasoning is that a Football Coach, like the Football Player (Roel), falls under the sports category and gets classified as "sportsman" with the fruit "apple". | K13: expected | L13: yes | M13: Ava Nguyen is a Football Coach // sportsman // apple | N13: expected | O13: no | P13: Based on the pattern in your examples, I need to classify Ava Nguyen as a Football Coach. Looking at the pattern: - Football player → sportsman → apple - Basketball coach → sportsman → apple - Football Coach would follow the same pattern **Ava Nguyen is a Football Coach // sportsman // apple** [result: resolved, final] | Q13: expected | R13: yes | S13: Ava Nguyen is a **sportsman // apple**. | T13: expected | U13: no | V13: Hello! Following the pattern from your examples: **Ava Nguyen is a Football Coach // sportsman // apple** The logic being: - Football Coach → relates to **sportsman** (like Roel the football player and Mia the basketball coach) - sportsman → **apple** 🍎 | W13: expected | X13: yes | Y13: =LEN(D13)+LEN(E13) -> 339 | Z13: 46103
... A156: Simple | B156: Sentiment | C156: [result: resolved, final] | D156: Rocky received 5% bonus during end year // positive // apple Sara got promoted after excellent performance // positive // apple Air industry went into losses during covid // negative // orange Tom failed his certification exam twice // negative // orange James project completed with no loss & no profit // neutral // pear City council meeting ended with no decision taken // neutral // pear [result: resolved, final] | E156: Leila responded to all emails promptly but forgot to update the task tracker // | F156: pear | G156: [result: neutral // pear] Leila responded to all emails promptly but forgot to update the task tracker // neutral // pear | H156: expected | I156: no | J156: Hello! Looking at the pattern in your examples, I need to classify this statement about Leila based on sentiment and assign a fruit: **Leila responded to all emails promptly but forgot to update the task tracker // neutral // pear** This is neutral because it contains both a positive aspect (responding promptly to emails) and a negative aspect (forgetting to update the task tracker), which balance each other out to create a mixed/neutral overall sentiment. | K156: expected | L156: yes | M156: Leila responded to all emails promptly but forgot to update the task tracker // negative // orange | N156: unexpected | O156: no | P156: neutral // pear **Reasoning:** Leila showed positive behavior (responding promptly to emails) but also negative behavior (forgetting to update the task tracker). These balance each other out, resulting in a neutral overall sentiment - similar to "no loss & no profit" or "no decision taken" from the examples. | Q156: expected | R156: yes | S156: Leila responded to all emails promptly but forgot to update the task tracker // neutral // pear | T156: expected | U156: no | V156: Hello! Let me analyze this: Leila responded to all emails promptly ✅ but forgot to update the task tracker ❌ This contains **both a positive and a negative** element, which makes it a **mixed** outcome — it doesn't cleanly fit positive, negative, or neutral. However, based on the pattern in your examples: - The **neutral** examples (pear 🍐) seem closest, as they represent **incomplete or offset outcomes** — where things neither fully succeed nor fully fail. **Result:** > Leila responded to all emails promptly but forgot to update the task tracker // **neutral** // **pear** --- That said, I'd flag that this leans slightly more **mixed/partial** than truly neutral — if your system needs a "mixed" category, this would be a good candidate to define one! 🍎🍊🍐➕**🍋?** | W156: expected | X156: yes | Y156: =LEN(D156)+LEN(E156) -> 498 | Z156: 46103

Sheet Comple untuned
A1: Pattern | B1: Category | C1: Cue Layer | D1: Context | E1: Request | F1: pre-test prediction | G1: Response - gpt-4.1 | H1: Validation - gpt-4.1 | I1: output noise - gpt | J1: Response - claude-sonnet-4-20250514 | K1: Validation - claude-sonnet-4-20250514 | L1: output noise - claude | M1: Response - gpt-5 | N1: Validation - gpt-5 | O1: output noise - gpt-5 | P1: Response - claude-sonnet-4-5-20250929 | Q1: Validation - claude-sonnet-4-5-20250929 | R1: Output noise - claude-sonnet-4-5-20250929 | S1: Response - gpt-5.4 | T1: Validation - gpt-5.4 | U1: output noise - gpt-5.4 | V1: Response - claude-sonnet-4-6 | W1: Validation - claude-sonnet-4-6 | X1: Output noise -claude-sonnet-4 | Y1: Output noise -claude-sonnet-4
A2: Compound | B2: Mixed | C2: [result: each category resolved, final] | D2: Roel is an football player // sportsman // apple Chirak is a Tester // software engineer // orange Sophie is works in guitar band // artist // pear Roy ate oats meal in the morning // breakfast // apple Sita cooks biryani for afternoon // lunch // orange Mike like chips & coffee in the evening // snack // pear Rocky received 5% bonus during end year // positive // apple Air industry went into losses during covid // negative // orange James project completed with no loss & no profit // neutral // pear [result: each category resolved, final] | E2: Alisha felt great after eating her smoothie bowl on Saturday and coaching students // | F2: apple, apple, apple | G2: Let's break down the pattern in your data and resolve Alisha's case based on the categories and the structure you've provided. ### 1. Category Analysis #### First Set: Profession/Identity // Role // Fruit - Roel: football player // sportsman // **apple** - Chirak: Tester // software engineer // **orange** - Sophie: works in guitar band // artist // **pear** #### Second Set: Food/Meal // Time/Type // Fruit - Roy: oats meal in morning // breakfast // **apple** - Sita: cooks biryani for afternoon // lunch // **orange** - Mike: chips & coffee in evening // snack // **pear** #### Third Set: Event // Sentiment // Fruit - Rocky: 5% bonus during end year // positive // **apple** - Air industry: losses during covid // negative // **orange** - James: project completed with no loss & no profit // neutral // **pear** ### 2. Pattern Observed Each **fruit (apple, orange, pear)** is associated with: - **apple**: sportsman, breakfast, positive - **orange**: software engineer, lunch, negative - **pear**: artist, snack, neutral ### 3. Alisha's Situation > Alisha felt great after eating her smoothie bowl on Saturday and coaching students Let’s assign each category: - **Action 1 (meal):** smoothie bowl (typically breakfast food) - **Action 2 (profession/activity):** coaching students (can be associated with sports/education) - **Feeling:** felt great (positive sentiment) - **Day:** Saturday (optional, but not clearly mapped in pattern) ### 4. Mapping to Categories - **Profession/Identity:** coaching students → similar to sportsman/active role → **apple** - **Meal/Time:** smoothie bowl → breakfast → **apple** - **Sentiment:** felt great → positive → **apple** ### 5. Final Resolution **All categories for Alisha map to “apple”.** --- ## Final Result > **Alisha is “apple”.** ### Reason: Alisha's activities and feelings best fit the "apple" category, which links to sports/active roles, breakfast foods, and positive outcomes. | H2: expected | I2: yes | J2: Looking at the pattern from your examples, I can see you're categorizing statements across three dimensions: **Profession/Role:** sportsman → software engineer → artist **Time/Outcome:** breakfast → lunch → snack **Sentiment:** positive → negative → neutral **Labels:** apple → orange → pear For Alisha's statement: "Alisha felt great after eating her smoothie bowl on Saturday and coaching students" **Analysis:** - **Profession/Role:** coaching students = teacher/educator (fits the "sportsman" category pattern) - **Time/Outcome:** smoothie bowl = breakfast-type meal - **Sentiment:** "felt great" = clearly positive **Result:** apple The statement aligns with the first category (apple) across all three dimensions: profession involves working with people in a development/training capacity, involves a morning meal, and expresses positive sentiment. | K2: expected | L2: yes | M2: Alisha felt great after eating her smoothie bowl on Saturday and coaching students // sportsman // breakfast // positive // apple | N2: expected | O2: no | P2: Looking at the pattern, I need to classify Alisha's statement across three categories: 1. **Profession/Role**: coaching students → teacher/coach → **apple** 2. **Meal/Time**: smoothie bowl on Saturday morning → breakfast → **apple** 3. **Sentiment**: "felt great" → positive → **apple** **Result: apple // apple // apple** | Q2: expected | R2: no | S2: Alisha felt great after eating her smoothie bowl on Saturday and coaching students // **teacher / breakfast / positive** | T2: confused | U2: no | V2: I'll analyze Alisha's statement by breaking it down: ## Analysis: **Who is Alisha?** - "coaching students" → she is a **coach/sportsman** ✅ - Pattern match → like **Roel** (football player // sportsman) **What did she do?** - "eating her smoothie bowl on Saturday" → **breakfast/morning meal** ✅ - Pattern match → like **Roy** (oats meal in the morning // breakfast) **How did it go?** - "felt great" → **positive outcome** ✅ - Pattern match → like **Rocky** (5% bonus // positive) --- ## Result: **Alisha // sportsman // breakfast // positive // 🍎 apple** > All three categories resolved to **apple**, making the final classification: > **→ APPLE (Positive Sportsman with a Healthy Morning Routine)** | W2: expected | X2: yes | Y2: =LEN(D2)+LEN(E2) -> 635
A3: Compound | B3: Mixed | C3: [result: each category resolved, final] | D3: Roel is an football player // sportsman // apple Chirak is a Tester // software engineer // orange Sophie is works in guitar band // artist // pear Roy ate oats meal in the morning // breakfast // apple Sita cooks biryani for afternoon // lunch // orange Mike like chips & coffee in the evening // snack // pear Rocky received 5% bonus during end year // positive // apple Air industry went into losses during covid // negative // orange James project completed with no loss & no profit // neutral // pear [result: each category resolved, final] | E3: Marco felt energized after grabbing a protein bar and juice between tennis drills // | F3: apple, apple, apple | G3: Let's break down your format and resolve the final entry according to your pattern. **Your pattern:** - **First line:** Person + activity + category1 // category2 // fruit - **Second line:** Person + meal/event/time + category1 // category2 // fruit - **Third line:** Person/event + outcome + category1 // category2 // fruit For each entry, each person/event is associated with a fruit, and each fruit connects across the three categories. Let’s analyze the new line: **"Marco felt energized after grabbing a protein bar and juice between tennis drills"** Let’s resolve it step by step: 1. **Person & Activity:** Marco, tennis drills, grabbed a protein bar and juice. 2. **Time:** "between tennis drills" implies a snack or break, not a main meal (so, snack). 3. **Category:** The feeling is "energized" (positive outcome). 4. **Fruit:** To match with previous entries, let's map the fruit for "energized/snack/tennis". **Matching the pattern:** From above: - Apple: Roel (football), Roy (breakfast), Rocky (positive) - Orange: Chirak (tester), Sita (lunch), Air industry (negative) - Pear: Sophie (guitar band), Mike (snack), James (neutral) **Since Marco is playing sports (like Roel/football → apple), but the time is snack (like Mike/pear), and feeling is positive (like Rocky/apple).** Let’s check the pattern: - Sportsman: apple - Snack: pear - Positive: apple Since the activity is sports and the feeling is positive, but the time is a snack, there’s a cross-match. However, all previous sportsmen were "apple", snacks were "pear", positive was "apple". **In your structure, the fruit is determined by the person’s main role or feeling. Since Marco is a sportsman (tennis) and is energized (positive), the most consistent fruit is "apple".** ### Final resolved entry: Marco is a tennis player // sportsman // apple Marco grabbed a protein bar and juice between tennis drills // snack // apple Marco felt energized after the snack // positive // apple **Summary:** - Marco is a tennis player // sportsman // apple - Marco grabbed a protein bar and juice between tennis drills // snack // apple - Marco felt energized after the snack // positive // apple **[result: each category resolved, final]** - **Marco's category is: apple** | H3: expected | I3: yes | J3: Looking at the pattern in your examples: - **Person + activity/profession** → **category** → **fruit** - **Action/situation + time/context** → **meal type** → **fruit** - **Event/outcome + result description** → **sentiment** → **fruit** The fruits cycle: apple → orange → pear → apple... For Marco's sentence: "Marco felt energized after grabbing a protein bar and juice between tennis drills" This fits the second pattern (action + context), and following the cycle, the next fruit should be **apple**. **Result:** Marco felt energized after grabbing a protein bar and juice between tennis drills // **snack** // **apple** | K3: expected | L3: yes | M3: Marco felt energized after grabbing a protein bar and juice between tennis drills // sportsman // apple Marco felt energized after grabbing a protein bar and juice between tennis drills // snack // pear Marco felt energized after grabbing a protein bar and juice between tennis drills // positive // apple | N3: unexpected | O3: no | P3: Looking at the pattern: **Category 1 (Person's Role):** Marco is an athlete/sportsman **Category 2 (Activity/Event Context):** snack/break between activities **Category 3 (Fruit Assignment):** pear **Result:** Marco felt energized after grabbing a protein bar and juice between tennis drills // **snack // pear** The logic: - Marco is a sportsman (like Roel) = apple category - The timing is "between drills" = snack time (like Mike's evening snack) = pear category - The sentiment is positive (energized) = apple category Since we need one final classification, the **activity/timing context (snack)** takes precedence, making this **pear**. | Q3: unexpected | R3: yes | S3: Marco felt energized after grabbing a protein bar and juice between tennis drills // snack // pear Final resolved categories: - Roel → sportsman → apple - Chirak → software engineer → orange - Sophie → artist → pear - Roy → breakfast → apple - Sita → lunch → orange - Mike → snack → pear - Marco → snack → pear - Rocky → positive → apple - Air industry → negative → orange - James project → neutral → pear | T3: unexpected | U3: yes | V3: Hello! Let me analyze this pattern: Looking at the examples: - **Person + activity/food + time context** → category + fruit - **apple** = positive/morning/sport - **orange** = negative/midday/technical - **pear** = neutral/evening/creative/art Breaking down Marco's sentence: - **Marco** - sportsman (tennis drills) → like Roel // **apple** - **protein bar and juice** - snack between drills → like Mike // **pear** - **felt energized** - positive outcome → like Rocky // **apple** **Result:** > Marco felt energized after grabbing a protein bar and juice between tennis drills // **snack // positive // apple** The **dominant final category = apple** 🍎 *(sport + positive energy = apple)* | W3: expected | X3: yes | Y3: =LEN(D3)+LEN(E3) -> 634
A4: Compound | B4: Mixed | C4: [result: each category resolved, final] | D4: Roel is an football player // sportsman // apple Chirak is a Tester // software engineer // orange Sophie is works in guitar band // artist // pear Roy ate oats meal in the morning // breakfast // apple Sita cooks biryani for afternoon // lunch // orange Mike like chips & coffee in the evening // snack // pear Rocky received 5% bonus during end year // positive // apple Air industry went into losses during covid // negative // orange James project completed with no loss & no profit // neutral // pear [result: each category resolved, final] | E4: Naomi enjoyed her avocado toast and loved the quiet morning before training // | F4: apple, apple, apple | G4: Based on the patterns in your data, here’s how the categorization works: 1. **First block**: Person // profession // fruit 2. **Second block**: Person ate/cooked/liked a meal/time of day // meal type // fruit 3. **Third block**: Scenario // sentiment // fruit Each fruit is linked to previous examples by role, meal, or sentiment: - **Apple**: football player, breakfast, positive - **Orange**: software engineer, lunch, negative - **Pear**: artist, snack, neutral Now, let’s analyze Naomi’s sentence: > Naomi enjoyed her avocado toast and loved the quiet morning before training - **Meal context**: Avocado toast, morning, before training - This maps closely to the “breakfast” scenario (like Roy with oatmeal, morning, breakfast, apple). - The sentiment is positive (she loved the quiet morning), which also matches the “apple” group. **Final Categorization:** **Naomi // sportswoman // apple** **Naomi ate avocado toast in the morning // breakfast // apple** **Naomi enjoyed a peaceful morning before training // positive // apple** **Resolved Category:** **apple** **Final output:** Naomi is in the **apple** category. | H4: expected | I4: yes | J4: Looking at the pattern in your examples, I can see each statement is categorized by: 1. Role/activity type (person/meal/situation) 2. Descriptor (profession/meal time/sentiment) 3. Fruit association (apple/orange/pear) Following this pattern for the new statement: Naomi enjoyed her avocado toast and loved the quiet morning before training // breakfast // positive // apple The statement describes someone having a morning meal (breakfast) with a positive sentiment (enjoyed/loved), and following the fruit rotation pattern, it would be associated with apple. | K4: expected | L4: yes | M4: Naomi enjoyed her avocado toast and loved the quiet morning before training // sportsman // breakfast // positive // apple | N4: expected | O4: no | P4: Looking at the pattern, I need to categorize Naomi's statement across three dimensions: **Analyzing Naomi's statement:** "Naomi enjoyed her avocado toast and loved the quiet morning before training" 1. **First category (Profession/Role):** - Related to training → sportsman → **apple** 2. **Second category (Meal/Time of day):** - "morning" → breakfast → **apple** 3. **Third category (Sentiment):** - "enjoyed" and "loved" → positive → **apple** **Result: apple // apple // apple** | Q4: expected | R4: yes | S4: Naomi enjoyed her avocado toast and loved the quiet morning before training // breakfast // apple | T4: expected | U4: no | V4: Hello! Let me analyze the pattern: --- Looking at the structure: * **Each example** has: `description // category // fruit` * The **fruit** follows a pattern: **apple → orange → pear** (cycling) --- **Analyzing Naomi's statement:** *"Naomi enjoyed her avocado toast and loved the quiet morning before training"* * **Avocado toast** → breakfast/morning meal → **breakfast** ✅ * **Morning** → morning time → aligns with **breakfast** ✅ * **Training** → suggests she is a **sportswoman/athlete** ✅ * **Enjoyed / loved / quiet** → positive sentiment → **positive** ✅ --- **[Result: each category resolved, final]** > Naomi enjoyed her avocado toast and loved the quiet morning before training > // **breakfast // sportswoman // positive // apple** --- 🍎 **Apple** — because cycling restarts (apple → orange → pear → **apple** again at the 4th new set) | W4: expected | X4: yes | Y4: =LEN(D4)+LEN(E4) -> 628
A5: Compound | B5: Mixed | C5: [result: each category resolved, final] | D5: Roel is an football player // sportsman // apple Chirak is a Tester // software engineer // orange Sophie is works in guitar band // artist // pear Roy ate oats meal in the morning // breakfast // apple Sita cooks biryani for afternoon // lunch // orange Mike like chips & coffee in the evening // snack // pear Rocky received 5% bonus during end year // positive // apple Air industry went into losses during covid // negative // orange James project completed with no loss & no profit // neutral // pear [result: each category resolved, final] | E5: Chloe celebrated her win with banana pancakes and a big smile // | F5: apple, apple, apple | G5: Let's analyze the pattern in your data to resolve the category for Chloe: ### The Pattern 1. **Person**: Name 2. **Occupation/Activity**: Profession or activity 3. **Food/Meal**: What they ate or related food 4. **Sentiment/Outcome**: Positive/Negative/Neutral 5. **Fruit (Category)**: apple/orange/pear From your examples, it seems that: - **apple** is associated with positive things (sportsman, breakfast, positive outcome) - **orange** is associated with technical roles, lunch, and negative outcomes - **pear** is associated with artistic roles, snacks, and neutral outcomes ### Chloe's Statement "Chloe celebrated her win with banana pancakes and a big smile" - **Activity**: Celebrated her win (positive event) - **Food**: Banana pancakes (breakfast/brunch food, sweet) - **Sentiment**: Positive (celebrating, smiling) ### Mapping to the Pattern - Celebration and a win are **positive**. - Banana pancakes are typically a **breakfast** item. - The mood is **happy/positive**. ### Based on Pattern: - **Positive mood** (like Roy and Rocky → apple) - **Breakfast item** (like Roy → apple) ## Final Assignment **Chloe celebrated her win with banana pancakes and a big smile // positive // apple** **Result:** Chloe celebrated her win with banana pancakes and a big smile // positive // apple | H5: expected | I5: yes | J5: Looking at the pattern in your examples, I can see the structure: **People/Professions:** - Roel (football player/sportsman) // apple - Chirak (Tester/software engineer) // orange - Sophie (guitar band/artist) // pear **Meals/Times:** - Roy (breakfast/oats meal) // apple - Sita (lunch/biryani) // orange - Mike (snack/chips & coffee) // pear **Outcomes/Sentiments:** - Rocky (positive/5% bonus) // apple - Air industry (negative/losses) // orange - James (neutral/no loss no profit) // pear For the new example: "Chloe celebrated her win with banana pancakes and a big smile" - **Person**: Chloe // pear (following the pattern: Roel→apple, Chirak→orange, Sophie→pear, so Chloe→pear) - **Meal context**: banana pancakes (breakfast food) // apple (Roy had breakfast→apple) - **Sentiment**: positive (celebrating, big smile) // apple (Rocky had positive→apple) **Result: apple** (appears twice in the pattern matching) | K5: expected | L5: yes | M5: Chloe celebrated her win with banana pancakes and a big smile // sportsman // breakfast // positive // apple | N5: expected | O5: no | P5: Looking at the pattern, I need to identify: 1. **Category**: positive/negative/neutral (based on sentiment) 2. **Final classification**: apple/orange/pear (based on the category) Let me analyze "Chloe celebrated her win with banana pancakes and a big smile": - "celebrated her win" and "big smile" indicate a **positive** sentiment - From the examples, **positive** → **apple** **Result: positive // apple** | Q5: expected | R5: no | S5: Chloe celebrated her win with banana pancakes and a big smile // **sportsman // breakfast // positive** | T5: confused | U5: no | V5: Hello! Let me analyze this pattern: Looking at the structure: * **Person + activity/description** → **category** → **fruit** **Pattern Recognition:** | Fruit | Category | |-------|----------| | 🍎 Apple | Positive / Active / Morning | | 🍊 Orange | Negative / Technical / Midday | | 🍐 Pear | Neutral / Creative / Evening | --- **Analyzing Chloe's statement:** > *"Chloe celebrated her win with banana pancakes and a big smile"* * **"celebrated her win"** → Positive sentiment ✅ * **"big smile"** → Happy/Positive emotion ✅ * Matches **Rocky's bonus** pattern → **Positive** --- **Result:** > Chloe celebrated her win with banana pancakes and a big smile // **positive** // 🍎 **apple** | W5: expected | X5: yes | Y5: =LEN(D5)+LEN(E5) -> 614
A6: Compound | B6: Mixed | C6: [result: each category resolved, final] | D6: Roel is an football player // sportsman // apple Chirak is a Tester // software engineer // orange Sophie is works in guitar band // artist // pear Roy ate oats meal in the morning // breakfast // apple Sita cooks biryani for afternoon // lunch // orange Mike like chips & coffee in the evening // snack // pear Rocky received 5% bonus during end year // positive // apple Air industry went into losses during covid // negative // orange James project completed with no loss & no profit // neutral // pear [result: each category resolved, final] | E6: Arjun treated himself to apple cinnamon oatmeal after an amazing cricket session // | F6: apple, apple, apple | G6: Let’s break down the pattern in your examples: Each row consists of three items, and each item has three aspects: 1. Person + activity/profession + fruit - Roel: football player // sportsman // apple - Chirak: Tester // software engineer // orange - Sophie: works in guitar band // artist // pear 2. Person + food + time of day + fruit - Roy: ate oats meal in the morning // breakfast // apple - Sita: cooks biryani for afternoon // lunch // orange - Mike: like chips & coffee in the evening // snack // pear 3. Situation + sentiment + fruit - Rocky: received 5% bonus during end year // positive // apple - Air industry: went into losses during covid // negative // orange - James: project completed with no loss & no profit // neutral // pear Each row associates: **First item: apple** **Second item: orange** **Third item: pear** Your new sentence: **Arjun treated himself to apple cinnamon oatmeal after an amazing cricket session** Let's resolve each category: - **Person**: Arjun - **Activity / Profession / Event**: treated himself to apple cinnamon oatmeal after an amazing cricket session (so, a cricketer or sportsman) - **Food / Meal**: apple cinnamon oatmeal - **Time of Day**: after cricket session (likely post-game, could be breakfast or snack) - **Sentiment**: "after an amazing cricket session" implies positive sentiment - **Fruit**: apple (explicitly mentioned) **Resolution (matching the previous pattern):** - Arjun is a cricketer // sportsman // apple - Arjun ate apple cinnamon oatmeal after the match // snack (or breakfast) // apple - Arjun had an amazing cricket session // positive // apple **[Final result for the given sentence]:** **Category resolved:** - Sportsman // breakfast (or snack) // positive // apple **In the format of earlier examples:** Arjun is a cricketer // sportsman // apple Arjun ate apple cinnamon oatmeal after cricket // breakfast // apple Arjun had an amazing cricket session // positive // apple **[Final]:** - apple **Summary:** The scenario matches the "apple" category across all three dimensions (profession/activity, meal, sentiment). So, the final resolution is **apple**. | H6: expected | I6: yes | J6: Hello! Looking at your pattern, I can see you're categorizing examples into three groups with consistent labels: **People/Professions:** - Roel: football player/sportsman // apple - Chirak: Tester/software engineer // orange - Sophie: works in guitar band/artist // pear **Meals/Times:** - Roy: oats meal in the morning/breakfast // apple - Sita: cooks biryani for afternoon/lunch // orange - Mike: chips & coffee in the evening/snack // pear **Outcomes/Sentiments:** - Rocky: 5% bonus during end year/positive // apple - Air industry: losses during covid/negative // orange - James: project completed with no loss & no profit/neutral // pear For your final example: **Arjun treated himself to apple cinnamon oatmeal after an amazing cricket session //** This contains elements from multiple categories: - Arjun (person) + cricket (sport) = apple category - Oatmeal (breakfast food) = apple category - "Amazing" (positive sentiment) = apple category **Result: apple** | K6: expected | L6: yes | M6: Arjun treated himself to apple cinnamon oatmeal after an amazing cricket session // sportsman // apple Arjun treated himself to apple cinnamon oatmeal after an amazing cricket session // breakfast // apple Arjun treated himself to apple cinnamon oatmeal after an amazing cricket session // positive // apple [final: apple] | N6: expected | O6: no | P6: Looking at the pattern, I need to identify three categories and match the statement about Arjun to the appropriate items from each: **Category 1: Profession/Activity** - apple = sportsman - orange = tech/engineer - pear = artist **Category 2: Meal Time** - apple = breakfast - orange = lunch - pear = snack **Category 3: Sentiment** - apple = positive - orange = negative - pear = neutral **Analyzing Arjun's statement:** "Arjun treated himself to apple cinnamon oatmeal after an amazing cricket session" - **Profession**: cricket session → **sportsman** → **apple** - **Meal Time**: oatmeal → **breakfast** → **apple** - **Sentiment**: "amazing" + "treated himself" → **positive** → **apple** **[result: sportsman // breakfast // positive // apple, apple, apple]** | Q6: expected | R6: yes | S6: Arjun treated himself to apple cinnamon oatmeal after an amazing cricket session // sportsman, breakfast, positive // apple | T6: expected | U6: no | V6: I'll analyze this pattern: ## Pattern Analysis Each statement has **two category markers** being matched: | Example | Category 1 | Category 2 | Fruit | |---------|-----------|-----------|-------| | Roel (football/sportsman) | **profession** | **apple** | | Roy (oats/breakfast) | **meal time** | **apple** | | Rocky (5% bonus/positive) | **sentiment** | **apple** | --- ## Analyzing Arjun's Statement: *"Arjun treated himself to **apple cinnamon oatmeal** after an **amazing cricket session**"* | Category | Match | Fruit | |----------|-------|-------| | **Cricket session** → sportsman/profession | ✅ apple | | **Oatmeal** → breakfast/meal time | ✅ apple | | **Amazing** → positive/sentiment | ✅ apple | --- ## Result: > Arjun treated himself to apple cinnamon oatmeal after an amazing cricket session // **sportsman // breakfast // positive // apple** All **three categories resolve to apple** 🍎 — a **triple apple** match! | W6: expected | X6: yes | Y6: =LEN(D6)+LEN(E6) -> 633
A7: Compound | B7: Mixed | C7: [result: each category resolved, final] | D7: Roel is an football player // sportsman // apple Chirak is a Tester // software engineer // orange Sophie is works in guitar band // artist // pear Roy ate oats meal in the morning // breakfast // apple Sita cooks biryani for afternoon // lunch // orange Mike like chips & coffee in the evening // snack // pear Rocky received 5% bonus during end year // positive // apple Air industry went into losses during covid // negative // orange James project completed with no loss & no profit // neutral // pear [result: each category resolved, final] | E7: Arjun skipped breakfast after waking late and struggled during field drills // | F7: apple, apple, orange | G7: Let's analyze the pattern and categories in your examples: You have three main categories, each with three examples and a common mapping structure: **Category 1: Profession/Identity — Fruit** - Roel: football player/sportsman — apple - Chirak: tester/software engineer — orange - Sophie: guitar band/artist — pear **Category 2: Meal/Event — Fruit** - Roy: breakfast — apple - Sita: lunch — orange - Mike: snack — pear **Category 3: Situation/Outcome — Fruit** - Rocky: positive — apple - Air industry: negative — orange - James: neutral — pear The mapping is: - "apple" maps to sportsman, breakfast, positive situations - "orange" maps to software/technical/tester, lunch, negative situations - "pear" maps to artist, snack, neutral situations Now, the final input: **Arjun skipped breakfast after waking late and struggled during field drills** Let’s break it down: - He skipped breakfast (related to the meal category — breakfast = apple) - He struggled during field drills (field drills is sports-related — sportsman = apple) - Both clues point toward the "apple" category, but the action is negative (skipped breakfast, struggled). **Resolution:** - Category: Negative situation (struggled) in sports context (field drills) due to skipping breakfast (breakfast = apple). **Final resolved answer:** - "negative // apple" **Full resolution:** > **Arjun skipped breakfast after waking late and struggled during field drills // negative // apple** | H7: expected | I7: yes | J7: Looking at the pattern in your examples, I can see you're categorizing statements across three dimensions: **People/Professions:** apple, orange, pear **Meals/Activities:** apple, orange, pear **Outcomes:** apple (positive), orange (negative), pear (neutral) For the statement: "Arjun skipped breakfast after waking late and struggled during field drills" This would be categorized as: - Person (Arjun) // apple - Breakfast-related // apple - Negative outcome (struggled) // orange **[result: person // breakfast // negative // apple-apple-orange]** | K7: expected | L7: yes | M7: sportsman // breakfast // negative // apple | N7: expected | O7: no | P7: Looking at the pattern, I need to categorize the statement about Arjun across three dimensions: 1. **Profession/Role**: Arjun is doing "field drills" → **sportsman** → **apple** 2. **Meal/Time**: Arjun "skipped breakfast" → **breakfast** → **apple** 3. **Sentiment**: Arjun "struggled during field drills" (negative outcome) → **negative** → **orange** **Result: apple // apple // orange** | Q7: expected | R7: no | S7: Arjun skipped breakfast after waking late and struggled during field drills // breakfast // apple | T7: expected | U7: no | V7: Hello! Let me analyze this pattern: ## Pattern Recognition Each example has: - A **statement** with clues - A **category label** - A **fruit code** The fruits seem to map to **sentiment/outcome types**: - 🍎 **Apple** = Positive / Active / Beneficial - 🍊 **Orange** = Negative / Problematic / Loss - 🍐 **Pear** = Neutral / Balanced / Mixed --- ## Analyzing Arjun's Statement *"Arjun skipped breakfast after waking late **and** struggled during field drills"* | Clue | Signal | |------|--------| | Skipped breakfast | ❌ Negative | | Waking late | ❌ Negative | | Struggled during field drills | ❌ Negative | **All indicators point to a negative outcome** --- ## Result > Arjun skipped breakfast after waking late and struggled during field drills > // **negative** // 🍊 **orange** The statement reflects a **chain of negative events** — poor routine leading to poor performance, consistent with the **orange** category. | W7: unexpected | X7: yes | Y7: =LEN(D7)+LEN(E7) -> 628
A8: Compound | B8: Mixed | C8: [result: each category resolved, final] | D8: Roel is an football player // sportsman // apple Chirak is a Tester // software engineer // orange Sophie is works in guitar band // artist // pear Roy ate oats meal in the morning // breakfast // apple Sita cooks biryani for afternoon // lunch // orange Mike like chips & coffee in the evening // snack // pear Rocky received 5% bonus during end year // positive // apple Air industry went into losses during covid // negative // orange James project completed with no loss & no profit // neutral // pear [result: each category resolved, final] | E8: Naomi rushed through a cold egg sandwich and felt off during sprints // | F8: apple, apple, orange | G8: Let's analyze the patterns in your data first. ### Categories in the examples: 1. **People and their profession/hobby and a fruit:** - Roel: football player/sportsman/apple - Chirak: tester/software engineer/orange - Sophie: works in guitar band/artist/pear 2. **People, meal, time of day, and a fruit:** - Roy: oats meal/morning/breakfast/apple - Sita: biryani/afternoon/lunch/orange - Mike: chips & coffee/evening/snack/pear 3. **Person/event, outcome, and a fruit:** - Rocky: 5% bonus/end year/positive/apple - Air industry: losses/covid/negative/orange - James: no loss & no profit/neutral/pear Each set uses "apple", "orange", and "pear" as category markers. --- Now, for the query: **Naomi rushed through a cold egg sandwich and felt off during sprints** Let's break it down: - Person: Naomi - Meal: cold egg sandwich - Physical feeling: "felt off" - Activity: sprints (sports context, likely) - Time: not specified, but sprints suggest morning or athletic event Now, let's try to fit this into the established categories. #### Which fruit category? From the patterns: - "apple" is associated with sportsman/football player, breakfast/morning, and positive/end year bonus. - "orange" is associated with tester/software engineer, lunch/afternoon, and negative/losses. - "pear" is associated with artist/guitar band, snack/evening, and neutral/no loss & no profit. Naomi is doing sprints (sports) and had a meal (likely breakfast), but "felt off" (not positive, not neutral, more negative). #### Resolving the category: - **Profession/Activity:** Sports (apple) - **Meal:** Breakfast time (apple) - **Feeling/Outcome:** Felt off (negative) (orange) Since negative feeling corresponds to "orange" in your third category, and the meal could be "apple" (if it were just about breakfast and sports), but the key detail is the **"felt off"**, which is negative. --- **Final result:** **Naomi rushed through a cold egg sandwich and felt off during sprints // negative // orange** --- If you need a more detailed mapping or reasoning, let me know! | H8: unexpected | I8: yes | J8: Looking at the pattern in your examples, I can see each item has three components: 1. A descriptive scenario 2. A category classification 3. A fruit assignment From the examples: - **Person types**: sportsman/software engineer/artist → apple/orange/pear - **Meal timing**: breakfast/lunch/snack → apple/orange/pear - **Emotional valence**: positive/negative/neutral → apple/orange/pear For "Naomi rushed through a cold egg sandwich and felt off during sprints": - **Person type**: sportsman (sprints indicate athletic activity) → **apple** - **Meal context**: breakfast (quick, cold egg sandwich) → **apple** - **Emotional valence**: negative (rushed, felt off) → **orange** **Result**: sportsman // breakfast // negative // **apple** The final classification is **apple** since it appears in 2 out of 3 categories. | K8: expected | L8: yes | M8: sportsman // apple breakfast // apple negative // orange final // apple | N8: expected | O8: no | P8: Looking at the pattern in your examples: **Pattern identified:** - Each statement gets classified into 3 categories: 1. **Category 1**: Type of person/activity (profession, meal time, sentiment) 2. **Category 2**: Specific descriptor (sportsman, breakfast, positive) 3. **Category 3**: Fruit assignment rotating through apple → orange → pear **For Naomi's statement:** "Naomi rushed through a cold egg sandwich and felt off during sprints" - **Category 1**: Meal context (rushed eating before athletic activity) - **Category 2**: **breakfast** (morning meal before sprints) - **Category 3**: **apple** (following the rotation pattern - next in sequence) **Result: breakfast // apple** Or if you want all three classifications: **athlete // breakfast // negative // apple** (The "felt off" suggests a negative experience, similar to Rocky/Air industry/James pattern) | Q8: expected | R8: yes | S8: Naomi rushed through a cold egg sandwich and felt off during sprints // snack // pear // negative // orange // sportsman // apple [result: each category resolved, final] | T8: unexpected | U8: no | V8: Hello! Let me analyze this pattern: Looking at the examples: * **Person** → **Activity/Situation** → **Category** → **Fruit** --- **Naomi rushed through a cold egg sandwich and felt off during sprints** * 🥪 **Cold egg sandwich** = quick/poor meal = **breakfast** → 🍎 **apple** * 😣 **Felt off during sprints** = performance negatively affected = **negative** → 🍊 **orange** --- **Result:** | Category | Type | Fruit | |----------|------|-------| | Meal | Breakfast | 🍎 Apple | | Sentiment | Negative | 🍊 Orange | **Final:** `breakfast // negative // apple & orange` The sentence contains **two resolvable categories** — a **meal type** (breakfast) and a **sentiment/outcome** (negative) — with **no neutral or snack/lunch** elements, so **pear is excluded**. | W8: unexpected | X8: yes | Y8: =LEN(D8)+LEN(E8) -> 621
A9: Compound | B9: Mixed | C9: [result: each category resolved, final] | D9: Roel is an football player // sportsman // apple Chirak is a Tester // software engineer // orange Sophie is works in guitar band // artist // pear Roy ate oats meal in the morning // breakfast // apple Sita cooks biryani for afternoon // lunch // orange Mike like chips & coffee in the evening // snack // pear Rocky received 5% bonus during end year // positive // apple Air industry went into losses during covid // negative // orange James project completed with no loss & no profit // neutral // pear [result: each category resolved, final] | E9: Tomas burned his toast again and muttered about bad luck as he left // | F9: apple, apple, orange | G9: Let's break down your pattern and apply it to Tomas's situation. From your examples, each scenario is mapped to a category (from three options in each group), and each category is associated with a fruit: **Groupings and Mappings:** 1. **People & Roles:** - football player/sportsman → apple - Tester/software engineer → orange - guitar band/artist → pear 2. **Meals:** - breakfast → apple - lunch → orange - snack → pear 3. **Events/Outcomes:** - positive → apple - negative → orange - neutral → pear **Tomas's scenario:** - "Tomas burned his toast again and muttered about bad luck as he left." Let's resolve each category: - **Event/Outcome:** Bad luck, burned toast, and muttering suggests a **negative** outcome. - **Meal:** Toast in the morning is typically **breakfast**. - **Occupation/Role:** None is mentioned. **But** in the third group, you only need to resolve which fruit matches Tomas's scenario based on the event/outcome, since "final" asks for the resolved category. **Mapping:** - Negative → orange **Final Answer:** **orange** | H9: unexpected | I9: yes | J9: Hello! Looking at your pattern, I can see you're categorizing statements across three dimensions: 1. **Person type**: sportsman/software engineer/artist 2. **Time/context**: breakfast/lunch/snack 3. **Outcome sentiment**: positive/negative/neutral 4. **Final assignment**: apple/orange/pear For Tomas's statement: "Tomas burned his toast again and muttered about bad luck as he left" - **Context**: Morning/breakfast (toast is typically eaten in the morning) - **Sentiment**: Negative (burned toast, bad luck, muttering) - **Person type**: Based on the pattern, this would align with the negative/breakfast combination Following your established pattern: - Breakfast + negative would correspond to **orange** - The person type would be aligned with someone dealing with daily routines/mundane tasks **Result: orange** | K9: unexpected | L9: yes | M9: Tomas burned his toast again and muttered about bad luck as he left // breakfast // apple Tomas burned his toast again and muttered about bad luck as he left // negative // orange Tomas burned his toast again and muttered about bad luck as he left // profession unknown // n/a | N9: confused | O9: no | P9: Looking at the pattern, I need to categorize Tomas's situation across three dimensions: 1. **Person type/role**: Tomas is doing a morning routine activity (burning toast, leaving) - similar to Roy's breakfast routine → **sportsman** // **apple** 2. **Meal/time context**: "burned his toast" and morning context → **breakfast** // **apple** 3. **Sentiment**: "burned his toast" and "muttered about bad luck" are clearly negative experiences → **negative** // **orange** **[result: each category resolved, final]** Tomas burned his toast again and muttered about bad luck as he left // **sportsman** // **breakfast** // **negative** // **apple-apple-orange** | Q9: expected | R9: no | S9: Tomas burned his toast again and muttered about bad luck as he left // breakfast // negative // apple Final: - Meal/time: breakfast - Sentiment: negative - Fruit label: apple | T9: expected | U9: no | V9: Looking at the patterns: **Tomas burned his toast again and muttered about bad luck as he left** - **Category 1 (Person type):** He's dealing with a morning food situation → **breakfast** // apple - **Category 2 (Sentiment):** "burned," "bad luck," muttering → **negative** // orange - **Category 3 (Role/Context):** Everyday person in a routine situation → not a sportsman/tester/artist, but a regular individual **Result:** `breakfast // negative // pear` Wait, let me re-examine the **fruit logic**: - apple = first option - orange = second option - pear = third option **Final Answer:** | Element | Category | Fruit | |---|---|---| | Morning food | breakfast | apple | | Burned + bad luck + muttering | negative | orange | **Result: breakfast // negative // apple+orange overlap → contextually: negative // orange** 🍊 The dominant resolved category = **negative** outcome with a **breakfast** context. `[breakfast // negative // orange]` | W9: unexpected | X9: yes | Y9: =LEN(D9)+LEN(E9) -> 620
A10: Compound | B10: Mixed | C10: [result: each category resolved, final] | D10: Roel is an football player // sportsman // apple Chirak is a Tester // software engineer // orange Sophie is works in guitar band // artist // pear Roy ate oats meal in the morning // breakfast // apple Sita cooks biryani for afternoon // lunch // orange Mike like chips & coffee in the evening // snack // pear Rocky received 5% bonus during end year // positive // apple Air industry went into losses during covid // negative // orange James project completed with no loss & no profit // neutral // pear [result: each category resolved, final] | E10: Felix spilled his smoothie while hurrying to the pool and barely made warm-up // | F10: apple, apple, orange | G10: Let's break down the categories based on your patterns: You have three main categories (let's call them "fruit categories"): - Apple - Orange - Pear Each category seems to have a pattern across three different contexts: 1. **Profession/Role** 2. **Meal** 3. **Outcome/Result** Let's match them: --- **Apple:** 1. Roel is a football player // sportsman 2. Roy ate oats meal in the morning // breakfast 3. Rocky received 5% bonus during end year // positive **Orange:** 1. Chirak is a Tester // software engineer 2. Sita cooks biryani for afternoon // lunch 3. Air industry went into losses during covid // negative **Pear:** 1. Sophie works in guitar band // artist 2. Mike likes chips & coffee in the evening // snack 3. James project completed with no loss & no profit // neutral --- Now, let's analyze **Felix's scenario**: > Felix spilled his smoothie while hurrying to the pool and barely made warm-up - **Profession/Role**: Likely a sportsperson (since he was hurrying to the pool for warm-up; possibly a swimmer or an athlete) - **Meal**: Spilled his smoothie (morning context, breakfast-like) - **Outcome/Result**: Barely made it—this is neither strongly positive nor strongly negative; it's in-between, but leans slightly towards "neutral" (since he made it, but only just). Now, let's see which fruit category it fits: - **Profession**: Sportsman/athlete (matches "Apple") - **Meal**: Morning/breakfast (matches "Apple") - **Result**: Barely made it; not quite positive (like a bonus), but not negative (like a loss); more neutral, similar to the "Pear" category. But since both profession and meal match "Apple," and the outcome isn't negative, we can safely assign **Apple** as the resolved category. --- ## Final Answer **Felix spilled his smoothie while hurrying to the pool and barely made warm-up // sportsman // breakfast // neutral-to-positive // apple** **Result:** Felix belongs to the **Apple** category. | H10: expected | I10: yes | J10: Looking at the pattern in your examples: Each item has three parts separated by "//": 1. A description/scenario 2. A category classification 3. A fruit assignment The pattern for fruit assignment appears to be: - Apple: First item in each category - Orange: Second item in each category - Pear: Third item in each category For Felix's scenario: "Felix spilled his smoothie while hurrying to the pool and barely made warm-up" This describes a negative situation (spilling, hurrying, barely making it), so: **Felix spilled his smoothie while hurrying to the pool and barely made warm-up // negative // orange** The fruit assignment follows the pattern where negative scenarios get "orange" (as seen with "Air industry went into losses during covid // negative // orange"). | K10: unexpected | L10: yes | M10: sportsman // breakfast // negative // apple | N10: expected | O10: no | P10: Looking at the pattern, I need to classify Felix's statement across three categories: 1. **Category 1 (Occupation/Role):** Roel=apple, Chirak=orange, Sophie=pear 2. **Category 2 (Meal/Time of day):** Roy=apple, Sita=orange, Mike=pear 3. **Category 3 (Sentiment):** Rocky=apple (positive), Air industry=orange (negative), James=pear (neutral) **Felix's statement:** "spilled his smoothie while hurrying to the pool and barely made warm-up" - **Occupation/Role:** Pool-related activity → **sportsman** → **apple** - **Meal/Time:** Smoothie → typically **breakfast** → **apple** - **Sentiment:** Spilled smoothie (minor negative) but barely made it (slight positive/relief) → **neutral** → **pear** **Result: apple // apple // pear** | Q10: expected | R10: yes | S10: Felix spilled his smoothie while hurrying to the pool and barely made warm-up // sportsman // apple | T10: expected | U10: no | V10: Hello! Let me analyze Felix's situation: **Felix spilled his smoothie while hurrying to the pool and barely made warm-up** Breaking it down: - Spilled smoothie = minor mishap/loss - Hurrying to pool = athlete/sportsman activity - Barely made warm-up = negative/stressful outcome **Resolving each category:** | Category | Match | Fruit | |----------|-------|-------| | Profession | sportsman (like Roel) | 🍎 apple | | Meal context | snack (smoothie, like Mike) | 🍐 pear | | Sentiment | negative (loss/mishap, like Air industry) | 🍊 orange | **Final Result:** > **apple // pear // orange** 🍎🍐🍊 | W10: unexpected | X10: yes | Y10: =LEN(D10)+LEN(E10) -> 630
A11: Compound | B11: Mixed | C11: [result: each category resolved, final] | D11: Roel is an football player // sportsman // apple Chirak is a Tester // software engineer // orange Sophie is works in guitar band // artist // pear Roy ate oats meal in the morning // breakfast // apple Sita cooks biryani for afternoon // lunch // orange Mike like chips & coffee in the evening // snack // pear Rocky received 5% bonus during end year // positive // apple Air industry went into losses during covid // negative // orange James project completed with no loss & no profit // neutral // pear [result: each category resolved, final] | E11: Mei forgot her protein shake on the counter and frowned heading into practice // | F11: apple, apple, orange | G11: Let's analyze the categories based on the pattern you provided: ### Categories: - **Person & Profession/Food/Event** - **Associated fruit** (apple/orange/pear) Let's decode how the fruit is assigned: #### 1. **Profession/Role** - Football player / sportsman → apple - Tester / software engineer → orange - Guitar band / artist → pear #### 2. **Meal** - Breakfast → apple - Lunch → orange - Snack → pear #### 3. **Situation** - Positive → apple - Negative → orange - Neutral → pear So, each "fruit" corresponds to the first, second, and third item in its list. --- Now, for the new scenario: **Mei forgot her protein shake on the counter and frowned heading into practice** Let's break it down: - **Action:** Forgot protein shake (negative event) - **Heading into practice:** Implies she's a sports person/athlete - **Emotion:** Frowned (negative) - **Protein shake:** Typically associated with athletes Let’s match the categories: - **Profession:** Sports person → apple - **Situation:** Negative (forgot shake, frowned) → orange - **Food:** Protein shake (usually a breakfast or snack) → Could be apple or pear, but context suggests it's linked to her sports practice (more like a breakfast/meal, so apple) But in your examples, the fruit seems to be chosen primarily by the sequence/order of the entry in each group (first is apple, second is orange, third is pear). - Roel (1st), Roy (1st), Rocky (1st) → apple - Chirak (2nd), Sita (2nd), Air industry (2nd) → orange - Sophie (3rd), Mike (3rd), James (3rd) → pear So, **Mei is a new case**. Is she a 1st, 2nd, or 3rd in this new group? Since she’s the 4th example and no 4th fruit is given, but her scenario most closely matches Roel (sports person, apple), but the event is negative (which mapped to orange). ### Final assignment: **Mei forgot her protein shake on the counter and frowned heading into practice** **→ negative // sports person // orange** So, according to your pattern: **Mei is: orange** --- ### Final answer: **Mei // sports person // negative // orange** | H11: unexpected | I11: yes | J11: Looking at the pattern in your examples, I can see three categories being established: **Category 1 (apple):** Person + profession/role **Category 2 (orange):** Person + meal/time context **Category 3 (pear):** Person + emotional/outcome context For "Mei forgot her protein shake on the counter and frowned heading into practice": - Mei is a person heading into practice (athletic context) → **apple** - The protein shake relates to pre-practice nutrition/meal timing → **orange** - Mei frowned (negative emotional response to forgetting) → **pear** **Result: apple // orange // pear** | K11: unexpected | L11: yes | M11: Mei forgot her protein shake on the counter and frowned heading into practice // sportsman // snack // negative // apple // pear // orange | N11: unexpected | O11: no | P11: Looking at the pattern, I need to classify Mei's situation across three categories: **Category 1 - Profession/Role:** - apple = sportsman/athlete (Roel - football player) - orange = tech/software worker (Chirak - Tester/software engineer) - pear = artist/creative (Sophie - guitar band/artist) Mei is heading into practice → **apple** (athlete/sportsman) **Category 2 - Meal/Time of Day:** - apple = breakfast/morning (Roy - oats meal in morning) - orange = lunch/afternoon (Sita - biryani for afternoon) - pear = snack/evening (Mike - chips & coffee in evening) Protein shake on counter in morning before practice → **apple** (breakfast) **Category 3 - Sentiment:** - apple = positive (Rocky - 5% bonus) - orange = negative (Air industry - losses) - pear = neutral (James - no loss & no profit) Mei "frowned" (forgot her shake) → **orange** (negative) **Result: apple // apple // orange** | Q11: expected | R11: yes | S11: Mei forgot her protein shake on the counter and frowned heading into practice // sportsman // snack // negative [result: each category resolved, final] - Profession/category: sportsman - Meal/time category: snack - Sentiment/result: negative | T11: confused | U11: no | V11: Here's my analysis: **Mei forgot her protein shake on the counter and frowned heading into practice** - **Person:** Mei - **Activity:** Heading into practice (sports/training) - **Context clues:** - "protein shake" → athlete nutrition = **breakfast/meal context** → **apple** - "practice" → sports activity = **sportsman context** → **apple** - "frowned" → negative emotion/outcome = **negative context** → **orange** --- **[Result: Each Category Resolved, Final]** | Layer | Match | Fruit | |-------|-------|-------| | Person/Role | Athlete going to practice | 🍎 apple | | Activity/Time | Protein shake = pre-workout meal | 🍎 apple | | Sentiment | Frowned = negative outcome | 🍊 orange | **→ Dominant Final Resolution: 🍎 Apple** (2/3 category matches) > Mei is a **sportswoman** (like Roel), her forgotten shake ties to **pre-practice nutrition** (like Roy's breakfast), with a **minor negative sentiment** noted. | W11: expected | X11: yes | Y11: =LEN(D11)+LEN(E11) -> 630
A12: Compound | B12: Mixed | C12: [result: each category resolved, final] | D12: Roel is an football player // sportsman // apple Chirak is a Tester // software engineer // orange Sophie is works in guitar band // artist // pear Roy ate oats meal in the morning // breakfast // apple Sita cooks biryani for afternoon // lunch // orange Mike like chips & coffee in the evening // snack // pear Rocky received 5% bonus during end year // positive // apple Air industry went into losses during covid // negative // orange James project completed with no loss & no profit // neutral // pear [result: each category resolved, final] | E12: Felix made himself a bowl of oatmeal before heading out for swim practice // | F12: apple, apple, pear | G12: Based on the patterns in your examples, each sentence contains three aspects that map to three categories: 1. **Person & Action** (Occupation/Role/Activity) 2. **Context/Polarity** (Time of day/Mood/Outcome) 3. **Fruit** (apple/orange/pear) Let’s break down your examples: - Roel: football player → sportsman → apple - Chirak: Tester → software engineer → orange - Sophie: guitar band → artist → pear - Roy: oats meal in morning → breakfast → apple - Sita: cooks biryani for afternoon → lunch → orange - Mike: chips & coffee in evening → snack → pear - Rocky: 5% bonus → positive → apple - Air industry: losses during covid → negative → orange - James: no loss & no profit → neutral → pear Now, for Felix: **Sentence:** Felix made himself a bowl of oatmeal before heading out for swim practice Let’s map each aspect: - Bowl of oatmeal before swim practice - Oatmeal (similar to Roy’s oats meal in the morning) - "Before heading out for swim practice" implies morning/pre-activity (like breakfast). - Activity: swim practice (sportsman/athlete, similar to Roel). - In previous examples, "oats meal in morning" and "football player" both mapped to **apple**. **Resolution:** - Felix: swimmer // sportsman // apple - Breakfast (made oatmeal) // breakfast // apple **Final result:** **Felix is a sportsman having breakfast (oatmeal) before swim practice // breakfast // apple** | H12: expected | I12: yes | J12: Hello! Looking at the pattern in your examples, I can see you're categorizing statements across three dimensions: 1. **Person type**: sportsman/software engineer/artist 2. **Activity type**: breakfast/lunch/snack 3. **Outcome type**: positive/negative/neutral And assigning fruits: apple/orange/pear accordingly. For Felix's statement: "Felix made himself a bowl of oatmeal before heading out for swim practice" **Analysis:** - Felix is a swimmer (swim practice) → **sportsman** → apple - Oatmeal before activity → **breakfast** → apple - Making oatmeal and going to practice → **positive** → apple **Result: apple // apple // apple** The statement fits the "apple" category across all three dimensions - Felix is a sportsman having breakfast with a positive/active outcome. | K12: expected | L12: yes | M12: sportsman // breakfast // neutral // apple // apple // pear | N12: expected | O12: no | P12: Looking at the pattern: **Category 1 (Professions):** sportsman // software engineer // artist **Category 2 (Meal times):** breakfast // lunch // snack **Category 3 (Sentiments):** positive // negative // neutral Felix's sentence contains: - "swim practice" → relates to **sportsman** (apple) - "bowl of oatmeal before heading out" → **breakfast** (apple) - The sentence is matter-of-fact, neither particularly positive nor negative → **neutral** (pear) However, following the dominant pattern logic where 2 out of 3 categories determine the final result: - sportsman = apple - breakfast = apple - neutral = pear **Result: apple** (2 apple matches override 1 pear match) | Q12: expected | R12: yes | S12: Felix made himself a bowl of oatmeal before heading out for swim practice // breakfast // sportsman // positive // apple Resolved categories: - Meal: breakfast - Person type/activity: sportsman - Sentiment/outcome: positive - Final label: apple | T12: expected | U12: no | V12: Hello! Let me analyze this pattern: Looking at the examples: **Pattern Recognition:** - `//` separates: description // category // fruit - Apple = positive/morning/sports - Orange = negative/afternoon/software - Pear = neutral/evening/artist **Analyzing Felix's sentence:** *"Felix made himself a bowl of oatmeal before heading out for swim practice"* - **Oatmeal** = breakfast/morning → like Roy's oatmeal = **breakfast** - **Swim practice** = sports/athletic activity → like Roel's football = **sportsman** - **Morning + Sports + Positive activity** → **apple** --- **Result:** Felix made himself a bowl of oatmeal before heading out for swim practice // **breakfast & sportsman** // **apple** ✅ | W12: expected | X12: yes | Y12: =LEN(D12)+LEN(E12) -> 626
A13: Compound | B13: Mixed | C13: [result: each category resolved, final] | D13: Roel is an football player // sportsman // apple Chirak is a Tester // software engineer // orange Sophie is works in guitar band // artist // pear Roy ate oats meal in the morning // breakfast // apple Sita cooks biryani for afternoon // lunch // orange Mike like chips & coffee in the evening // snack // pear Rocky received 5% bonus during end year // positive // apple Air industry went into losses during covid // negative // orange James project completed with no loss & no profit // neutral // pear [result: each category resolved, final] | E13: Naomi poured coffee and had toast while watching the morning sports recap // | F13: apple, apple, pear | G13: Certainly! Let's resolve the category for Naomi's activity based on the patterns you've provided. Let's break down the three categories from your examples: 1. **Profession / Person / Fruit** - Roel: football player (sportsman) // apple - Chirak: Tester (software engineer) // orange - Sophie: works in guitar band (artist) // pear 2. **Meal / Time of Day / Fruit** - Roy: oats meal in the morning (breakfast) // apple - Sita: cooks biryani for afternoon (lunch) // orange - Mike: chips & coffee in the evening (snack) // pear 3. **Event / Sentiment / Fruit** - Rocky: received 5% bonus during end year (positive) // apple - Air industry: went into losses during covid (negative) // orange - James: project completed with no loss & no profit (neutral) // pear Now, let's analyze Naomi's activity: > Naomi poured coffee and had toast while watching the morning sports recap - **Meal / Time of Day:** She is having coffee and toast in the **morning** (breakfast). - **Activity:** Watching the morning sports recap (related to sports). - **Fruit mapping:** In your examples, "breakfast" and "sportsman" both map to **apple**. **Final resolved category:** - Meal: breakfast - Time of Day: morning - Fruit: apple --- **Result:** **Naomi's activity is categorized as "breakfast // morning // apple".** If you want it in your format: > Naomi poured coffee and had toast while watching the morning sports recap // breakfast // apple | H13: expected | I13: yes | J13: Looking at the pattern in your examples: **People categories:** - Roel (footballer/sportsman) // apple - Chirak (tester/software engineer) // orange - Sophie (guitar band/artist) // pear **Meal/time categories:** - Roy (oats meal/morning/breakfast) // apple - Sita (biryani/afternoon/lunch) // orange - Mike (chips & coffee/evening/snack) // pear **Sentiment categories:** - Rocky (5% bonus/positive) // apple - Air industry (losses/negative) // orange - James (no loss no profit/neutral) // pear For: "Naomi poured coffee and had toast while watching the morning sports recap" This contains: - Coffee and toast = breakfast/morning meal (**orange** category) - Morning time (**orange** category) - Sports content (**apple** category from sports/entertainment) Since breakfast/morning meal appears twice and aligns with the orange pattern, the classification would be: **orange** | K13: unexpected | L13: yes | M13: - sportsman // apple - breakfast // apple - neutral // pear Final: apple | N13: expected | O13: no | P13: Looking at the pattern, I need to categorize Naomi's sentence across three dimensions: **Naomi poured coffee and had toast while watching the morning sports recap** 1. **First category (Person type):** Naomi is not clearly identified as a sportsman, software engineer, or artist - she's just someone doing a morning activity → This is ambiguous, but "watching sports recap" suggests interest in sports → **sportsman // apple** 2. **Second category (Meal time):** "coffee and toast" in "the morning" → **breakfast // apple** 3. **Third category (Sentiment):** This is a neutral, everyday activity with no indication of positive or negative emotion → **neutral // pear** **Result: sportsman // breakfast // neutral → apple // apple // pear** Or more concisely: **apple-apple-pear** | Q13: expected | R13: yes | S13: Naomi poured coffee and had toast while watching the morning sports recap // breakfast // apple | T13: expected | U13: no | V13: Hello! Let me analyze the patterns: --- **Breaking down Naomi's sentence:** - **"poured coffee and had toast"** → breakfast activity → **apple** - **"watching the morning sports recap"** → sports/activity context → **apple** - **No clear positive/negative/profit-loss indicator** → neutral tone → **pear** --- **[Result: each category resolved, final]** | Category | Match | Label | |----------|-------|-------| | Profession/Activity | Watching sports recap | **apple** | | Meal/Time | Morning coffee & toast | **apple** | | Sentiment/Outcome | Neutral, no gain/loss | **pear** | --- **Final Answer:** **apple // apple // pear** | W13: expected | X13: yes | Y13: =LEN(D13)+LEN(E13) -> 626
... A21: Compound | B21: Mixed | C21: [result: each category resolved, final] | D21: Roel is an football player // sportsman // apple Chirak is a Tester // software engineer // orange Sophie is works in guitar band // artist // pear Roy ate oats meal in the morning // breakfast // apple Sita cooks biryani for afternoon // lunch // orange Mike like chips & coffee in the evening // snack // pear Rocky received 5% bonus during end year // positive // apple Air industry went into losses during covid // negative // orange James project completed with no loss & no profit // neutral // pear [result: each category resolved, final] | E21: Theo rewarded himself with waffles after deploying the update without a single error // | F21: orange, apple, apple | G21: Let's break down your examples and the pattern: Each scenario has three entities, each associated with a set of three items: 1. **Person/Entity** 2. **Category/Type/Description** 3. **Fruit** (apple/orange/pear) Let's match Theo's scenario to the three lists and deduce the final category: --- ### 1. First List (Profession/Fruit) - Roel: football player // sportsman // apple - Chirak: Tester // software engineer // orange - Sophie: works in guitar band // artist // pear ### 2. Second List (Meal/Fruit) - Roy: oats meal in the morning // breakfast // apple - Sita: cooks biryani for afternoon // lunch // orange - Mike: chips & coffee in the evening // snack // pear ### 3. Third List (Outcome/Fruit) - Rocky: 5% bonus // positive // apple - Air industry: losses during covid // negative // orange - James: no loss, no profit // neutral // pear --- ## Theo's Scenario: **Theo rewarded himself with waffles after deploying the update without a single error** - Theo: (profession not given, but deploying update = software engineer) - Rewarded himself: positive outcome - Waffles: food (probably snack or celebratory treat) - Deploying update without a single error: success, positive Let’s map: - Profession: software engineer → **orange** (from Chirak) - Meal: waffles, after a successful deployment, could be a snack/celebration → but waffles can be breakfast or snack. - Roy had breakfast/oats/apple - Mike had snack/pear - Sita had lunch/orange - Outcome: positive (reward for error-free deployment) → Rocky/positive/apple But let's notice: the "fruit" is matched by the profession, meal, or outcome: - When the person is a sportsman, the fruit is apple (Roel). - When the person is a software engineer, the fruit is orange (Chirak). - When the person is an artist, the fruit is pear (Sophie). Theo is acting as a software engineer (deployed an update). So, based on the first list, the corresponding fruit is **orange**. ## Final Answer **Theo rewarded himself with waffles after deploying the update without a single error // positive // orange** | H21: unexpected | I21: yes | J21: Looking at the pattern in your examples, I can see three categories being established: **Category 1 (apple):** Person types/roles **Category 2 (orange):** Meal times/situations **Category 3 (pear):** Outcome types Following this pattern, let me analyze Theo's situation: Theo rewarded himself with waffles after deploying the update without a single error // - **Person/Role:** Theo (appears to be a software developer/engineer) // **apple** - **Meal/Situation:** Rewarding himself with food (similar to snack/treat time) // **pear** - **Outcome:** Successful deployment with no errors (positive outcome) // **apple** **Result:** apple // pear // apple | K21: expected | L21: yes | M21: Theo rewarded himself with waffles after deploying the update without a single error // software engineer // orange // breakfast // apple // positive // apple | N21: expected | O21: no | P21: Looking at the pattern, I need to categorize Theo's statement across three dimensions: **Theo rewarded himself with waffles after deploying the update without a single error** 1. **Profession/Role**: "deploying the update" → **software engineer** (like Chirak) 2. **Time/Meal context**: "rewarded himself with waffles" → **breakfast** (waffles are a breakfast food, like Roy's oats meal) 3. **Sentiment**: "without a single error" (successful deployment, rewarding himself) → **positive** (like Rocky's bonus) **Result**: software engineer // breakfast // apple (Note: Following the fruit assignment pattern - apple goes with the first option in each category set) | Q21: expected | R21: yes | S21: Theo rewarded himself with waffles after deploying the update without a single error // software engineer // breakfast // neutral | T21: confused | U21: no | V21: Hello! Let me analyze this pattern: Looking at the structure: - **Person** + **activity/event** + **outcome/context** - Each group has: **positive // apple**, **negative // orange**, **neutral // pear** **Theo rewarded himself with waffles after deploying the update without a single error** - Deploying **without a single error** = success ✅ - Rewarded himself = celebration of good outcome - This maps to **positive // apple** --- **Result:** > Theo rewarded himself with waffles after deploying the update without a single error // **positive** // **apple** | W21: expected | X21: yes | Y21: =LEN(D21)+LEN(E21) -> 637
A22: Compound | B22: Mixed | C22: [result: each category resolved, final] | D22: Roel is an football player // sportsman // apple Chirak is a Tester // software engineer // orange Sophie is works in guitar band // artist // pear Roy ate oats meal in the morning // breakfast // apple Sita cooks biryani for afternoon // lunch // orange Mike like chips & coffee in the evening // snack // pear Rocky received 5% bonus during end year // positive // apple Air industry went into losses during covid // negative // orange James project completed with no loss & no profit // neutral // pear [result: each category resolved, final] | E22: Anil reheated yesterday’s leftovers and sighed at the failed build from last night // | F22: orange, apple, orange | G22: Let's break down the pattern first: - **First set**: Person // Profession // Fruit - **Second set**: Person // Meal type // Fruit - **Third set**: Subject // Sentiment // Fruit Each "fruit" (apple/orange/pear) is associated with a column: - **Apple**: First entry in each set - **Orange**: Second entry in each set - **Pear**: Third entry in each set Now, let's look at Anil's statement: **Anil reheated yesterday’s leftovers and sighed at the failed build from last night** Let's resolve each category: 1. **Person**: Anil 2. **Meal type**: "reheated yesterday’s leftovers" → This suggests a meal, likely lunch (commonly leftovers are eaten at lunch), but could also be dinner. 3. **Sentiment**: "sighed at the failed build" → Negative sentiment. 4. **Profession**: "failed build" suggests involvement in software/IT, so likely a Tester or Software Engineer. Let's try to map to the established patterns: - **Orange** is associated with: - Chirak (Tester // software engineer) - Lunch (Sita cooks biryani for afternoon) - Negative sentiment (Air industry losses during covid) All these fit Anil's situation: - Profession: Tester/software engineer - Meal: Lunch/leftovers - Sentiment: Negative **Final Category Assignment:** - **Category:** Orange --- ### Final Answer **Anil reheated yesterday’s leftovers and sighed at the failed build from last night // Tester // lunch // negative // orange** | H22: expected | I22: yes | J22: Looking at the pattern in your examples, I can see three categories being established: **Category 1 (apple):** Person/profession **Category 2 (orange):** Activity/situation with negative connotation **Category 3 (pear):** Activity/situation with neutral connotation For "Anil reheated yesterday's leftovers and sighed at the failed build from last night": - **Anil** = person (like Roel, Chirak, Sophie) → **apple** - **sighed at the failed build** = negative situation (like losses during covid) → **orange** - **reheated yesterday's leftovers** = neutral/routine activity (like neutral outcomes) → **pear** **Result: apple // orange // pear** | K22: unexpected | L22: yes | M22: Anil reheated yesterday’s leftovers and sighed at the failed build from last night // software engineer // lunch // negative // orange | N22: expected | O22: no | P22: Looking at the pattern from the examples: **Pattern Analysis:** - Each example combines elements from different categories - The fruit assignment follows a rotating pattern based on which elements are combined **Breaking down Anil's scenario:** 1. **"reheated yesterday's leftovers"** → relates to food/meal → matches the breakfast/lunch/snack category - Leftovers suggest a simple meal (like Roy's oatmeal) → **breakfast pattern → apple** 2. **"sighed at the failed build from last night"** → relates to work context - "failed build" is a software engineering term → matches Chirak (Tester/software engineer) → **orange** - Failed build implies something went wrong → matches negative sentiment (like Air industry losses) → **orange** 3. **Combining the elements:** - Food aspect + Software engineering context + Negative emotion - breakfast (apple) + software engineer (orange) + negative (orange) **[result: lunch // software engineer // negative // orange]** The dominant element is **orange** (appearing in both the profession and sentiment), and the scenario describes Anil as a software professional having a disappointing meal during a work situation. | Q22: expected | S22: Anil reheated yesterday’s leftovers and sighed at the failed build from last night → **Tester / software engineer // snack // negative // orange** ### Resolved categories - **Profession/category**: “failed build” suggests **Tester / software engineer** - **Meal/time**: “reheated yesterday’s leftovers” most closely fits **snack** - **Sentiment/outcome**: “sighed” + “failed build” indicates **negative** - **Final mapping**: all three point to **orange** ### Final **Anil is a Tester / software engineer // snack // negative // orange** | T22: expected | U22: no | V22: Hello! Let me analyze the sentence about Anil: --- **"Anil reheated yesterday's leftovers and sighed at the failed build from last night"** Breaking it down: | Part | Category | Fruit | |------|----------|-------| | "reheated yesterday's leftovers" | meal / breakfast-lunch-snack | 🍐 **pear** (snack / leftover / informal eating) | | "sighed at the failed build" | software engineer / tester | 🍊 **orange** (Tester / software engineer) | | "failed build / sighed" | negative sentiment | 🍊 **orange** (negative) | --- ### ✅ Final Result: | Dimension | Resolution | Fruit | |-----------|------------|-------| | Profession | Software Engineer / Tester | 🍊 Orange | | Meal | Snack (informal/leftover) | 🍐 Pear | | Sentiment | Negative (sighed, failed) | 🍊 Orange | > **Dominant Final: 🍊 Orange** (2/3 signals align to orange) --- **Anil = Orange** — A software/tester professional, having an informal meal, in a negative state of mind. | W22: expected | X22: yes | Y22: =LEN(D22)+LEN(E22) -> 635
A23: Compound | B23: Mixed | C23: [result: each category resolved, final] | D23: Roel is an football player // sportsman // apple Chirak is a Tester // software engineer // orange Sophie is works in guitar band // artist // pear Roy ate oats meal in the morning // breakfast // apple Sita cooks biryani for afternoon // lunch // orange Mike like chips & coffee in the evening // snack // pear Rocky received 5% bonus during end year // positive // apple Air industry went into losses during covid // negative // orange James project completed with no loss & no profit // neutral // pear [result: each category resolved, final] | E23: Chloe skipped breakfast and felt groggy debugging a memory leak // | F23: orange, apple, orange | G23: Let's break down your input and resolve the categories as per your examples: ### Categories Observed: 1. **Person/Profession/Associated Fruit:** - Roel: football player // sportsman // **apple** - Chirak: Tester // software engineer // **orange** - Sophie: works in guitar band // artist // **pear** 2. **Person/Food/Time of Day/Associated Fruit:** - Roy: ate oats meal in the morning // breakfast // **apple** - Sita: cooks biryani for afternoon // lunch // **orange** - Mike: likes chips & coffee in the evening // snack // **pear** 3. **Scenario/Sentiment/Associated Fruit:** - Rocky: received 5% bonus during end year // positive // **apple** - Air industry: went into losses during covid // negative // **orange** - James: project completed with no loss & no profit // neutral // **pear** --- Now, let's analyze your input: > Chloe skipped breakfast and felt groggy debugging a memory leak // - **Person:** Chloe - **Action:** skipped breakfast, debugging a memory leak - **Profession:** Likely software engineer/tester (debugging memory leak) - **Food/Time:** Skipped breakfast (morning) - **Sentiment:** Negative (felt groggy) - **Associated Fruit:** Based on patterns: - Software engineer/tester → **orange** - Skipped breakfast (negative morning experience) → **orange** - Negative sentiment → **orange** ### [Final Result] **Chloe skipped breakfast and felt groggy debugging a memory leak // negative // orange** #### Each category resolved: - **Profession:** Software engineer/tester - **Time/Food:** Skipped breakfast (morning) - **Sentiment:** Negative (felt groggy) - **Fruit:** Orange Let me know if you want further breakdown or have more examples! | H23: expected | I23: yes | J23: Hello! Looking at your pattern, I need to analyze Chloe's situation across the three categories you've established: **Category 1 (Person Type):** - apple: sportsman/football player - orange: software engineer/tester - pear: artist/musician **Category 2 (Activity/Time):** - apple: breakfast/morning - orange: lunch/afternoon - pear: snack/evening **Category 3 (Sentiment):** - apple: positive - orange: negative - pear: neutral For "Chloe skipped breakfast and felt groggy debugging a memory leak": - **Person Type**: Debugging a memory leak indicates she's a software engineer → **orange** - **Activity/Time**: She skipped breakfast (morning meal) → **apple** - **Sentiment**: Felt groggy and dealing with problems → **negative** → **orange** **Result: orange, apple, orange** | K23: expected | L23: yes | M23: - Role: software engineer // orange - Meal: breakfast // apple - Sentiment: negative // orange | N23: expected | O23: no | P23: Looking at the pattern, I need to categorize Chloe's statement across three dimensions: **Chloe skipped breakfast and felt groggy debugging a memory leak** 1. **Profession/Role**: "debugging a memory leak" → **software engineer** (like Chirak) 2. **Meal/Time**: "skipped breakfast" → **breakfast** (like Roy) 3. **Sentiment**: "felt groggy" (negative feeling/experience) → **negative** (like the air industry example) **Result: software engineer // breakfast // negative → orange // apple // orange** Or if you want the final single category (following the mapping where each gets a fruit): **orange** (taking the middle category as the primary classifier, similar to how the examples seem weighted) | Q23: expected | S23: Here’s the resolved classification for the final line: **Chloe skipped breakfast and felt groggy debugging a memory leak** - **Category 1:** **software engineer / Tester-type** → **orange** - “debugging a memory leak” points to a software/testing/engineering context. - **Category 2:** **breakfast** → **apple** - “skipped breakfast” clearly maps to the meal category as breakfast. - **Category 3:** **negative** → **orange** - “felt groggy” indicates a negative outcome/state. ## Final **Chloe skipped breakfast and felt groggy debugging a memory leak // software engineer // breakfast // negative // orange, apple, orange** | T23: expected | U23: no | V23: I'll analyze Chloe's sentence across all three category frameworks: --- **Category 1: Person Type** - Chloe is **debugging a memory leak** → software/technical work - → **Tester // Software Engineer** → 🍊 **orange** --- **Category 2: Meal Time** - Chloe **skipped breakfast** → morning meal reference - → **Breakfast** → 🍎 **apple** --- **Category 3: Sentiment** - **Skipped breakfast + felt groggy** → negative experience/outcome - → **Negative** → 🍊 **orange** --- **[Result: each category resolved, final]** | Category | Label | Fruit | |---|---|---| | Person Type | Software Engineer / Tester | 🍊 Orange | | Meal Time | Breakfast | 🍎 Apple | | Sentiment | Negative | 🍊 Orange | **Final Summary:** `orange // apple // orange` | W23: expected | X23: yes | Y23: =LEN(D23)+LEN(E23) -> 616
A24: Compound | B24: Mixed | C24: [result: each category resolved, final] | D24: Roel is an football player // sportsman // apple Chirak is a Tester // software engineer // orange Sophie is works in guitar band // artist // pear Roy ate oats meal in the morning // breakfast // apple Sita cooks biryani for afternoon // lunch // orange Mike like chips & coffee in the evening // snack // pear Rocky received 5% bonus during end year // positive // apple Air industry went into losses during covid // negative // orange James project completed with no loss & no profit // neutral // pear [result: each category resolved, final] | E24: Omar spilled his cereal while rushing to fix a server outage // | F24: orange, apple, orange | G24: Let's break down the pattern: - There are three categories, each with three examples, all mapped to an object: apple, orange, pear. - Each example has a main subject, a profession or activity, and a key detail. Let's identify the categories: **Category 1: Person and Profession/Role** - Roel: football player, sportsman → apple - Chirak: Tester, software engineer → orange - Sophie: works in guitar band, artist → pear **Category 2: Food/Eating Context** - Roy: oats meal in the morning, breakfast → apple - Sita: cooks biryani for afternoon, lunch → orange - Mike: chips & coffee in the evening, snack → pear **Category 3: Outcome/Result** - Rocky: 5% bonus during end year, positive → apple - Air industry: losses during covid, negative → orange - James: no loss & no profit, neutral → pear Now, for your query: > Omar spilled his cereal while rushing to fix a server outage Let's analyze Omar's situation: - Omar: spilled his cereal (context: likely breakfast food) - Rushing to fix a server outage (profession: likely IT, software engineer) - No explicit outcome, but seems like a neutral or slightly negative situation (spilled cereal, but not a disaster) Now, let's map Omar to the above categories: - Profession: software engineer → orange (from Chirak's example) - Food context: cereal in the morning → breakfast → apple (from Roy's example) - Outcome: spilled cereal, but not a big loss, perhaps neutral or negative → orange or pear Given that the main action is "rushing to fix a server outage" (software engineer context), and tying back to Chirak (software engineer = orange), the best fit is: **Omar → orange** **Final Answer:** Omar spilled his cereal while rushing to fix a server outage // Tester // software engineer // orange or, more simply: **orange** | H24: expected | I24: yes | J24: Looking at the pattern in your examples: Each entry has three parts: 1. A description/scenario 2. A category classification 3. A fruit assignment The categories are: - **Person types**: sportsman, software engineer, artist - **Meal times**: breakfast, lunch, snack - **Outcomes**: positive, negative, neutral The fruits cycle through: apple, orange, pear For Omar's scenario: "Omar spilled his cereal while rushing to fix a server outage" - **Person type**: software engineer (fixing server outage indicates tech role) - **Meal context**: breakfast (cereal is typically a breakfast food) - **Outcome**: negative (spilling cereal while rushing is an unfortunate/stressful situation) Following the fruit pattern (next in sequence would be orange): **Omar spilled his cereal while rushing to fix a server outage // software engineer, breakfast, negative // orange** | K24: expected | L24: yes | M24: Omar spilled his cereal while rushing to fix a server outage // software engineer // breakfast // negative // orange | N24: expected | O24: no | P24: Looking at the pattern in your examples: **Category 1 (Profession):** football player/sportsman, Tester/software engineer, guitar band/artist **Category 2 (Meal/Time):** breakfast, lunch, snack **Category 3 (Sentiment):** positive, negative, neutral For Omar's situation: - **Profession:** software engineer (fixing a server outage) - **Meal/Time:** breakfast (cereal is a breakfast food) - **Sentiment:** negative (spilling cereal while rushing indicates stress/mishap) **Result:** orange | Q24: expected | S24: Omar spilled his cereal while rushing to fix a server outage // breakfast // orange | T24: expected | U24: no | V24: Looking at the patterns: **Omar spilled his cereal while rushing to fix a server outage** Breaking it down: - **Cereal spilled while rushing** → breakfast // **apple** - **Fix a server outage** → software engineer // **orange** - **Rushing + spilling = things going wrong** → negative // **orange** --- **[result: each category resolved, final]** | Category | Match | Fruit | |---|---|---| | Meal/Time | Breakfast (cereal) | 🍎 apple | | Profession | Software Engineer (server outage) | 🍊 orange | | Sentiment | Negative (spilled, rushing, outage) | 🍊 orange | **Final: apple, orange, orange** | W24: expected | X24: yes | Y24: =LEN(D24)+LEN(E24) -> 613
A25: Compound | B25: Mixed | C25: [result: each category resolved, final] | D25: Roel is an football player // sportsman // apple Chirak is a Tester // software engineer // orange Sophie is works in guitar band // artist // pear Roy ate oats meal in the morning // breakfast // apple Sita cooks biryani for afternoon // lunch // orange Mike like chips & coffee in the evening // snack // pear Rocky received 5% bonus during end year // positive // apple Air industry went into losses during covid // negative // orange James project completed with no loss & no profit // neutral // pear [result: each category resolved, final] | E25: Leila grabbed cold toast, frustrated by a persistent syntax error // | F25: orange, apple, orange | G25: Let's break down the pattern in your examples: Each set has three lines, and each line has three elements: 1. **Person** (or entity) 2. **Context** (occupation, meal, event, etc.) 3. **Category** (apple, orange, pear) For each group, there is a mapping: - First line → apple - Second line → orange - Third line → pear Your query: > Leila grabbed cold toast, frustrated by a persistent syntax error Let's resolve each field: - **Person:** Leila - **Action/context:** grabbed cold toast, frustrated by a persistent syntax error To map this to the category: - "Grabbed cold toast" suggests a meal (likely breakfast, based on similar context as Roy's "oats meal in the morning"). - "Frustrated by a persistent syntax error" suggests a negative or challenging outcome (similar to "Air industry went into losses during covid" which is negative and maps to orange). However, since in your previous sets, the context and category are determined by position/order, and "Leila" is a new entry, let's see: - In all examples, the first line is apple, second is orange, third is pear. If Leila's line is presented as a new first, second, or third line in a new set, it would get apple, orange, or pear accordingly. But you wrote "[result: each category resolved, final] Leila grabbed cold toast, frustrated by a persistent syntax error //", suggesting you want the category resolved. **Final answer:** Since "frustrated by a persistent syntax error" is a negative context (like Air industry/covid, which mapped to orange), and cold toast for breakfast matches the meal pattern, the correct category is: **orange** So, the resolved line would be: **Leila grabbed cold toast, frustrated by a persistent syntax error // orange** | H25: expected | I25: yes | J25: Looking at the pattern in your examples, I can see each entry follows the format: [Person/situation] // [category] // [fruit assignment] The categories are: - Profession: apple, orange, pear - Meal timing: apple (morning/breakfast), orange (afternoon/lunch), pear (evening/snack) - Sentiment: apple (positive), orange (negative), pear (neutral) For "Leila grabbed cold toast, frustrated by a persistent syntax error": - **Meal timing**: Cold toast = breakfast = apple - **Sentiment**: Frustrated = negative = orange - **Profession**: Syntax error suggests programming/software = orange **Result: Leila grabbed cold toast, frustrated by a persistent syntax error // breakfast, negative, programmer // apple, orange, orange** | K25: expected | L25: yes | M25: Leila grabbed cold toast, frustrated by a persistent syntax error // software engineer // orange Leila grabbed cold toast, frustrated by a persistent syntax error // breakfast // apple Leila grabbed cold toast, frustrated by a persistent syntax error // negative // orange Leila grabbed cold toast, frustrated by a persistent syntax error // final // orange | N25: expected | O25: no | P25: Looking at the pattern, I need to categorize Leila's statement across three dimensions: **Leila grabbed cold toast, frustrated by a persistent syntax error** 1. **Profession/Role**: "persistent syntax error" indicates she's dealing with code → **software engineer** → **orange** 2. **Meal/Time of day**: "grabbed cold toast" (a quick morning meal) → **breakfast** → **apple** 3. **Sentiment**: "frustrated" indicates a negative emotion → **negative** → **orange** **Result: breakfast // negative // orange-apple-orange** Or if you want just the final fruit mapping: **orange** (since software engineer and negative both point to orange, with breakfast as apple - orange appears twice) | Q25: expected | S25: Leila grabbed cold toast, frustrated by a persistent syntax error // breakfast // negative // software engineer | T25: confused | U25: no | V25: Hello! Let me analyze Leila's situation across the three categories: --- **Person Category:** Leila is working with code ("syntax error") → **software engineer** // **orange** **Meal/Time Category:** She grabbed "cold toast" (a breakfast item, eaten hastily) → **breakfast** // **apple** **Sentiment Category:** "Frustrated" + dealing with an error = negative outcome feeling → **negative** // **orange** --- **[result: each category resolved, final]** `Leila grabbed cold toast, frustrated by a persistent syntax error // software engineer, breakfast, negative // orange, apple, orange` | W25: expected | X25: yes | Y25: =LEN(D25)+LEN(E25) -> 618
A26: Compound | B26: Mixed | C26: [result: each category resolved, final] | D26: Roel is an football player // sportsman // apple Chirak is a Tester // software engineer // orange Sophie is works in guitar band // artist // pear Roy ate oats meal in the morning // breakfast // apple Sita cooks biryani for afternoon // lunch // orange Mike like chips & coffee in the evening // snack // pear Rocky received 5% bonus during end year // positive // apple Air industry went into losses during covid // negative // orange James project completed with no loss & no profit // neutral // pear [result: each category resolved, final] | E26: Theo burned his omelet and arrived late to the code review // | F26: orange, apple, orange | G26: Let's resolve the categories based on your previous patterns: **Pattern Explanation:** Each entry is mapped to three categories: 1. **Person/Profession:** Who or what is involved. 2. **Context/Type:** The situation type (sports, meal, sentiment, etc.). 3. **Fruit:** A mapped fruit (apple, orange, pear). Let's analyze Theo's sentence: "Theo burned his omelet and arrived late to the code review." - **Person/Profession:** Theo (Possible profession: software engineer or developer, given the code review context) - **Context/Type:** Negative (burned omelet and arrived late—both negative outcomes) - **Fruit (mapping):** Let's see the pattern: - "Tester // software engineer" → orange - "Sita cooks biryani for afternoon // lunch" → orange - "Air industry went into losses during covid // negative" → orange Negative situations are mapped to **orange**. **Final Resolved Categories:** Theo // software engineer // negative // orange **Final Answer:** Theo is a software engineer who had a negative experience (burned his omelet and arrived late to the code review) — orange. | H26: expected | I26: yes | J26: Looking at the pattern in your examples, I can see three categories being established: **Category 1 (apple):** Person descriptions/professions **Category 2 (orange):** Meal/time descriptions **Category 3 (pear):** Outcome descriptions For "Theo burned his omelet and arrived late to the code review": - **Person/profession:** Theo (appears to be a developer/programmer based on "code review") - **Meal/time context:** burned omelet (breakfast/morning meal) - **Outcome:** negative (burning food and being late are both negative events) **Result:** Theo // developer // apple, burned omelet // breakfast // orange, negative outcome // negative // pear | K26: unexpected | L26: yes | M26: - software engineer // orange - breakfast // apple - negative // orange | N26: expected | O26: no | P26: Looking at the pattern, I need to classify Theo's situation across three categories: **Category 1 - Profession/Role:** - "code review" suggests **software engineer** → **orange** **Category 2 - Time/Meal:** - "burned his omelet" (breakfast food) and "morning" (code reviews typically happen during work hours) → **breakfast** → **apple** **Category 3 - Sentiment:** - "burned" and "arrived late" are both negative events → **negative** → **orange** **[result: software engineer // breakfast // negative → orange // apple // orange]** Or if you want the final single classification, the dominant category is **orange** (appears twice). | Q26: expected | S26: Theo burned his omelet and arrived late to the code review // breakfast // orange Final resolved categories: - Person/role: - Roel → sportsman - Chirak → software engineer - Sophie → artist - Meal/time: - Roy → breakfast - Sita → lunch - Mike → snack - Sentiment/outcome: - Rocky → positive - Air industry → negative - James project → neutral Final: - Theo burned his omelet and arrived late to the code review → breakfast, orange | T26: expected | U26: yes | V26: Hello! Let me analyze Theo's situation: "Theo burned his omelet and arrived late to the code review" Breaking it down: - **Burned his omelet** → breakfast (morning meal) → **apple** - **Arrived late to the code review** → software/work related → **orange** (tester/engineer) - **Late + burned omelet** → negative outcome → **orange** (negative) **[result: each category resolved, final]** - **Profession/Role** → Software Engineer // **orange** - **Meal/Time** → Breakfast // **apple** - **Outcome** → Negative // **orange** **Final dominant result → orange/apple** ⚠️ | W26: expected | X26: yes | Y26: =LEN(D26)+LEN(E26) -> 611
A27: Compound | B27: Mixed | C27: [result: each category resolved, final] | D27: Roel is an football player // sportsman // apple Chirak is a Tester // software engineer // orange Sophie is works in guitar band // artist // pear Roy ate oats meal in the morning // breakfast // apple Sita cooks biryani for afternoon // lunch // orange Mike like chips & coffee in the evening // snack // pear Rocky received 5% bonus during end year // positive // apple Air industry went into losses during covid // negative // orange James project completed with no loss & no profit // neutral // pear [result: each category resolved, final] | E27: Anil had oatmeal before logging in to review pull requests // | F27: orange, apple, pear | G27: Let's analyze the pattern in your data: Each row contains three pieces of information, each linked to a "fruit" keyword (apple, orange, pear), and each category (person/profession, meal/time, event/sentiment) aligns with the fruit: - apple = first entity in each set - orange = second entity in each set - pear = third entity in each set For Anil: - "had oatmeal before logging in to review pull requests" - Oatmeal is similar to Roy's "ate oats meal in the morning" (breakfast, apple category) - "review pull requests" relates to testing/software engineer (Chirak, orange) - But meal is before work, so maps more to Roy's scenario (apple) Mapping: - Roel // football player // apple - Roy // oats meal in the morning // breakfast // apple - Rocky // 5% bonus // positive // apple **Anil had oatmeal before logging in to review pull requests** - Breakfast (oatmeal) => apple - Activity: review pull requests (software context) => orange (but this is secondary, as the primary event is the breakfast) - Sentiment: Implied positivity (starting the day with breakfast, ready for work) => apple ## [result: apple] **Final Answer:** Anil's scenario maps to the **apple category**. | H27: unexpected | I27: yes | J27: Hello! Looking at your pattern, I can see you're categorizing items across three dimensions: 1. **Person/Profession**: sportsman, software engineer, artist 2. **Activity/Context**: breakfast, lunch, snack 3. **Outcome/Sentiment**: positive, negative, neutral 4. **Final marker**: apple, orange, pear For your example: "Anil had oatmeal before logging in to review pull requests" Following the pattern: - **Anil** = software engineer (logging in to review pull requests indicates tech work) - **oatmeal** = breakfast (like Roy's oats meal) - **review pull requests** = neutral (routine work activity, neither clearly positive nor negative) **Result**: breakfast // software engineer // neutral // orange Is this the pattern you were looking for me to identify and complete? | K27: expected | L27: yes | M27: Anil had oatmeal before logging in to review pull requests // breakfast // apple Anil had oatmeal before logging in to review pull requests // software engineer // orange Anil had oatmeal before logging in to review pull requests // neutral // pear | N27: expected | O27: no | P27: Looking at the pattern: **Category 1 (Person type):** - apple = sportsman - orange = software engineer - pear = artist **Category 2 (Meal time):** - apple = breakfast - orange = lunch - pear = snack **Category 3 (Sentiment):** - apple = positive - orange = negative - pear = neutral **Anil had oatmeal before logging in to review pull requests //** - **oatmeal** = breakfast = **apple** - **review pull requests** = software engineer = **orange** - **completed review** (implied neutral task) = **pear** **Result: apple // orange // pear** Or if you want the categories spelled out: **breakfast // software engineer // neutral** | Q27: expected | R27: yes | S27: Anil had oatmeal before logging in to review pull requests → **breakfast // software engineer // apple** **Resolved categories:** - **Meal time:** oatmeal in the morning/before work → **breakfast** - **Profession:** review pull requests → **software engineer** - **Final label:** breakfast maps to **apple**, software engineer maps to **orange** in examples, but requested format suggests one final resolved mapping. Based on the first matching category pattern from the examples, **breakfast → apple** **Final:** **breakfast // software engineer // apple** | T27: expected | U27: no | V27: Hello! Let me analyze Anil's statement: **"Anil had oatmeal before logging in to review pull requests"** Breaking it down: | Element | Match | Category | |---|---|---| | "had oatmeal" | Roy ate oats meal in the morning → **breakfast** | 🍎 apple | | "logging in to review pull requests" | Chirak is a Tester // software engineer → **software engineer** | 🍊 orange | --- **Result:** > Anil had oatmeal before logging in to review pull requests > // **breakfast** // **software engineer** // **apple + orange** --- **Final Resolved Categories:** - 🍎 **Apple** → Breakfast (oatmeal) - 🍊 **Orange** → Software Engineer (pull requests = coding/testing activity) - 🍐 **Pear** → *(not triggered in this statement)* | W27: expected | X27: yes | Y27: =LEN(D27)+LEN(E27) -> 611
A28: Compound | B28: Mixed | C28: [result: each category resolved, final] | D28: Roel is an football player // sportsman // apple Chirak is a Tester // software engineer // orange Sophie is works in guitar band // artist // pear Roy ate oats meal in the morning // breakfast // apple Sita cooks biryani for afternoon // lunch // orange Mike like chips & coffee in the evening // snack // pear Rocky received 5% bonus during end year // positive // apple Air industry went into losses during covid // negative // orange James project completed with no loss & no profit // neutral // pear [result: each category resolved, final] | E28: Chloe brewed tea and read documentation while having toast // | F28: orange, apple, pear | G28: Certainly! Let's resolve the category for Chloe based on the given patterns. Let's analyze the categories: **1. First Category: Profession / Role** - Roel: football player // sportsman // apple - Chirak: Tester // software engineer // orange - Sophie: works in guitar band // artist // pear **2. Second Category: Meal / Time** - Roy: oats meal in the morning // breakfast // apple - Sita: biryani for afternoon // lunch // orange - Mike: chips & coffee in the evening // snack // pear **3. Third Category: Sentiment / Outcome** - Rocky: 5% bonus // positive // apple - Air industry: losses // negative // orange - James: no loss & no profit // neutral // pear **Each row corresponds to a color/fruit:** - apple: Roel, Roy, Rocky - orange: Chirak, Sita, Air industry - pear: Sophie, Mike, James Now, Chloe's sentence is: > Chloe brewed tea and read documentation while having toast Let's break it down: - Brewed tea and read documentation (activity, possibly work-related) - Having toast (food, can be associated with breakfast) Let's try to fit Chloe into each category: ### 1. Profession / Activity: - Roel: sportsman - Chirak: software engineer - Sophie: artist - **Chloe:** If she's reading documentation, that's often associated with a software/technical field. So, "Tester // software engineer" (orange) ### 2. Meal / Time: - Roy: breakfast - Sita: lunch - Mike: snack - **Chloe:** Having toast (typically breakfast food), so "breakfast" (apple) ### 3. Sentiment / Outcome: - Rocky: positive - Air industry: negative - James: neutral - **Chloe:** No explicit sentiment, but reading documentation and having toast suggests a neutral or routine activity, so "neutral" (pear) ### Fruit/Color Assignment: Each person fits only once into each fruit/color: - apple: Roel, Roy, Rocky - orange: Chirak, Sita, Air industry - pear: Sophie, Mike, James Since Chloe is a new entry, and for "each category resolved, final", let's assign Chloe consistently in one of the categories (as per the previous patterns): **Chloe brewed tea and read documentation while having toast // Tester // breakfast // neutral // orange** **Final assignment for Chloe:** - **Profession/Role:** Tester // software engineer (orange) - **Meal/Time:** breakfast (apple) - **Sentiment/Outcome:** neutral (pear) - **Fruit/Color:** orange (following the mapping for Tester/Software engineer) **So, resolved result:** **Chloe brewed tea and read documentation while having toast // Tester // breakfast // neutral // orange** Let me know if you want this in a different format or if you have more items to categorize! | H28: expected | I28: yes | J28: Hello! Looking at your pattern, I can see you're categorizing items across three dimensions: 1. **Person/Role**: sportsman, software engineer, artist 2. **Activity/Context**: breakfast, lunch, snack 3. **Outcome/Sentiment**: positive, negative, neutral 4. **Final assignment**: apple, orange, pear Following your established pattern: **Chloe brewed tea and read documentation while having toast //** - **breakfast** (tea and toast indicates morning meal) - **positive** (productive activity - brewing tea, reading documentation, having food) - **apple** (following the pattern: positive + breakfast = apple) The activity suggests someone starting their day productively with documentation review, which fits the positive/apple category like Roy's oats meal breakfast and Rocky's bonus. | K28: unexpected | L28: yes | M28: Final result: - Fruit tag: apple - Meal: breakfast - Occupation category: sportsman - Sentiment: positive Completed line: Chloe brewed tea and read documentation while having toast // breakfast // apple | N28: expected | O28: no | P28: Looking at the pattern, I need to categorize Chloe's activity across three dimensions: **Chloe brewed tea and read documentation while having toast** 1. **Profession/Role category**: Reading documentation suggests **software engineer** (like Chirak) 2. **Meal/Time category**: Tea and toast is a typical **breakfast** (like Roy) 3. **Sentiment category**: This is a neutral, routine activity with no particular positive or negative outcome, so **neutral** (like James) **Result: software engineer // breakfast // neutral** Or using the fruit notation: **orange // apple // pear** | Q28: expected | R28: yes | S28: Chloe brewed tea and read documentation while having toast // software engineer // breakfast // neutral | T28: confused | U28: no | V28: Hello! Let me analyze Chloe's sentence across all three categories: **People & Profession:** Chloe is doing a **relaxed/intellectual activity** (reading documentation) → - Not sports, not technical testing, not artistic → closest to **artist/leisure** // **pear** **Meal/Time of Day:** Tea + toast = light morning meal → **breakfast** // **apple** **Sentiment/Outcome:** Reading documentation + brewing tea = calm, productive, no negative or positive extreme → **neutral** // **pear** --- **Result:** > Chloe brewed tea and read documentation while having toast > // **breakfast** // **neutral** // **pear** 🍐 | W28: expected | X28: yes | Y28: =LEN(D28)+LEN(E28) -> 611
A29: Compound | B29: Mixed | C29: [result: each category resolved, final] | D29: Roel is an football player // sportsman // apple Chirak is a Tester // software engineer // orange Sophie is works in guitar band // artist // pear Roy ate oats meal in the morning // breakfast // apple Sita cooks biryani for afternoon // lunch // orange Mike like chips & coffee in the evening // snack // pear Rocky received 5% bonus during end year // positive // apple Air industry went into losses during covid // negative // orange James project completed with no loss & no profit // neutral // pear [result: each category resolved, final] | E29: Omar poured orange juice while checking his email notifications // | F29: orange, apple, pear | G29: Based on your format, let's break down Omar's scenario according to the three categories: 1. **Action/Profession/Context**: Omar poured orange juice while checking his email notifications - This suggests a modern work or leisure scenario, likely involving technology—perhaps a software engineer, office worker, or someone casually working. 2. **Category**: - From the context, pouring juice and checking emails sound like a neutral activity, not overtly positive or negative. However, since "orange" is involved directly, and in the previous examples, the fruit mapped to a category, let's check the mapping. 3. **Fruit Mapping**: - In previous examples, "apple," "orange," and "pear" are mapped to different people and situations. - "Orange" was associated with Chirak (Tester // software engineer), Sita (lunch), and air industry (negative). - The pattern seems to connect orange with the second item in each set. **Final Categorization for Omar:** - **Omar is a software engineer (or someone in a tech role) // Neutral (activity) // Orange** **Resolved format:** Omar is a software engineer // neutral // orange If you need a more specific label for his profession/activity, let me know! | H29: expected | I29: yes | J29: Looking at the pattern in your examples, I can see three categories being established: **Category 1 (apple):** People and their professions/roles **Category 2 (orange):** Activities and their timing/context **Category 3 (pear):** Situations and their emotional/financial outcomes For Omar's scenario: "Omar poured orange juice while checking his email notifications" This describes Omar (a person) performing an activity (pouring juice while checking emails), which fits most closely with **Category 2 (orange)** - activities and their timing/context. **Result: orange** | K29: expected | L29: yes | M29: Omar poured orange juice while checking his email notifications // software engineer // orange Omar poured orange juice while checking his email notifications // breakfast // apple Omar poured orange juice while checking his email notifications // neutral // pear | N29: expected | O29: no | P29: Looking at the pattern, I need to categorize Omar's statement across three dimensions: **Omar poured orange juice while checking his email notifications //** 1. **Person type/profession**: checking email notifications → office worker/professional → **software engineer** → **orange** 2. **Time of day/meal**: poured orange juice → typically a morning activity → **breakfast** → **apple** 3. **Sentiment**: checking email notifications (routine, neutral activity) → **neutral** → **pear** **Result: orange // apple // pear** | Q29: expected | R29: yes | S29: Omar poured orange juice while checking his email notifications → **drink // multitasking // orange** ## Final resolved categories - Roel → **sportsman // apple** - Chirak → **software engineer // orange** - Sophie → **artist // pear** - Roy → **breakfast // apple** - Sita → **lunch // orange** - Mike → **snack // pear** - Rocky → **positive // apple** - Air industry → **negative // orange** - James project → **neutral // pear** - Omar → **drink // multitasking // orange** | T29: expected | U29: yes | V29: Hello! Let me analyze Omar's sentence across all three categories: **People & Roles:** Omar is doing a casual activity (pouring juice + checking emails) → **sportsman / software engineer / artist** context → feels like everyday routine = **software engineer // orange** **Meal / Time of Day:** Orange juice is typically a **morning drink** → **breakfast // apple** **Sentiment:** The action is neutral — no gain, no loss, just a routine moment → **neutral // pear** --- **Result:** Omar poured orange juice while checking his email notifications // **breakfast // neutral // software engineer** // **apple + pear + orange** --- The interesting observation here is that **all three fruits appear**, making this a **fully balanced / complete** resolution across all category dimensions! 🍎🍊🍐 | W29: expected | X29: yes | Y29: =LEN(D29)+LEN(E29) -> 616
A30: Compound | B30: Mixed | C30: [result: each category resolved, final] | D30: Roel is an football player // sportsman // apple Chirak is a Tester // software engineer // orange Sophie is works in guitar band // artist // pear Roy ate oats meal in the morning // breakfast // apple Sita cooks biryani for afternoon // lunch // orange Mike like chips & coffee in the evening // snack // pear Rocky received 5% bonus during end year // positive // apple Air industry went into losses during covid // negative // orange James project completed with no loss & no profit // neutral // pear [result: each category resolved, final] | E30: Leila unpacked granola bars before heading to the coworking space // | F30: orange, apple, pear | G30: Let's break down the pattern in your examples: You have three categories, each with three items. Each item has: - A person or entity - An action or event - A summary label (e.g., sportsman, breakfast, positive) - A fruit (apple, orange, pear) Each fruit is associated with the position in the category: - First item: apple - Second item: orange - Third item: pear Let's analyze your new item: > Leila unpacked granola bars before heading to the coworking space // Let's assign it to each category and see which fits best: ### 1. Profession / Role - Football player // sportsman // apple - Tester // software engineer // orange - Guitar band // artist // pear "Unpacking granola bars before coworking" suggests a preparatory or practical action, possibly not clearly fitting the above roles. But if forced, coworking spaces are often used by software engineers or freelancers. So possibly: **software engineer // orange** ### 2. Meal / Time of Day - Oats meal in morning // breakfast // apple - Biryani for afternoon // lunch // orange - Chips & coffee in evening // snack // pear Granola bars before coworking could be breakfast or a snack, but since it's "before heading to," it likely happens in the morning: **breakfast // apple** ### 3. Outcome / Sentiment - 5% bonus // positive // apple - Losses during covid // negative // orange - No loss & no profit // neutral // pear Unpacking granola bars before work is neutral or positive (preparation, routine): **neutral // pear** or **positive // apple** Since you asked for "each category resolved, final," here's the final mapping for Leila: ### Final Answer - **Leila is a software engineer // orange** (if matching with profession) - **Leila ate breakfast // apple** (if matching with meal/time) - **Leila's action is neutral // pear** (if matching with sentiment/outcome) **Full resolved example:** Leila is a software engineer // breakfast // neutral // orange (orange is the fruit for the second item in each category; breakfast is the meal; software engineer is the role; neutral is the outcome most fitting routine actions) If you want to specify only one, please clarify which category you want to resolve! | H30: expected | I30: yes | J30: Hello! Looking at your pattern, I can see you're categorizing items across three dimensions: 1. **Person/Role**: Roel (football player/sportsman), Chirak (Tester/software engineer), Sophie (guitar band/artist) 2. **Activity/Context**: Roy (breakfast), Sita (lunch), Mike (snack) 3. **Sentiment/Outcome**: Rocky (positive), Air industry (negative), James (neutral) Each gets assigned to apple, orange, or pear respectively. For your new example: "Leila unpacked granola bars before heading to the coworking space" This appears to fit the **Activity/Context** category (like Roy, Sita, Mike) as it describes a food-related activity with timing context. Following your pattern, this would be classified as: **snack // pear** (Since unpacking granola bars suggests a snack-type food preparation, similar to Mike's chips & coffee scenario) | K30: confused | L30: yes | M30: Leila unpacked granola bars before heading to the coworking space // software engineer // orange Leila unpacked granola bars before heading to the coworking space // breakfast // apple Leila unpacked granola bars before heading to the coworking space // neutral // pear | N30: expected | O30: no | P30: Looking at the pattern, I need to categorize this sentence across three dimensions: 1. **Profession/Role**: breakfast/lunch/snack OR positive/negative/neutral 2. **Time/Sentiment**: breakfast/lunch/snack OR positive/negative/neutral 3. **Fruit**: apple/orange/pear Analyzing "Leila unpacked granola bars before heading to the coworking space": - **Granola bars** = a snack/breakfast food → **snack** (or could be breakfast, but granola bars are typically snacks) - **Sentiment** = neutral statement (just describing an action, no positive/negative connotation) → **neutral** - **Fruit pattern** = Following the rotation pattern (apple→orange→pear), this would be → **apple** **Result: snack // neutral // apple** | Q30: expected | R30: yes | S30: Leila unpacked granola bars before heading to the coworking space // snack // pear | T30: expected | U30: no | V30: I'll analyze Leila's statement across the three category frameworks: **Person → Role:** "heading to the coworking space" → suggests a **software engineer / tech worker** // Tester // **orange** **Food → Meal Time:** "granola bars" → a light, quick bite → **snack** // evening // **pear** **Event → Sentiment:** "unpacked granola bars before heading" → neutral, routine action → no loss/gain implied → **neutral** // **pear** --- **[Result: each category resolved, final]** Leila unpacked granola bars before heading to the coworking space // - **Role:** Tester / Software Engineer // 🟠 orange - **Meal:** Snack // 🍐 pear - **Sentiment:** Neutral // 🍐 pear **Dominant Pattern → 🍐 Pear / Orange blend** *(snack + neutral strongly align to pear; profession leans orange)* | W30: unexpected | X30: yes | Y30: =LEN(D30)+LEN(E30) -> 618
A31: Compound | B31: Mixed | C31: [result: each category resolved, final] | D31: Roel is an football player // sportsman // apple Chirak is a Tester // software engineer // orange Sophie is works in guitar band // artist // pear Roy ate oats meal in the morning // breakfast // apple Sita cooks biryani for afternoon // lunch // orange Mike like chips & coffee in the evening // snack // pear Rocky received 5% bonus during end year // positive // apple Air industry went into losses during covid // negative // orange James project completed with no loss & no profit // neutral // pear [result: each category resolved, final] | E31: Theo finished his sandwich while syncing with the dev team // | F31: orange, apple, pear | G31: Sure! Let's analyze the categories and resolve the final category for Theo based on the patterns in your examples. **1. Occupation // Profession // Fruit** - Roel: football player // sportsman // apple - Chirak: Tester // software engineer // orange - Sophie: works in guitar band // artist // pear **2. Food // Meal time // Fruit** - Roy: oats meal in the morning // breakfast // apple - Sita: cooks biryani for afternoon // lunch // orange - Mike: like chips & coffee in the evening // snack // pear **3. Event // Sentiment // Fruit** - Rocky: received 5% bonus during end year // positive // apple - Air industry: losses during covid // negative // orange - James: project completed with no loss & no profit // neutral // pear **Your query:** Theo finished his sandwich while syncing with the dev team // Let’s break it down: - **Activity:** Finished sandwich while syncing with dev team (eating + working with developers) - **From previous patterns:** - “Oats meal in the morning // breakfast // apple” - “Cooks biryani for afternoon // lunch // orange” - “Chips & coffee in the evening // snack // pear” “Sandwich” is a common lunch item, and “syncing with dev team” likely happens during a work lunch break. **So:** - **Meal time:** lunch - **Fruit:** Based on pattern: breakfast → apple, lunch → orange, snack → pear. **Final resolved category:** Theo finished his sandwich while syncing with the dev team // lunch // orange | H31: expected | I31: yes | J31: Looking at the pattern in your examples, I can see you're categorizing statements into three groups: **People/Professions:** - Roel (football player/sportsman) = apple - Chirak (Tester/software engineer) = orange - Sophie (guitar band/artist) = pear **Meals/Times:** - Roy (breakfast/oats) = apple - Sita (lunch/biryani) = orange - Mike (evening snack/chips & coffee) = pear **Outcomes:** - Rocky (positive/5% bonus) = apple - Air industry (negative/losses) = orange - James (neutral/no loss no profit) = pear For: "Theo finished his sandwich while syncing with the dev team" This contains: - **Person/Profession**: Theo (dev team member) = **orange** - **Meal**: sandwich = **apple** - **Outcome**: completed/finished = **apple** **Result: apple** (2 apple elements, 1 orange element - apple predominates) | K31: expected | L31: yes | M31: Theo finished his sandwich while syncing with the dev team // software engineer // orange Theo finished his sandwich while syncing with the dev team // lunch // orange Theo finished his sandwich while syncing with the dev team // neutral // pear final // orange | N31: unexpected | O31: no | P31: Looking at the pattern, I need to categorize Theo's statement across three dimensions: **Theo finished his sandwich while syncing with the dev team** 1. **Profession/Role**: "syncing with the dev team" indicates → **software engineer** → **orange** 2. **Meal/Time**: "finished his sandwich" suggests a casual meal, likely → **lunch** → **orange** 3. **Sentiment**: "finished" and "syncing" are neutral/routine activities, no positive or negative outcome → **neutral** → **pear** **Result: orange // orange // pear** | Q31: unexpected | R31: yes | S31: Theo finished his sandwich while syncing with the dev team // lunch // orange | T31: expected | U31: no | V31: Looking at the patterns: **Theo finished his sandwich while syncing with the dev team** - "finished his sandwich" → **snack/meal** → food activity - "syncing with the dev team" → **work/meeting** → professional activity Matching the pattern structure: **snack // neutral** And for the fruit: - apple = positive/first - orange = negative/second - pear = neutral/third **Result:** `snack // software/work // pear` Or following the **[result: each category resolved, final]** format: > Theo finished his sandwich while syncing with the dev team // **snack // neutral // pear** The sentence contains **two combined elements** (eating + working), making it a **neutral/mixed** activity, during what appears to be a **snack** break, resolving to **pear**. 🍐 | W31: expected | X31: yes | Y31: =LEN(D31)+LEN(E31) -> 611
A32: Compound | B32: Mixed | C32: [result: each category resolved, final] | D32: Roel is an football player // sportsman // apple Chirak is a Tester // software engineer // orange Sophie is works in guitar band // artist // pear Roy ate oats meal in the morning // breakfast // apple Sita cooks biryani for afternoon // lunch // orange Mike like chips & coffee in the evening // snack // pear Rocky received 5% bonus during end year // positive // apple Air industry went into losses during covid // negative // orange James project completed with no loss & no profit // neutral // pear [result: each category resolved, final] | E32: Biba felt inspired after enjoying her smoothie bowl and finishing a new violin piece // | F32: pear, apple, apple | G32: Sure! Let’s break down the categories first: **Category 1: Profession/Role // Personality // Fruit** - Roel: football player // sportsman // apple - Chirak: Tester // software engineer // orange - Sophie: works in guitar band // artist // pear **Category 2: Food/Meal // Time of day // Fruit** - Roy: oats meal in the morning // breakfast // apple - Sita: biryani for afternoon // lunch // orange - Mike: chips & coffee in the evening // snack // pear **Category 3: Situation // Sentiment // Fruit** - Rocky: 5% bonus during end year // positive // apple - Air industry: losses during covid // negative // orange - James: project completed with no loss & no profit // neutral // pear Each group links to a fruit: **apple, orange, pear**. Now, let's analyze Biba's statement: > Biba felt inspired after enjoying her smoothie bowl and finishing a new violin piece - Emotion: Inspired (positive) - Action: Finished a new violin piece (artist/musician) - Meal: Smoothie bowl (often breakfast/snack) Let's see which categories this matches: 1. **Profession/Role:** Artist (like Sophie, who is associated with pear) 2. **Meal/Time:** Smoothie bowl (commonly breakfast/snack; both Roy and Mike—apple/pear) 3. **Sentiment:** Inspired (positive, like Rocky—apple) But Sophie (artist) is pear, and "inspired" is positive (apple). The meal (smoothie bowl) is ambiguous but often breakfast/snack. **Resolution:** The most significant clue is the "violin piece" (artist), which matches Sophie's category (pear). Emotion is positive, but the role seems more defining in these examples. **Final result:** Biba is **pear** (artist category prevails). --- **[Result: Biba is associated with 'pear'. Each category resolved. Final.]** | H32: unexpected | I32: yes | J32: Looking at the pattern in your examples, I can see three categories being established: **Category 1 (apple):** Person types - football player/sportsman, breakfast, positive **Category 2 (orange):** Professional roles - software engineer, lunch, negative **Category 3 (pear):** Creative/leisure - artist, snack, neutral For "Biba felt inspired after enjoying her smoothie bowl and finishing a new violin piece": - **Person aspect**: Biba (violin player) → artist/musician = **pear** - **Food/time aspect**: smoothie bowl (healthy morning/snack food) = **pear** - **Sentiment aspect**: "felt inspired" (positive emotion) = **apple** Since 2 out of 3 elements point to **pear** (artist category, snack-type food) with the creative/artistic theme being dominant, the classification would be: **pear** | K32: unexpected | L32: yes | M32: Biba felt inspired after enjoying her smoothie bowl and finishing a new violin piece // artist // pear Biba felt inspired after enjoying her smoothie bowl and finishing a new violin piece // breakfast // apple Biba felt inspired after enjoying her smoothie bowl and finishing a new violin piece // positive // apple | N32: expected | O32: no | P32: Looking at the pattern, I need to classify Biba's statement across three categories: **Category 1 (Profession/Role):** - violin piece → **artist** // pear **Category 2 (Meal/Time):** - smoothie bowl → **breakfast** // apple **Category 3 (Sentiment):** - felt inspired → **positive** // apple **[result: each category resolved, final]** Biba felt inspired after enjoying her smoothie bowl and finishing a new violin piece // **artist // breakfast // positive** // **pear // apple // apple** | Q32: expected | S32: Biba felt inspired after enjoying her smoothie bowl and finishing a new violin piece // breakfast, artist, positive // apple | T32: expected | U32: no | V32: I'll analyze Biba's statement across all three categories: --- **Person & Role:** Biba finished a **violin piece** → relates to music/arts → **Artist // pear** --- **Meal/Time:** Biba enjoyed a **smoothie bowl** → light, healthy food → **Breakfast // apple** --- **Outcome:** Biba felt **inspired** → positive emotion/result → **Positive // apple** --- **[Result: each category resolved, final]** > **Biba // Artist / Breakfast / Positive // pear, apple, apple** | W32: expected | X32: yes | Y32: =LEN(D32)+LEN(E32) -> 637
